Workbook
Name ADM_D01: Emp_ADM[Name_AR]
Name ADM_D01: Emp_ADM[Name_AR]
Name ADM_D01: Emp_ADM[Name_AR]
Name All_D11: Emp_All[Name_AR]
Name All_D11: Emp_All[Name_AR]
Name All_D11: Emp_All[Name_AR]
Name CON_D03: Emp_CON[Name_AR]
Name CON_D03: Emp_CON[Name_AR]
Name CON_D03: Emp_CON[Name_AR]
Name DeptList: Lookups!$B$2:$B$11
Name ELE_D04: Emp_ELE[Name_AR]
Name ELE_D04: Emp_ELE[Name_AR]
Name ELE_D04: Emp_ELE[Name_AR]
Name EmpDepts: Master_Employee!$D$5:$D$30
Name EmpIDs: Master_Employee!$B$5:$B$30
Name EmpNames: Master_Employee!$H$5:$H$30
Name EmpStatus: Lookups!$F$2:$F$5
Name FIN_D02: Emp_FIN[Name_AR]
Name FIN_D02: Emp_FIN[Name_AR]
Name FIN_D02: Emp_FIN[Name_AR]
Name PayMethods: Lookups!$D$2:$D$4
Name PLM_D05: Emp_PLM[Name_AR]
Name PLM_D05: Emp_PLM[Name_AR]
Name PLM_D05: Emp_PLM[Name_AR]
Name ProjectList: Projects!$B$4:$B$70
Name ProjectNames: Projects!$C$4:$C$70
Name Slicer_Dept_Name: #N/A
Name Slicer_Emp_Status: #N/A
Name Slicer_Grade: #N/A
Name Slicer_Job_Title: #N/A
Name Slicer_Payment_Method: #N/A
Name Slicer_Project_Name: #N/A
Name Slicer_Supervisor: #N/A
Name STN_D06: Emp_STN[Name_AR]
Name STN_D06: Emp_STN[Name_AR]
Name STN_D06: Emp_STN[Name_AR]
Name SupvList: Master_Employee!$H$5:$H$30
Name Timeline_Month: #N/A
Name TransTypes: Lookups!$H$2:$H$5

Sheet Lookups
A1: Dept_ID | B1: Dept_Name | D1: Payment_Method | F1: Status | H1: Trans_Type
A2: ADM_D01 | B2: الإدارة | D2: كاش - Cash | F2: يعمل - Active | H2: سلف - Advance
A3: FIN_D02 | B3: التشطيبات | D3: بنك - Bank | F3: اجازة - Vacation | H3: خصم - Deduction
A4: CON_D03 | B4: الإنشاءات | D4: فودافون - Vodafone | F4: استقالة - Resigned | H4: بونص - Bonus
A5: ELE_D04 | B5: الكهرباء | F5: اجازة مرضية - Sick Leave | H5: زيادة - Addition
A6: PLM_D05 | B6: السباكة
A7: STN_D06 | B7: الحجر
A8: ALU_D07 | B8: الألمنيوم
A9: EQP_D08 | B9: المعدات
A10: CRP_D09 | B10: النجارة
A11: PTG_D10 | B11: الدهانات

Sheet HR_Dashboard

Sheet Project_Cost_Dashboard 

Sheet Payroll Analysis

Sheet Pivot_Tables
A1: Payroll Analysis
C2: Total Net Salary | F2: AVG Salary | G2: #EMP | AG2: HR Analysis
C3: Net Salary | D3: Max Salary | E3: Min Salary | F3: Avg Salary | G3: Selected Month Salary | H3: Previous Month Salary | I3: Difference Display | J3: Workers Count
C4: 12846.25 | D4: 2300 | E4: 1100 | F4: 1680.7812 | G4: 12846.25 | H4: 5366.25 | I4: ↑ 7,480 | J4: 8 | AI4: Total Employees | AJ4: #Department
C5: =GETPIVOTDATA("[Measures].[Net Salary]",$C$3) -> 12846.25 | D5: =GETPIVOTDATA("[Measures].[Max Salary]",$C$3) -> 2300 | E5: =GETPIVOTDATA("[Measures].[Min Salary]",$C$3) -> 1100 | F5: =GETPIVOTDATA("[Measures].[Avg Salary]",$C$3) -> 1680.7812 | G5: =GETPIVOTDATA("[Measures].[Selected Month Salary]",$C$3) -> 12846.25 | H5: =GETPIVOTDATA("[Measures].[Previous Month Salary]",$C$3) -> 5366.25 | I5: =GETPIVOTDATA("[Measures].[Difference Display]",$C$3) -> ↑ 7,480 | J5: =GETPIVOTDATA("[Measures].[Workers Count]",$C$3) -> 8 | O5: Salary by Dep | AI5: Employee Count | AJ5: Count of Dept_ID | AK5: Count of Project_ID | AL5: Count of Nationality
H6: hاعلى مهنة بتكلفني مرتبات | AG6: =GETPIVOTDATA("[Measures].[Employee Count]",$AI$5) -> 26 | AI6: 26 | AJ6: 14 | AK6: 67 | AL6: 26
D7: Salary by job title and #Job_title | O7: Row Labels | P7: Net Salary | W7: Row Labels | X7: Net Salary | AJ7: =GETPIVOTDATA("[Measures].[Count of Dept_ID 2]",$AJ$5) -> 14 | AK7: =GETPIVOTDATA("[Measures].[Count of Project_ID]",$AK$5) -> 67
A8: Row Labels | B8: Net Salary | G8: Row Labels | H8: Net Salary | O8: الإدارة | W8: (blank) | X8: -750 | AI8: Employee by Grade | AL8: Employees by Job Title | AO8: Employee By Status | AS8: Employee By Department | AV8: Employee By Sponsership | AZ8: Salary by Job Title
A9: Bank - بنك | B9: 4450.8333 | G9: مشرف_موقع | H9: 960.83333 | O9: ADM_D01 | P9: 2780 | W9: 46082 | X9: 5366.25 | AI9: Row Labels | AJ9: Count of Emp_ID | AL9: Row Labels | AM9: Count of Emp_ID | AO9: Row Labels | AP9: Count of Status_Code | AS9: Row Labels | AT9: Count of Emp_ID | AV9: Row Labels | AW9: Count of Emp_ID | AZ9: Row Labels | BA9: Sum of Total_Salary
A10: cash - نقدا | B10: 3900 | G10: عامل | H10: 1100 | O10: الإنشاءات | W10: 46113 | X10: 6730 | AI10: Manager | AJ10: 2 | AL10: فني عزل | AM10: 1 | AO10: New appointment - تعيين جديد | AP10: 1 | AS10: الإدارة | AT10: 6 | AV10: غير كفالة-NoSponsership | AW10: 8 | AZ10: Manager
A11: Vodafone - فودافون | B11: 4495.4167 | G11: مساعد كهربائي | H11: 1233.3333 | O11: CON_D03 | P11: 2795.4167 | W11: Grand Total | X11: 12846.25 | AI11: Supervisor | AJ11: 2 | AL11: سائق | AM11: 1 | AO11: vacation - إجازة | AP11: 3 | AS11: الإنشاءات | AT11: 10 | AV11: كفالة-Sponsership | AW11: 18 | AZ11: مشرف_موقع | BA11: 3200
A12: Grand Total | B12: 12846.25 | G12: صباغ | H12: 1437.5 | O12: التشطيبات | AI12: Worker | AJ12: 22 | AL12: فني بلاستر | AM12: 1 | AO12: works - يعمل | AP12: 22 | AS12: التشطيبات | AT12: 10 | AV12: Grand Total | AW12: 26 | AZ12: Supervisor
G13: فورمان | H13: 1680 | O13: FIN_D02 | P13: 7270.8333 | AI13: Grand Total | AJ13: 26 | AL13: معلم جبس بورد | AM13: 1 | AO13: Grand Total | AP13: 26 | AS13: Grand Total | AT13: 26 | AZ13: مشرف_موقع | BA13: 3400
G14: سائق | H14: 1934.5833 | O14: Grand Total | P14: 12846.25 | AL14: صباغ | AM14: 1 | AZ14: Worker
G15: عامل الثرى دى | H15: 4500 | AL15: فنى | AM15: 1 | AZ15: سائق | BA15: 1700
G16: Grand Total | H16: 12846.25 | AL16: معلم تشطيب | AM16: 1 | AZ16: سباك | BA16: 2600
AL17: فورمان | AM17: 2 | AZ17: صباغ | BA17: 1400
AL18: مساعد كهربائي | AM18: 2 | AZ18: عامل | BA18: 3500
AL19: عامل | AM19: 2 | AZ19: عامل الثرى دى | BA19: 4500
AL20: ناطور | AM20: 2 | AZ20: فنى | BA20: 2500
A21: Row Labels | B21: Net Salary | AL21: سباك | AM21: 2 | AZ21: فني بلاستر | BA21: 2500
A22: عبدالحكيم رستم انصاري | B22: 760.83333 | AL22: عامل الثرى دى | AM22: 2 | AZ22: فني عزل | BA22: 3500
A23: صلاح عبدالرحمن الحاج احمد | B23: 930 | AL23: كهربائي | AM23: 3 | AZ23: فورمان | BA23: 4000
A24: محمد اكبر صافي | B24: 1084.5833 | AL24: مشرف_موقع | AM24: 4 | AZ24: كهربائي | BA24: 5000
A25: محمد نور الأسلام | B25: 1450 | AL25: Grand Total | AM25: 26 | AZ25: مساعد كهربائي | BA25: 2700
A26: عبد الباسي عبد الرحمن اشير | B26: 1550 | AZ26: معلم تشطيب | BA26: 1700
A27: Grand Total | B27: 8775.4167 | AZ27: معلم جبس بورد | BA27: 1300
AZ28: ناطور | BA28: 3100
AZ29: Grand Total | BA29: 46600
AO30: Row Labels | AP30: Count of Emp_ID
AO31: إندونيسي – Indonesian | AP31: 1
AO32: أوغندي – Ugandan | AP32: 1
AO33: باكستاني – Pakistani | AP33: 4
AO34: تونسي – Tunisian | AP34: 2
AO35: فلبيني – Filipino | AP35: 2
AO36: مصري – Egyptian | AP36: 2
AO37: نيبالي – Nepali | AP37: 10
AO38: هندي – Indian | AP38: 4
AO39: Grand Total | AP39: 26
A48: Project Analysis
B49: Project Cost
B50: Project Cost | C50: Total Work Cost | D50: Workers Count | E50: Total Work Days | F50: Days per Worker | G50: Sum of Days_Work | H50: Sum of OT_Hrs | I50: Absent Days | J50: OT Cost | K50: Normal Cost | L50: Total Days | M50: Valid Worker | N50: OT per Worker | O50: Cost per Worker | P50: Projects per Employee
B51: 13596.25 | C51: 13596.25 | D51: 8 | E51: 235 | F51: 29.375 | G51: 235 | H51: 79 | I51: 3 | J51: 466.25 | K51: 13130 | L51: 235 | M51: 1 | N51: 9.875 | O51: 1699.5312 | P51: 26
B53: =GETPIVOTDATA("[Measures].[Project Cost]",$B$50) -> 13596.25 | C53: =GETPIVOTDATA("[Measures].[Total Work Cost]",$B$50) -> 13596.25 | D53: =GETPIVOTDATA("[Measures].[Workers Count]",$B$50) -> 8 | E53: =GETPIVOTDATA("[Measures].[Total Work Days]",$B$50) -> 235 | F53: =GETPIVOTDATA("[Measures].[Days per Worker]",$B$50) -> 29.375 | G53: =GETPIVOTDATA("[Measures].[Sum of Days_Work]",$B$50) -> 235 | H53: =GETPIVOTDATA("[Measures].[Sum of OT_Hrs]",$B$50) -> 79 | I53: =GETPIVOTDATA("[Measures].[Absent Days]",$B$50) -> 3 | J53: =GETPIVOTDATA("[Measures].[OT Cost]",$B$50) -> 466.25 | K53: =GETPIVOTDATA("[Measures].[Normal Cost]",$B$50) -> 13130 | P53: =GETPIVOTDATA("[Measures].[Projects per Employee]",$B$50) -> 26
N55: Row Labels | O55: Sum of Normal_Cost | P55: Sum of OT_Cost | AD55: Row Labels | AE55: Sum of Normal_Cost | AF55: Sum of OT_Cost
N56: الحجر | O56: 0 | P56: 0 | AD56: الحجر | AE56: 0 | AF56: 0
N57: (blank) | O57: 0 | P57: 0 | AD57: (blank) | AE57: 0 | AF57: 0
E58: Row Labels | F58: Sum of Normal_Cost | G58: Sum of OT_Cost | N58: حمد عايض حسين الاحبابي | O58: 93.333333 | P58: 0 | AD58: حمد عايض حسين الاحبابي | AE58: 93.333333 | AF58: 0
E59: ADM_D01 | F59: 2980 | G59: 0 | I59: Row Labels | J59: Workers Count | N59: هزاع مبارك الهاجري | O59: 160 | P59: 17.5 | AD59: هزاع مبارك الهاجري | AE59: 160 | AF59: 17.5
E60: CON_D03 | F60: 2950 | G60: 395.41667 | I60: صالح العذبة | J60: 1 | N60: سعد الدوسري | O60: 170 | P60: 0 | AD60: سعد الدوسري | AE60: 170 | AF60: 0
B61: project cost | E61: FIN_D02 | F61: 7200 | G61: 70.833333 | I61: سعيد صالح الجحيش | J61: 1 | N61: فهد ظافر القحطاني | O61: 173.33333 | P61: 0 | AD61: فهد ظافر القحطاني | AE61: 173.33333 | AF61: 0
E62: (blank) | F62: 0 | G62: 0 | I62: امل الشمري | J62: 1 | N62: جابر قحيز المري | O62: 186.66667 | P62: 20.833333 | AD62: جابر قحيز المري | AE62: 186.66667 | AF62: 20.833333
E63: Grand Total | F63: 13130 | G63: 466.25 | I63: جابر قحيز المري | J63: 1 | N63: سعود وعبدالرحمن ناقادان | O63: 206.66667 | P63: 0 | AD63: سعود وعبدالرحمن ناقادان | AE63: 206.66667 | AF63: 0
I64: جابر سالم الغواص | J64: 1 | N64: سعد عزران | O64: 240 | P64: 0 | AD64: سعد عزران | AE64: 240 | AF64: 0
I65: سعد الدوسري | J65: 1 | N65: امل الشمري | O65: 260 | P65: 0 | AD65: امل الشمري | AE65: 260 | AF65: 0
I66: عبدالرحمن نقدان | J66: 1 | N66: صالح العذبة | O66: 306.66667 | P66: 0 | AD66: صالح العذبة | AE66: 306.66667 | AF66: 0
B67: Department | C67: All | I67: سعود الأحبابي | J67: 1 | N67: نايف الموسى | O67: 433.33333 | P67: 0 | AD67: نايف الموسى | AE67: 433.33333 | AF67: 0
I68: عبدالهادي الماجد | J68: 1 | N68: ناصر الحايف | O68: 433.33333 | P68: 0 | AD68: ناصر الحايف | AE68: 433.33333 | AF68: 0
B69: Row Labels | C69: Project Cost | I69: نايف الموسى | J69: 1 | N69: عبد الهادي السهلي | O69: 460 | P69: 46.666667 | AD69: عبد الهادي السهلي | AE69: 460 | AF69: 46.666667
B70: امل الشمري | C70: 260 | I70: عمارة الدوسري | J70: 1 | N70: حمد المعاضيد | O70: 516.66667 | P70: 142.08333 | AD70: حمد المعاضيد | AE70: 516.66667 | AF70: 142.08333
B71: جابر سالم الغواص | C71: 660 | I71: سعد عزران | J71: 1 | N71: عبدالرحمن نقدان | O71: 540 | P71: 0 | AD71: عبدالرحمن نقدان | AE71: 540 | AF71: 0
B72: جابر قحيز المري | C72: 207.5 | I72: فهد ظافر القحطاني | J72: 1 | N72: عبدالعزيز قحيز المري | O72: 553.33333 | P72: 0 | AD72: عبدالعزيز قحيز المري | AE72: 553.33333 | AF72: 0
B73: حمد المعاضيد | C73: 658.75 | I73: حمد عايض حسين الاحبابي | J73: 1 | N73: سعيد صالح الجحيش | O73: 560 | P73: 12.5 | AD73: سعيد صالح الجحيش | AE73: 560 | AF73: 12.5
B74: حمد عايض حسين الاحبابي | C74: 93.333333 | I74: فيصل محمد العذبة | J74: 1 | N74: عبدالهادي الماجد | O74: 606.66667 | P74: 8.3333333 | AD74: عبدالهادي الماجد | AE74: 606.66667 | AF74: 8.3333333
B75: سعد الدوسري | C75: 170 | I75: سعود نقدان | J75: 1 | N75: سعود الفهد | O75: 636.66667 | P75: 32.5 | AD75: سعود الفهد | AE75: 636.66667 | AF75: 32.5
B76: سعد عزران | C76: 240 | I76: ناصر الحايف | J76: 1 | N76: جابر سالم الغواص | O76: 660 | P76: 0 | AD76: جابر سالم الغواص | AE76: 660 | AF76: 0
B77: سعود الأحبابي | C77: 690 | I77: عبد الهادي السهلي | J77: 2 | N77: سعود الأحبابي | O77: 690 | P77: 0 | AD77: سعود الأحبابي | AE77: 690 | AF77: 0
B78: سعود الفهد | C78: 669.16667 | I78: عبدالعزيز قحيز المري | J78: 2 | N78: سعود نقدان | O78: 733.33333 | P78: 0 | AD78: سعود نقدان | AE78: 733.33333 | AF78: 0
B79: سعود نقدان | C79: 733.33333 | I79: مصطفى | J79: 2 | N79: فيصل محمد العذبة | O79: 766.66667 | P79: 0 | AD79: فيصل محمد العذبة | AE79: 766.66667 | AF79: 0
B80: سعود وعبدالرحمن ناقادان | C80: 206.66667 | I80: سعود الفهد | J80: 2 | N80: عمارة الدوسري | O80: 806.66667 | P80: 0 | AD80: عمارة الدوسري | AE80: 806.66667 | AF80: 0
B81: سعيد صالح الجحيش | C81: 572.5 | I81: حمد المعاضيد | J81: 2 | N81: عمير راشد المري | O81: 830 | P81: 0 | AD81: عمير راشد المري | AE81: 830 | AF81: 0
... B84: عبدالرحمن نقدان | C84: 540 | I84: فهد ونواف الكربى | J84: 2 | N84: Grand Total | O84: 13130 | P84: 466.25 | AD84: Grand Total | AE84: 13130 | AF84: 466.25
B85: عبدالعزيز قحيز المري | C85: 553.33333 | I85: هزاع مبارك الهاجري | J85: 2
B86: عبدالهادي الماجد | C86: 615 | I86: Grand Total | J86: 8
B87: عمارة الدوسري | C87: 806.66667
B88: عمير راشد المري | C88: 830
B89: فهد ظافر القحطاني | C89: 173.33333
B90: فهد ونواف الكربى | C90: 1334.1667
B91: فيصل محمد العذبة | C91: 766.66667 | F91: Row Labels | G91: Count of Flag_Status
B92: مصطفى | C92: 958.33333 | F92: جاري - Active | G92: 39
B93: ناصر الحايف | C93: 433.33333 | F93: متوقف - On Hold | G93: 14
B94: نايف الموسى | C94: 433.33333 | F94: مكتمل - Completed | G94: 14
B95: هزاع مبارك الهاجري | C95: 177.5 | F95: Grand Total | G95: 67
B96: Grand Total | C96: 13596.25

Sheet Departments
A1: 📋 Departments – جدول الأقسام
A2: م | B2: كود القسم | C2: اسم القسم بالعربي | D2: اسم القسم بالانجليزي | E2: ملاحظات
A3: # | B3: Dept_ID | C3: Dept_Name | D3: Dept_Name_EN | E3: Notes
A4: 1 | B4: ADM_D01 | C4: الإدارة | D4: Administration
A5: 2 | B5: FIN_D02 | C5: التشطيبات | D5: Finishes
A6: 3 | B6: CON_D03 | C6: الإنشاءات | D6: Construction
A7: 4 | B7: ELE_D04 | C7: الكهرباء | D7: electricity
A8: 5 | B8: PLM_D05 | C8: السباكة | D8: Plumbing
A9: 6 | B9: STN_D06 | C9: الحجر | D9: Stone
A10: 7 | B10: ALU_D07 | C10: الألمنيوم | D10: aluminum
A11: 8 | B11: EQP_D08 | C11: المعدات | D11: Equipment
A12: 9 | B12: CRP_D09 | C12: النجارة | D12: Carpentry
A13: 10 | B13: PTG_D10 | C13: الدهانات | D13: paints
A14: 11 | B14: All_D11 | C14: كل الأقسام | D14: All sections
A15: 12 | B15: D13
A16: 13 | B16: D14
A17: 14 | B17: D15

Sheet Projects
A1: 🏗️ Projects – سجل المشاريع
B2: كود المشروع | C2: اسم المشروع | D2: القسم | E2: الموقع | F2: تاريخ البدء | G2: تاريخ الانتهاء | H2: الحالة | J2: اسم العميل | K2: رقم الموبايل | L2: مسؤول_العميل | M2: ملاحظات
A3: # | B3: Project_ID | C3: Project_Name | D3: Department | E3: Location | F3: Start_Date | G3: End_Date | H3: Status | I3: Flag_Status | J3: Client_Name | K3: Contact_Number | L3: Client_Sales | M3: Notes
A4: 1 | B4: S001F | C4: سعود الفهد | D4: كل الأقسام | F4: 46095 | G4: 46097 | H4: جاري - Active | I4: =_xlfn.XLOOKUP(tbl_Projects[[#This Row],[Status]],Project_Status[Status],Project_Status[Flag],"",0) -> Ac_0
A5: 2 | B5: S002F | C5: سعيد صالح الجحيش | D5: كل الأقسام | F5: 46098 | G5: 46101 | H5: جاري - Active | I5: =_xlfn.XLOOKUP(tbl_Projects[[#This Row],[Status]],Project_Status[Status],Project_Status[Flag],"",0) -> Ac_0
A6: 3 | B6: CF0F | C6: الإنشاءات | D6: كل الأقسام | F6: 46103 | G6: 46107 | H6: جاري - Active | I6: =_xlfn.XLOOKUP(tbl_Projects[[#This Row],[Status]],Project_Status[Status],Project_Status[Flag],"",0) -> Ac_0
A7: 4 | B7: J001F | C7: جابر قحيز المري | D7: كل الأقسام | F7: 46100 | H7: جاري - Active | I7: =_xlfn.XLOOKUP(tbl_Projects[[#This Row],[Status]],Project_Status[Status],Project_Status[Flag],"",0) -> Ac_0
A8: 5 | B8: A001F | C8: عبدالعزيز قحيز المري | D8: كل الأقسام | H8: جاري - Active | I8: =_xlfn.XLOOKUP(tbl_Projects[[#This Row],[Status]],Project_Status[Status],Project_Status[Flag],"",0) -> Ac_0
A9: 6 | B9: H001F | C9: حمد خجيم عايض العذبة | D9: كل الأقسام | H9: مكتمل - Completed | I9: =_xlfn.XLOOKUP(tbl_Projects[[#This Row],[Status]],Project_Status[Status],Project_Status[Flag],"",0) -> Co_0
A10: 7 | B10: S003F | C10: سعود نقدان | D10: كل الأقسام | H10: مكتمل - Completed | I10: =_xlfn.XLOOKUP(tbl_Projects[[#This Row],[Status]],Project_Status[Status],Project_Status[Flag],"",0) -> Co_0
A11: 8 | B11: N001F | C11: ناصر الحايف | D11: كل الأقسام | H11: مكتمل - Completed | I11: =_xlfn.XLOOKUP(tbl_Projects[[#This Row],[Status]],Project_Status[Status],Project_Status[Flag],"",0) -> Co_0
A12: 9 | B12: S004F | C12: صالح العذبة | D12: كل الأقسام | H12: جاري - Active | I12: =_xlfn.XLOOKUP(tbl_Projects[[#This Row],[Status]],Project_Status[Status],Project_Status[Flag],"",0) -> Ac_0
A13: 10 | B13: A002F | C13: عبدالهادي الماجد | D13: كل الأقسام | H13: جاري - Active | I13: =_xlfn.XLOOKUP(tbl_Projects[[#This Row],[Status]],Project_Status[Status],Project_Status[Flag],"",0) -> Ac_0
A14: 11 | B14: EF0F | C14: مصطفى | D14: كل الأقسام | H14: جاري - Active | I14: =_xlfn.XLOOKUP(tbl_Projects[[#This Row],[Status]],Project_Status[Status],Project_Status[Flag],"",0) -> Ac_0
A15: 12 | B15: U001F | C15: عمير راشد المري | D15: كل الأقسام | H15: جاري - Active | I15: =_xlfn.XLOOKUP(tbl_Projects[[#This Row],[Status]],Project_Status[Status],Project_Status[Flag],"",0) -> Ac_0
A16: 13 | B16: H002F | C16: حمد راشد المري | D16: كل الأقسام | H16: جاري - Active | I16: =_xlfn.XLOOKUP(tbl_Projects[[#This Row],[Status]],Project_Status[Status],Project_Status[Flag],"",0) -> Ac_0
A17: 14 | B17: A003F | C17: علي فاران البريدي | D17: كل الأقسام | H17: جاري - Active | I17: =_xlfn.XLOOKUP(tbl_Projects[[#This Row],[Status]],Project_Status[Status],Project_Status[Flag],"",0) -> Ac_0
A18: 15 | B18: K001F | C18: خالد زاين الدوسري | D18: كل الأقسام | H18: جاري - Active | I18: =_xlfn.XLOOKUP(tbl_Projects[[#This Row],[Status]],Project_Status[Status],Project_Status[Flag],"",0) -> Ac_0
A19: 16 | B19: H003F | C19: حمد الشهوانى الهاجرى | D19: كل الأقسام | H19: جاري - Active | I19: =_xlfn.XLOOKUP(tbl_Projects[[#This Row],[Status]],Project_Status[Status],Project_Status[Flag],"",0) -> Ac_0
... A70: 67 | B70: J001C | C70: جابر سالم الغواص | D70: كل الأقسام | H70: مكتمل - Completed | I70: =_xlfn.XLOOKUP(tbl_Projects[[#This Row],[Status]],Project_Status[Status],Project_Status[Flag],"",0) -> Co_0

Sheet Master_Employee
A1: 👷 Master Employee – سجل بيانات الموظفين
A2: # | B2: 🔑 Key Info | H2: 👤 Personal Info | O2: 💼 Employment | Y2: 💰 Salary | AD2: ⏱ Hour Rates | AH2: 📊 Role | AI2: بيانات الكفالة
A3: م | B3: كود الموظف | C3: كود القسم | D3: القسم | E3: القسم بالانجليزي | F3: المشرف | H3: اسم الموظف بالعربي | I3: اسم الموظف بالانجليزي | J3: رقم الإقامة | K3: تاريج انتهاء الإقامة | L3: عدد الأيام من بعد انتهاء الإقامة | M3: الجنسية | N3: المهنة | O3: تاريخ تعيين | P3: تاريخ مباشرة العمل | Q3: تاريخ اخر مباشرة العمل | R3: حالة الموظف | S3: كود الحالة | T3: طريقة الدفع | U3: كود الدفع | V3: رقم حساب البنك | W3: عهدة الموظف | X3: ملاحظات | Y3: المرتب الأساسي | Z3: بدلات المعيشة | AA3: بدلات المواصلات | AB3: بدلات أخرى | AC3: المرتب الكلي | AD3: معدل اليوم | AE3: معدل الساعة العادية | AF3: معدل ساعة الوقت الإضافي | AG3: مضروب الوقت الإضافي | AH3: الدرجة | AI3: الكفالة | AJ3: اسم شركة الكفيل
A4: # | B4: Emp_ID | C4: Dept_ID | D4: Department | E4: Department_EN | F4: Supervisor_Name | G4: Supervisor_ID | H4: Name_AR | I4: Name_EN | J4: National_ID | K4: Q_ID_Expire_Date | L4: Residency_Days_Status | M4: Nationality | N4: Job_Title | O4: Hire_Date | P4: Join_Date | Q4: Last_Return_Date | R4: Emp_Status | S4: Status_Code | T4: Payment_Method | U4: Payment_Code | V4: Bank_Account_Number | W4: Employee_Assets | X4: Notes | Y4: Basic_Salary | Z4: Living_Allowance | AA4: Transport_Allowance | AB4: Other_Allowance | AC4: Total_Salary | AD4: Daily_Rate | AE4: Hour_Rate | AF4: OT_Hr_Rate | AG4: OT_Multiplier | AH4: Grade | AI4: sponsorship | AJ4: Name_of_sponsorship_company
A5: 1 | B5: =_xlfn.XLOOKUP(Master_Employee[[#This Row],[Name_AR]],Lists!AN:AN,Lists!AL:AL," ",0) -> O60 | C5: =_xlfn.XLOOKUP(Master_Employee[[#This Row],[Department]],tbl_Dept[Dept_Name],tbl_Dept[Dept_ID],"",0) -> CON_D03 | D5: الإنشاءات | E5: =_xlfn.XLOOKUP(Master_Employee[[#This Row],[Dept_ID]],tbl_Dept[Dept_ID],tbl_Dept[Dept_Name_EN],"",0) -> Construction | G5: =_xlfn.XLOOKUP(Master_Employee[[#This Row],[Supervisor_Name]],EmpNames,EmpIDs,"",0) | H5: محمد اكبر صافي | I5: =_xlfn.XLOOKUP(Master_Employee[[#This Row],[Emp_ID]],Lists!AL:AL,Lists!AO:AO,"",0) -> Muhammad Akbar Safi | J5: 299010001 | K5: 46122 | L5: =IF(Master_Employee[[#This Row],[Q_ID_Expire_Date]]="","",TODAY()-Master_Employee[[#This Row],[Q_ID_Expire_Date]]) -> 101 | M5: مصري – Egyptian | N5: سائق | O5: 44927 | R5: works - يعمل | S5: =_xlfn.XLOOKUP(Master_Employee[[#This Row],[Emp_Status]],Emp_Status[Emp_Status],Emp_Status[Status_Code],"",0) -> W_01 | T5: Vodafone - فودافون | U5: =_xlfn.XLOOKUP(Master_Employee[[#This Row],[Payment_Method]],Pay[Payment_Method],Pay[Pay_Code],"",0) -> V_0 | Y5: 1700 | AA5: 0 | AB5: 0 | AC5: =Master_Employee[[#This Row],[Basic_Salary]]+Master_Employee[[#This Row],[Living_Allowance]]+Master_Employee[[#This Row],[Transport_Allowance]]+Master_Employee[[#This Row],[Other_Allowance]] -> 1700 | AD5: =(Master_Employee[[#This Row],[Total_Salary]]/30) -> 56.666667 | AE5: =Master_Employee[[#This Row],[Daily_Rate]]/8 -> 7.0833333 | AF5: =(Master_Employee[[#This Row],[Basic_Salary]]/30/8)*(Master_Employee[[#This Row],[OT_Multiplier]]) -> 7.0833333 | AG5: =1 -> 1 | AH5: Worker | AI5: كفالة-Sponsership
A6: 2 | B6: =_xlfn.XLOOKUP(Master_Employee[[#This Row],[Name_AR]],Lists!AN:AN,Lists!AL:AL," ",0) -> O61 | C6: =_xlfn.XLOOKUP(Master_Employee[[#This Row],[Department]],tbl_Dept[Dept_Name],tbl_Dept[Dept_ID],"",0) -> CON_D03 | D6: الإنشاءات | E6: =_xlfn.XLOOKUP(Master_Employee[[#This Row],[Dept_ID]],tbl_Dept[Dept_ID],tbl_Dept[Dept_Name_EN],"",0) -> Construction | G6: =_xlfn.XLOOKUP(Master_Employee[[#This Row],[Supervisor_Name]],EmpNames,EmpIDs,"",0) | H6: عبدالحكيم رستم انصاري | I6: =_xlfn.XLOOKUP(Master_Employee[[#This Row],[Emp_ID]],Lists!AL:AL,Lists!AO:AO,"",0) -> Abdul Hakim Rustam Ansari | J6: 299010002 | K6: 46116 | L6: =IF(Master_Employee[[#This Row],[Q_ID_Expire_Date]]="","",TODAY()-Master_Employee[[#This Row],[Q_ID_Expire_Date]]) -> 107 | M6: مصري – Egyptian | N6: مشرف_موقع | O6: 01/03/2023 | R6: works - يعمل | S6: =_xlfn.XLOOKUP(Master_Employee[[#This Row],[Emp_Status]],Emp_Status[Emp_Status],Emp_Status[Status_Code],"",0) -> W_01 | T6: Vodafone - فودافون | U6: =_xlfn.XLOOKUP(Master_Employee[[#This Row],[Payment_Method]],Pay[Payment_Method],Pay[Pay_Code],"",0) -> V_0 | Y6: 1400 | AA6: 0 | AB6: 0 | AC6: =Master_Employee[[#This Row],[Basic_Salary]]+Master_Employee[[#This Row],[Living_Allowance]]+Master_Employee[[#This Row],[Transport_Allowance]]+Master_Employee[[#This Row],[Other_Allowance]] -> 1400 | AD6: =(Master_Employee[[#This Row],[Total_Salary]]/30) -> 46.666667 | AE6: =Master_Employee[[#This Row],[Daily_Rate]]/8 -> 5.8333333 | AF6: =(Master_Employee[[#This Row],[Basic_Salary]]/30/8)*(Master_Employee[[#This Row],[OT_Multiplier]]) -> 5.8333333 | AG6: =1 -> 1 | AH6: Supervisor | AI6: كفالة-Sponsership
A7: 3 | B7: =_xlfn.XLOOKUP(Master_Employee[[#This Row],[Name_AR]],Lists!AN:AN,Lists!AL:AL," ",0) -> O52 | C7: =_xlfn.XLOOKUP(Master_Employee[[#This Row],[Department]],tbl_Dept[Dept_Name],tbl_Dept[Dept_ID],"",0) -> CON_D03 | D7: الإنشاءات | E7: =_xlfn.XLOOKUP(Master_Employee[[#This Row],[Dept_ID]],tbl_Dept[Dept_ID],tbl_Dept[Dept_Name_EN],"",0) -> Construction | G7: =_xlfn.XLOOKUP(Master_Employee[[#This Row],[Supervisor_Name]],EmpNames,EmpIDs,"",0) | H7: شميم انصاري | I7: =_xlfn.XLOOKUP(Master_Employee[[#This Row],[Emp_ID]],Lists!AL:AL,Lists!AO:AO,"",0) -> Shamim Ansari | J7: 299010003 | K7: 46123 | L7: =IF(Master_Employee[[#This Row],[Q_ID_Expire_Date]]="","",TODAY()-Master_Employee[[#This Row],[Q_ID_Expire_Date]]) -> 100 | M7: هندي – Indian | N7: مشرف_موقع | O7: 15/04/2023 | R7: vacation - إجازة | S7: =_xlfn.XLOOKUP(Master_Employee[[#This Row],[Emp_Status]],Emp_Status[Emp_Status],Emp_Status[Status_Code],"",0) -> V_01 | T7: Vodafone - فودافون | U7: =_xlfn.XLOOKUP(Master_Employee[[#This Row],[Payment_Method]],Pay[Payment_Method],Pay[Pay_Code],"",0) -> V_0 | Y7: 2000 | AA7: 0 | AB7: 0 | AC7: =Master_Employee[[#This Row],[Basic_Salary]]+Master_Employee[[#This Row],[Living_Allowance]]+Master_Employee[[#This Row],[Transport_Allowance]]+Master_Employee[[#This Row],[Other_Allowance]] -> 2000 | AD7: =(Master_Employee[[#This Row],[Total_Salary]]/30) -> 66.666667 | AE7: =Master_Employee[[#This Row],[Daily_Rate]]/8 -> 8.3333333 | AF7: =(Master_Employee[[#This Row],[Basic_Salary]]/30/8)*(Master_Employee[[#This Row],[OT_Multiplier]]) -> 8.3333333 | AG7: =1 -> 1 | AH7: Supervisor | AI7: كفالة-Sponsership
A8: 4 | B8: =_xlfn.XLOOKUP(Master_Employee[[#This Row],[Name_AR]],Lists!AN:AN,Lists!AL:AL," ",0) -> O162 | C8: =_xlfn.XLOOKUP(Master_Employee[[#This Row],[Department]],tbl_Dept[Dept_Name],tbl_Dept[Dept_ID],"",0) -> CON_D03 | D8: الإنشاءات | E8: =_xlfn.XLOOKUP(Master_Employee[[#This Row],[Dept_ID]],tbl_Dept[Dept_ID],tbl_Dept[Dept_Name_EN],"",0) -> Construction | G8: =_xlfn.XLOOKUP(Master_Employee[[#This Row],[Supervisor_Name]],EmpNames,EmpIDs,"",0) | H8: يرافن انصاري | I8: =_xlfn.XLOOKUP(Master_Employee[[#This Row],[Emp_ID]],Lists!AL:AL,Lists!AO:AO,"",0) -> Yaraven Ansari | J8: 299010101 | K8: 46124 | L8: =IF(Master_Employee[[#This Row],[Q_ID_Expire_Date]]="","",TODAY()-Master_Employee[[#This Row],[Q_ID_Expire_Date]]) -> 99 | M8: هندي – Indian | N8: مشرف_موقع | O8: 01/05/2023 | R8: vacation - إجازة | S8: =_xlfn.XLOOKUP(Master_Employee[[#This Row],[Emp_Status]],Emp_Status[Emp_Status],Emp_Status[Status_Code],"",0) -> V_01 | T8: Bank - بنك | U8: =_xlfn.XLOOKUP(Master_Employee[[#This Row],[Payment_Method]],Pay[Payment_Method],Pay[Pay_Code],"",0) -> B_0 | Y8: 1500 | AA8: 300 | AB8: 0 | AC8: =Master_Employee[[#This Row],[Basic_Salary]]+Master_Employee[[#This Row],[Living_Allowance]]+Master_Employee[[#This Row],[Transport_Allowance]]+Master_Employee[[#This Row],[Other_Allowance]] -> 1800 | AD8: =(Master_Employee[[#This Row],[Total_Salary]]/30) -> 60 | AE8: =Master_Employee[[#This Row],[Daily_Rate]]/8 -> 7.5 | AF8: =(Master_Employee[[#This Row],[Basic_Salary]]/30/8)*(Master_Employee[[#This Row],[OT_Multiplier]]) -> 6.25 | AG8: =1 -> 1 | AH8: Manager | AI8: كفالة-Sponsership
A9: 5 | B9: =_xlfn.XLOOKUP(Master_Employee[[#This Row],[Name_AR]],Lists!AN:AN,Lists!AL:AL," ",0) -> O175 | C9: =_xlfn.XLOOKUP(Master_Employee[[#This Row],[Department]],tbl_Dept[Dept_Name],tbl_Dept[Dept_ID],"",0) -> CON_D03 | D9: الإنشاءات | E9: =_xlfn.XLOOKUP(Master_Employee[[#This Row],[Dept_ID]],tbl_Dept[Dept_ID],tbl_Dept[Dept_Name_EN],"",0) -> Construction | G9: =_xlfn.XLOOKUP(Master_Employee[[#This Row],[Supervisor_Name]],EmpNames,EmpIDs,"",0) | H9: انوار انصاري رحيم انصاري | I9: =_xlfn.XLOOKUP(Master_Employee[[#This Row],[Emp_ID]],Lists!AL:AL,Lists!AO:AO,"",0) -> Anwar Ansari Rahim Ansari | J9: 299010202 | K9: 46125 | L9: =IF(Master_Employee[[#This Row],[Q_ID_Expire_Date]]="","",TODAY()-Master_Employee[[#This Row],[Q_ID_Expire_Date]]) -> 98 | M9: هندي – Indian | N9: مشرف_موقع | O9: 01/06/2023 | R9: works - يعمل | S9: =_xlfn.XLOOKUP(Master_Employee[[#This Row],[Emp_Status]],Emp_Status[Emp_Status],Emp_Status[Status_Code],"",0) -> W_01 | T9: cash - نقدا | U9: =_xlfn.XLOOKUP(Master_Employee[[#This Row],[Payment_Method]],Pay[Payment_Method],Pay[Pay_Code],"",0) -> C_0 | Y9: 1100 | AA9: 300 | AB9: 0 | AC9: =Master_Employee[[#This Row],[Basic_Salary]]+Master_Employee[[#This Row],[Living_Allowance]]+Master_Employee[[#This Row],[Transport_Allowance]]+Master_Employee[[#This Row],[Other_Allowance]] -> 1400 | AD9: =(Master_Employee[[#This Row],[Total_Salary]]/30) -> 46.666667 | AE9: =Master_Employee[[#This Row],[Daily_Rate]]/8 -> 5.8333333 | AF9: =(Master_Employee[[#This Row],[Basic_Salary]]/30/8)*(Master_Employee[[#This Row],[OT_Multiplier]]) -> 4.5833333 | AG9: =1 -> 1 | AH9: Manager | AI9: كفالة-Sponsership
A10: 6 | B10: =_xlfn.XLOOKUP(Master_Employee[[#This Row],[Name_AR]],Lists!AN:AN,Lists!AL:AL," ",0) -> O180 | C10: =_xlfn.XLOOKUP(Master_Employee[[#This Row],[Department]],tbl_Dept[Dept_Name],tbl_Dept[Dept_ID],"",0) -> CON_D03 | D10: الإنشاءات | E10: =_xlfn.XLOOKUP(Master_Employee[[#This Row],[Dept_ID]],tbl_Dept[Dept_ID],tbl_Dept[Dept_Name_EN],"",0) -> Construction | G10: =_xlfn.XLOOKUP(Master_Employee[[#This Row],[Supervisor_Name]],EmpNames,EmpIDs,"",0) | H10: جسير انصاري | I10: =_xlfn.XLOOKUP(Master_Employee[[#This Row],[Emp_ID]],Lists!AL:AL,Lists!AO:AO,"",0) -> Jasser Ansari | J10: 299010303 | K10: 46157 | L10: =IF(Master_Employee[[#This Row],[Q_ID_Expire_Date]]="","",TODAY()-Master_Employee[[#This Row],[Q_ID_Expire_Date]]) -> 66 | M10: هندي – Indian | N10: سباك | O10: 10/07/2023 | R10: works - يعمل | S10: =_xlfn.XLOOKUP(Master_Employee[[#This Row],[Emp_Status]],Emp_Status[Emp_Status],Emp_Status[Status_Code],"",0) -> W_01 | T10: Vodafone - فودافون | U10: =_xlfn.XLOOKUP(Master_Employee[[#This Row],[Payment_Method]],Pay[Payment_Method],Pay[Pay_Code],"",0) -> V_0 | Y10: 1000 | AA10: 300 | AB10: 0 | AC10: =Master_Employee[[#This Row],[Basic_Salary]]+Master_Employee[[#This Row],[Living_Allowance]]+Master_Employee[[#This Row],[Transport_Allowance]]+Master_Employee[[#This Row],[Other_Allowance]] -> 1300 | AD10: =(Master_Employee[[#This Row],[Total_Salary]]/30) -> 43.333333 | AE10: =Master_Employee[[#This Row],[Daily_Rate]]/8 -> 5.4166667 | AF10: =(Master_Employee[[#This Row],[Basic_Salary]]/30/8)*(Master_Employee[[#This Row],[OT_Multiplier]]) -> 4.1666667 | AG10: =1 -> 1 | AH10: Worker | AI10: غير كفالة-NoSponsership
A11: 7 | B11: =_xlfn.XLOOKUP(Master_Employee[[#This Row],[Name_AR]],Lists!AN:AN,Lists!AL:AL," ",0) -> O183 | C11: =_xlfn.XLOOKUP(Master_Employee[[#This Row],[Department]],tbl_Dept[Dept_Name],tbl_Dept[Dept_ID],"",0) -> CON_D03 | D11: الإنشاءات | E11: =_xlfn.XLOOKUP(Master_Employee[[#This Row],[Dept_ID]],tbl_Dept[Dept_ID],tbl_Dept[Dept_Name_EN],"",0) -> Construction | G11: =_xlfn.XLOOKUP(Master_Employee[[#This Row],[Supervisor_Name]],EmpNames,EmpIDs,"",0) | H11: محمد عمران انصاري | I11: =_xlfn.XLOOKUP(Master_Employee[[#This Row],[Emp_ID]],Lists!AL:AL,Lists!AO:AO,"",0) -> Muhammad Imran Ansari | J11: 299010404 | K11: 46218 | L11: =IF(Master_Employee[[#This Row],[Q_ID_Expire_Date]]="","",TODAY()-Master_Employee[[#This Row],[Q_ID_Expire_Date]]) -> 5 | M11: باكستاني – Pakistani | N11: عامل | O11: 01/08/2023 | R11: vacation - إجازة | S11: =_xlfn.XLOOKUP(Master_Employee[[#This Row],[Emp_Status]],Emp_Status[Emp_Status],Emp_Status[Status_Code],"",0) -> V_01 | T11: cash - نقدا | U11: =_xlfn.XLOOKUP(Master_Employee[[#This Row],[Payment_Method]],Pay[Payment_Method],Pay[Pay_Code],"",0) -> C_0 | Y11: 1700 | AA11: 300 | AB11: 200 | AC11: =Master_Employee[[#This Row],[Basic_Salary]]+Master_Employee[[#This Row],[Living_Allowance]]+Master_Employee[[#This Row],[Transport_Allowance]]+Master_Employee[[#This Row],[Other_Allowance]] -> 2200 | AD11: =(Master_Employee[[#This Row],[Total_Salary]]/30) -> 73.333333 | AE11: =Master_Employee[[#This Row],[Daily_Rate]]/8 -> 9.1666667 | AF11: =(Master_Employee[[#This Row],[Basic_Salary]]/30/8)*(Master_Employee[[#This Row],[OT_Multiplier]]) -> 7.0833333 | AG11: =1 -> 1 | AH11: Worker | AI11: غير كفالة-NoSponsership
A12: 8 | B12: =_xlfn.XLOOKUP(Master_Employee[[#This Row],[Name_AR]],Lists!AN:AN,Lists!AL:AL," ",0) -> O201 | C12: =_xlfn.XLOOKUP(Master_Employee[[#This Row],[Department]],tbl_Dept[Dept_Name],tbl_Dept[Dept_ID],"",0) -> CON_D03 | D12: الإنشاءات | E12: =_xlfn.XLOOKUP(Master_Employee[[#This Row],[Dept_ID]],tbl_Dept[Dept_ID],tbl_Dept[Dept_Name_EN],"",0) -> Construction | G12: =_xlfn.XLOOKUP(Master_Employee[[#This Row],[Supervisor_Name]],EmpNames,EmpIDs,"",0) | H12: محمد ياسين تورب علي | I12: =_xlfn.XLOOKUP(Master_Employee[[#This Row],[Emp_ID]],Lists!AL:AL,Lists!AO:AO,"",0) -> Mohammed Yassin Torb Ali | J12: 299010505 | L12: =IF(Master_Employee[[#This Row],[Q_ID_Expire_Date]]="","",TODAY()-Master_Employee[[#This Row],[Q_ID_Expire_Date]]) | M12: باكستاني – Pakistani | N12: كهربائي | O12: 01/09/2023 | R12: works - يعمل | S12: =_xlfn.XLOOKUP(Master_Employee[[#This Row],[Emp_Status]],Emp_Status[Emp_Status],Emp_Status[Status_Code],"",0) -> W_01 | T12: Bank - بنك | U12: =_xlfn.XLOOKUP(Master_Employee[[#This Row],[Payment_Method]],Pay[Payment_Method],Pay[Pay_Code],"",0) -> B_0 | Y12: 1000 | AA12: 300 | AB12: 100 | AC12: =Master_Employee[[#This Row],[Basic_Salary]]+Master_Employee[[#This Row],[Living_Allowance]]+Master_Employee[[#This Row],[Transport_Allowance]]+Master_Employee[[#This Row],[Other_Allowance]] -> 1400 | AD12: =(Master_Employee[[#This Row],[Total_Salary]]/30) -> 46.666667 | AE12: =Master_Employee[[#This Row],[Daily_Rate]]/8 -> 5.8333333 | AF12: =(Master_Employee[[#This Row],[Basic_Salary]]/30/8)*(Master_Employee[[#This Row],[OT_Multiplier]]) -> 4.1666667 | AG12: =1 -> 1 | AH12: Worker | AI12: غير كفالة-NoSponsership
A13: 9 | B13: =_xlfn.XLOOKUP(Master_Employee[[#This Row],[Name_AR]],Lists!AN:AN,Lists!AL:AL," ",0) -> O229 | C13: =_xlfn.XLOOKUP(Master_Employee[[#This Row],[Department]],tbl_Dept[Dept_Name],tbl_Dept[Dept_ID],"",0) -> CON_D03 | D13: الإنشاءات | E13: =_xlfn.XLOOKUP(Master_Employee[[#This Row],[Dept_ID]],tbl_Dept[Dept_ID],tbl_Dept[Dept_Name_EN],"",0) -> Construction | G13: =_xlfn.XLOOKUP(Master_Employee[[#This Row],[Supervisor_Name]],EmpNames,EmpIDs,"",0) | H13: محمد سهيل محمد سليم | I13: =_xlfn.XLOOKUP(Master_Employee[[#This Row],[Emp_ID]],Lists!AL:AL,Lists!AO:AO,"",0) -> Mohammed Suhail Mohammed Salim | J13: 299010606 | L13: =IF(Master_Employee[[#This Row],[Q_ID_Expire_Date]]="","",TODAY()-Master_Employee[[#This Row],[Q_ID_Expire_Date]]) | M13: باكستاني – Pakistani | N13: مساعد كهربائي | O13: 15/01/2024 | R13: works - يعمل | S13: =_xlfn.XLOOKUP(Master_Employee[[#This Row],[Emp_Status]],Emp_Status[Emp_Status],Emp_Status[Status_Code],"",0) -> W_01 | T13: cash - نقدا | U13: =_xlfn.XLOOKUP(Master_Employee[[#This Row],[Payment_Method]],Pay[Payment_Method],Pay[Pay_Code],"",0) -> C_0 | Y13: 1000 | AA13: 300 | AB13: 100 | AC13: =Master_Employee[[#This Row],[Basic_Salary]]+Master_Employee[[#This Row],[Living_Allowance]]+Master_Employee[[#This Row],[Transport_Allowance]]+Master_Employee[[#This Row],[Other_Allowance]] -> 1400 | AD13: =(Master_Employee[[#This Row],[Total_Salary]]/30) -> 46.666667 | AE13: =Master_Employee[[#This Row],[Daily_Rate]]/8 -> 5.8333333 | AF13: =(Master_Employee[[#This Row],[Basic_Salary]]/30/8)*(Master_Employee[[#This Row],[OT_Multiplier]]) -> 4.1666667 | AG13: =1 -> 1 | AH13: Worker | AI13: غير كفالة-NoSponsership
A14: 10 | B14: =_xlfn.XLOOKUP(Master_Employee[[#This Row],[Name_AR]],Lists!AN:AN,Lists!AL:AL," ",0) -> 244 | C14: =_xlfn.XLOOKUP(Master_Employee[[#This Row],[Department]],tbl_Dept[Dept_Name],tbl_Dept[Dept_ID],"",0) -> CON_D03 | D14: الإنشاءات | E14: =_xlfn.XLOOKUP(Master_Employee[[#This Row],[Dept_ID]],tbl_Dept[Dept_ID],tbl_Dept[Dept_Name_EN],"",0) -> Construction | G14: =_xlfn.XLOOKUP(Master_Employee[[#This Row],[Supervisor_Name]],EmpNames,EmpIDs,"",0) | H14: جمال انصاري | I14: =_xlfn.XLOOKUP(Master_Employee[[#This Row],[Emp_ID]],Lists!AL:AL,Lists!AO:AO,"",0) -> Jamal Ansari | J14: 299010707 | L14: =IF(Master_Employee[[#This Row],[Q_ID_Expire_Date]]="","",TODAY()-Master_Employee[[#This Row],[Q_ID_Expire_Date]]) | M14: باكستاني – Pakistani | N14: كهربائي | O14: 01/02/2024 | R14: works - يعمل | S14: =_xlfn.XLOOKUP(Master_Employee[[#This Row],[Emp_Status]],Emp_Status[Emp_Status],Emp_Status[Status_Code],"",0) -> W_01 | T14: cash - نقدا | U14: =_xlfn.XLOOKUP(Master_Employee[[#This Row],[Payment_Method]],Pay[Payment_Method],Pay[Pay_Code],"",0) -> C_0 | Y14: 1200 | AA14: 300 | AB14: 100 | AC14: =Master_Employee[[#This Row],[Basic_Salary]]+Master_Employee[[#This Row],[Living_Allowance]]+Master_Employee[[#This Row],[Transport_Allowance]]+Master_Employee[[#This Row],[Other_Allowance]] -> 1600 | AD14: =(Master_Employee[[#This Row],[Total_Salary]]/30) -> 53.333333 | AE14: =Master_Employee[[#This Row],[Daily_Rate]]/8 -> 6.6666667 | AF14: =(Master_Employee[[#This Row],[Basic_Salary]]/30/8)*(Master_Employee[[#This Row],[OT_Multiplier]]) -> 5 | AG14: =1 -> 1 | AH14: Worker | AI14: غير كفالة-NoSponsership
A15: 11 | B15: =_xlfn.XLOOKUP(Master_Employee[[#This Row],[Name_AR]],Lists!AN:AN,Lists!AL:AL," ",0) -> 243 | C15: =_xlfn.XLOOKUP(Master_Employee[[#This Row],[Department]],tbl_Dept[Dept_Name],tbl_Dept[Dept_ID],"",0) -> FIN_D02 | D15: التشطيبات | E15: =_xlfn.XLOOKUP(Master_Employee[[#This Row],[Dept_ID]],tbl_Dept[Dept_ID],tbl_Dept[Dept_Name_EN],"",0) -> Finishes | G15: =_xlfn.XLOOKUP(Master_Employee[[#This Row],[Supervisor_Name]],EmpNames,EmpIDs,"",0) | H15: محمد عزيز لاحق | I15: =_xlfn.XLOOKUP(Master_Employee[[#This Row],[Emp_ID]],Lists!AL:AL,Lists!AO:AO,"",0) -> 0 | L15: =IF(Master_Employee[[#This Row],[Q_ID_Expire_Date]]="","",TODAY()-Master_Employee[[#This Row],[Q_ID_Expire_Date]]) | M15: نيبالي – Nepali | N15: صباغ | R15: works - يعمل | S15: =_xlfn.XLOOKUP(Master_Employee[[#This Row],[Emp_Status]],Emp_Status[Emp_Status],Emp_Status[Status_Code],"",0) -> W_01 | T15: Bank - بنك | U15: =_xlfn.XLOOKUP(Master_Employee[[#This Row],[Payment_Method]],Pay[Payment_Method],Pay[Pay_Code],"",0) -> B_0 | Y15: 1000 | AA15: 300 | AB15: 100 | AC15: =Master_Employee[[#This Row],[Basic_Salary]]+Master_Employee[[#This Row],[Living_Allowance]]+Master_Employee[[#This Row],[Transport_Allowance]]+Master_Employee[[#This Row],[Other_Allowance]] -> 1400 | AD15: =(Master_Employee[[#This Row],[Total_Salary]]/30) -> 46.666667 | AE15: =Master_Employee[[#This Row],[Daily_Rate]]/8 -> 5.8333333 | AF15: =(Master_Employee[[#This Row],[Basic_Salary]]/30/8)*(Master_Employee[[#This Row],[OT_Multiplier]]) -> 4.1666667 | AG15: =1 -> 1 | AH15: Worker | AI15: غير كفالة-NoSponsership
A16: 12 | B16: =_xlfn.XLOOKUP(Master_Employee[[#This Row],[Name_AR]],Lists!AN:AN,Lists!AL:AL," ",0) -> 389 | C16: =_xlfn.XLOOKUP(Master_Employee[[#This Row],[Department]],tbl_Dept[Dept_Name],tbl_Dept[Dept_ID],"",0) -> FIN_D02 | D16: التشطيبات | E16: =_xlfn.XLOOKUP(Master_Employee[[#This Row],[Dept_ID]],tbl_Dept[Dept_ID],tbl_Dept[Dept_Name_EN],"",0) -> Finishes | G16: =_xlfn.XLOOKUP(Master_Employee[[#This Row],[Supervisor_Name]],EmpNames,EmpIDs,"",0) | H16: محمد نور نبي | I16: =_xlfn.XLOOKUP(Master_Employee[[#This Row],[Emp_ID]],Lists!AL:AL,Lists!AO:AO,"",0) -> 0 | L16: =IF(Master_Employee[[#This Row],[Q_ID_Expire_Date]]="","",TODAY()-Master_Employee[[#This Row],[Q_ID_Expire_Date]]) | M16: نيبالي – Nepali | N16: مساعد كهربائي | R16: works - يعمل | S16: =_xlfn.XLOOKUP(Master_Employee[[#This Row],[Emp_Status]],Emp_Status[Emp_Status],Emp_Status[Status_Code],"",0) -> W_01 | T16: Bank - بنك | U16: =_xlfn.XLOOKUP(Master_Employee[[#This Row],[Payment_Method]],Pay[Payment_Method],Pay[Pay_Code],"",0) -> B_0 | Y16: 1000 | AA16: 300 | AB16: 0 | AC16: =Master_Employee[[#This Row],[Basic_Salary]]+Master_Employee[[#This Row],[Living_Allowance]]+Master_Employee[[#This Row],[Transport_Allowance]]+Master_Employee[[#This Row],[Other_Allowance]] -> 1300 | AD16: =(Master_Employee[[#This Row],[Total_Salary]]/30) -> 43.333333 | AE16: =Master_Employee[[#This Row],[Daily_Rate]]/8 -> 5.4166667 | AF16: =(Master_Employee[[#This Row],[Basic_Salary]]/30/8)*(Master_Employee[[#This Row],[OT_Multiplier]]) -> 4.1666667 | AG16: =1 -> 1 | AH16: Worker | AI16: غير كفالة-NoSponsership
A17: 13 | B17: =_xlfn.XLOOKUP(Master_Employee[[#This Row],[Name_AR]],Lists!AN:AN,Lists!AL:AL," ",0) -> 411 | C17: =_xlfn.XLOOKUP(Master_Employee[[#This Row],[Department]],tbl_Dept[Dept_Name],tbl_Dept[Dept_ID],"",0) -> FIN_D02 | D17: التشطيبات | E17: =_xlfn.XLOOKUP(Master_Employee[[#This Row],[Dept_ID]],tbl_Dept[Dept_ID],tbl_Dept[Dept_Name_EN],"",0) -> Finishes | G17: =_xlfn.XLOOKUP(Master_Employee[[#This Row],[Supervisor_Name]],EmpNames,EmpIDs,"",0) | H17: نور ميستري | I17: =_xlfn.XLOOKUP(Master_Employee[[#This Row],[Emp_ID]],Lists!AL:AL,Lists!AO:AO,"",0) -> 0 | L17: =IF(Master_Employee[[#This Row],[Q_ID_Expire_Date]]="","",TODAY()-Master_Employee[[#This Row],[Q_ID_Expire_Date]]) | M17: نيبالي – Nepali | N17: سباك | R17: works - يعمل | S17: =_xlfn.XLOOKUP(Master_Employee[[#This Row],[Emp_Status]],Emp_Status[Emp_Status],Emp_Status[Status_Code],"",0) -> W_01 | T17: Bank - بنك | U17: =_xlfn.XLOOKUP(Master_Employee[[#This Row],[Payment_Method]],Pay[Payment_Method],Pay[Pay_Code],"",0) -> B_0 | Y17: 1000 | AA17: 300 | AB17: 0 | AC17: =Master_Employee[[#This Row],[Basic_Salary]]+Master_Employee[[#This Row],[Living_Allowance]]+Master_Employee[[#This Row],[Transport_Allowance]]+Master_Employee[[#This Row],[Other_Allowance]] -> 1300 | AD17: =(Master_Employee[[#This Row],[Total_Salary]]/30) -> 43.333333 | AE17: =Master_Employee[[#This Row],[Daily_Rate]]/8 -> 5.4166667 | AF17: =(Master_Employee[[#This Row],[Basic_Salary]]/30/8)*(Master_Employee[[#This Row],[OT_Multiplier]]) -> 4.1666667 | AG17: =1 -> 1 | AH17: Worker | AI17: غير كفالة-NoSponsership
A18: 14 | B18: =_xlfn.XLOOKUP(Master_Employee[[#This Row],[Name_AR]],Lists!AN:AN,Lists!AL:AL," ",0) -> 448 | C18: =_xlfn.XLOOKUP(Master_Employee[[#This Row],[Department]],tbl_Dept[Dept_Name],tbl_Dept[Dept_ID],"",0) -> FIN_D02 | D18: التشطيبات | E18: =_xlfn.XLOOKUP(Master_Employee[[#This Row],[Dept_ID]],tbl_Dept[Dept_ID],tbl_Dept[Dept_Name_EN],"",0) -> Finishes | G18: =_xlfn.XLOOKUP(Master_Employee[[#This Row],[Supervisor_Name]],EmpNames,EmpIDs,"",0) | H18: بابو رام كامي | I18: =_xlfn.XLOOKUP(Master_Employee[[#This Row],[Emp_ID]],Lists!AL:AL,Lists!AO:AO,"",0) -> 0 | L18: =IF(Master_Employee[[#This Row],[Q_ID_Expire_Date]]="","",TODAY()-Master_Employee[[#This Row],[Q_ID_Expire_Date]]) | M18: نيبالي – Nepali | N18: كهربائي | R18: works - يعمل | S18: =_xlfn.XLOOKUP(Master_Employee[[#This Row],[Emp_Status]],Emp_Status[Emp_Status],Emp_Status[Status_Code],"",0) -> W_01 | T18: Bank - بنك | U18: =_xlfn.XLOOKUP(Master_Employee[[#This Row],[Payment_Method]],Pay[Payment_Method],Pay[Pay_Code],"",0) -> B_0 | Y18: 1500 | AA18: 500 | AB18: 0 | AC18: =Master_Employee[[#This Row],[Basic_Salary]]+Master_Employee[[#This Row],[Living_Allowance]]+Master_Employee[[#This Row],[Transport_Allowance]]+Master_Employee[[#This Row],[Other_Allowance]] -> 2000 | AD18: =(Master_Employee[[#This Row],[Total_Salary]]/30) -> 66.666667 | AE18: =Master_Employee[[#This Row],[Daily_Rate]]/8 -> 8.3333333 | AF18: =(Master_Employee[[#This Row],[Basic_Salary]]/30/8)*(Master_Employee[[#This Row],[OT_Multiplier]]) -> 6.25 | AG18: =1 -> 1 | AH18: Worker | AI18: كفالة-Sponsership
A19: 15 | B19: =_xlfn.XLOOKUP(Master_Employee[[#This Row],[Name_AR]],Lists!AN:AN,Lists!AL:AL," ",0) -> 247 | C19: =_xlfn.XLOOKUP(Master_Employee[[#This Row],[Department]],tbl_Dept[Dept_Name],tbl_Dept[Dept_ID],"",0) -> FIN_D02 | D19: التشطيبات | E19: =_xlfn.XLOOKUP(Master_Employee[[#This Row],[Dept_ID]],tbl_Dept[Dept_ID],tbl_Dept[Dept_Name_EN],"",0) -> Finishes | G19: =_xlfn.XLOOKUP(Master_Employee[[#This Row],[Supervisor_Name]],EmpNames,EmpIDs,"",0) | H19: جمال محمد علي | I19: =_xlfn.XLOOKUP(Master_Employee[[#This Row],[Emp_ID]],Lists!AL:AL,Lists!AO:AO,"",0) -> 0 | L19: =IF(Master_Employee[[#This Row],[Q_ID_Expire_Date]]="","",TODAY()-Master_Employee[[#This Row],[Q_ID_Expire_Date]]) | M19: نيبالي – Nepali | N19: معلم جبس بورد | R19: works - يعمل | S19: =_xlfn.XLOOKUP(Master_Employee[[#This Row],[Emp_Status]],Emp_Status[Emp_Status],Emp_Status[Status_Code],"",0) -> W_01 | T19: cash - نقدا | U19: =_xlfn.XLOOKUP(Master_Employee[[#This Row],[Payment_Method]],Pay[Payment_Method],Pay[Pay_Code],"",0) -> C_0 | Y19: 1000 | AA19: 0 | AB19: 300 | AC19: =Master_Employee[[#This Row],[Basic_Salary]]+Master_Employee[[#This Row],[Living_Allowance]]+Master_Employee[[#This Row],[Transport_Allowance]]+Master_Employee[[#This Row],[Other_Allowance]] -> 1300 | AD19: =(Master_Employee[[#This Row],[Total_Salary]]/30) -> 43.333333 | AE19: =Master_Employee[[#This Row],[Daily_Rate]]/8 -> 5.4166667 | AF19: =(Master_Employee[[#This Row],[Basic_Salary]]/30/8)*(Master_Employee[[#This Row],[OT_Multiplier]]) -> 4.1666667 | AG19: =1 -> 1 | AH19: Worker | AI19: كفالة-Sponsership
A20: 16 | B20: =_xlfn.XLOOKUP(Master_Employee[[#This Row],[Name_AR]],Lists!AN:AN,Lists!AL:AL," ",0) -> O204 | C20: =_xlfn.XLOOKUP(Master_Employee[[#This Row],[Department]],tbl_Dept[Dept_Name],tbl_Dept[Dept_ID],"",0) -> FIN_D02 | D20: التشطيبات | E20: =_xlfn.XLOOKUP(Master_Employee[[#This Row],[Dept_ID]],tbl_Dept[Dept_ID],tbl_Dept[Dept_Name_EN],"",0) -> Finishes | G20: =_xlfn.XLOOKUP(Master_Employee[[#This Row],[Supervisor_Name]],EmpNames,EmpIDs,"",0) | H20: محمد ابوبكور محمد حسين | I20: =_xlfn.XLOOKUP(Master_Employee[[#This Row],[Emp_ID]],Lists!AL:AL,Lists!AO:AO,"",0) -> 0 | L20: =IF(Master_Employee[[#This Row],[Q_ID_Expire_Date]]="","",TODAY()-Master_Employee[[#This Row],[Q_ID_Expire_Date]]) | M20: نيبالي – Nepali | N20: فورمان | R20: works - يعمل | S20: =_xlfn.XLOOKUP(Master_Employee[[#This Row],[Emp_Status]],Emp_Status[Emp_Status],Emp_Status[Status_Code],"",0) -> W_01 | T20: cash - نقدا | U20: =_xlfn.XLOOKUP(Master_Employee[[#This Row],[Payment_Method]],Pay[Payment_Method],Pay[Pay_Code],"",0) -> C_0 | Y20: 1700 | AA20: 300 | AB20: 200 | AC20: =Master_Employee[[#This Row],[Basic_Salary]]+Master_Employee[[#This Row],[Living_Allowance]]+Master_Employee[[#This Row],[Transport_Allowance]]+Master_Employee[[#This Row],[Other_Allowance]] -> 2200 | AD20: =(Master_Employee[[#This Row],[Total_Salary]]/30) -> 73.333333 | AE20: =Master_Employee[[#This Row],[Daily_Rate]]/8 -> 9.1666667 | AF20: =(Master_Employee[[#This Row],[Basic_Salary]]/30/8)*(Master_Employee[[#This Row],[OT_Multiplier]]) -> 7.0833333 | AG20: =1 -> 1 | AH20: Worker | AI20: كفالة-Sponsership
A21: 17 | B21: =_xlfn.XLOOKUP(Master_Employee[[#This Row],[Name_AR]],Lists!AN:AN,Lists!AL:AL," ",0) -> O207 | C21: =_xlfn.XLOOKUP(Master_Employee[[#This Row],[Department]],tbl_Dept[Dept_Name],tbl_Dept[Dept_ID],"",0) -> FIN_D02 | D21: التشطيبات | E21: =_xlfn.XLOOKUP(Master_Employee[[#This Row],[Dept_ID]],tbl_Dept[Dept_ID],tbl_Dept[Dept_Name_EN],"",0) -> Finishes | G21: =_xlfn.XLOOKUP(Master_Employee[[#This Row],[Supervisor_Name]],EmpNames,EmpIDs,"",0) | H21: محمد نور الأسلام | I21: =_xlfn.XLOOKUP(Master_Employee[[#This Row],[Emp_ID]],Lists!AL:AL,Lists!AO:AO,"",0) -> 0 | L21: =IF(Master_Employee[[#This Row],[Q_ID_Expire_Date]]="","",TODAY()-Master_Employee[[#This Row],[Q_ID_Expire_Date]]) | M21: نيبالي – Nepali | N21: عامل الثرى دى | R21: works - يعمل | S21: =_xlfn.XLOOKUP(Master_Employee[[#This Row],[Emp_Status]],Emp_Status[Emp_Status],Emp_Status[Status_Code],"",0) -> W_01 | T21: cash - نقدا | U21: =_xlfn.XLOOKUP(Master_Employee[[#This Row],[Payment_Method]],Pay[Payment_Method],Pay[Pay_Code],"",0) -> C_0 | Y21: 1700 | AA21: 300 | AB21: 200 | AC21: =Master_Employee[[#This Row],[Basic_Salary]]+Master_Employee[[#This Row],[Living_Allowance]]+Master_Employee[[#This Row],[Transport_Allowance]]+Master_Employee[[#This Row],[Other_Allowance]] -> 2200 | AD21: =(Master_Employee[[#This Row],[Total_Salary]]/30) -> 73.333333 | AE21: =Master_Employee[[#This Row],[Daily_Rate]]/8 -> 9.1666667 | AF21: =(Master_Employee[[#This Row],[Basic_Salary]]/30/8)*(Master_Employee[[#This Row],[OT_Multiplier]]) -> 7.0833333 | AG21: =1 -> 1 | AH21: Worker | AI21: كفالة-Sponsership
A22: 18 | B22: =_xlfn.XLOOKUP(Master_Employee[[#This Row],[Name_AR]],Lists!AN:AN,Lists!AL:AL," ",0) -> O163 | C22: =_xlfn.XLOOKUP(Master_Employee[[#This Row],[Department]],tbl_Dept[Dept_Name],tbl_Dept[Dept_ID],"",0) -> FIN_D02 | D22: التشطيبات | E22: =_xlfn.XLOOKUP(Master_Employee[[#This Row],[Dept_ID]],tbl_Dept[Dept_ID],tbl_Dept[Dept_Name_EN],"",0) -> Finishes | G22: =_xlfn.XLOOKUP(Master_Employee[[#This Row],[Supervisor_Name]],EmpNames,EmpIDs,"",0) | H22: عبد الباسي عبد الرحمن اشير | I22: =_xlfn.XLOOKUP(Master_Employee[[#This Row],[Emp_ID]],Lists!AL:AL,Lists!AO:AO,"",0) -> 0 | L22: =IF(Master_Employee[[#This Row],[Q_ID_Expire_Date]]="","",TODAY()-Master_Employee[[#This Row],[Q_ID_Expire_Date]]) | M22: نيبالي – Nepali | N22: عامل الثرى دى | R22: works - يعمل | S22: =_xlfn.XLOOKUP(Master_Employee[[#This Row],[Emp_Status]],Emp_Status[Emp_Status],Emp_Status[Status_Code],"",0) -> W_01 | T22: cash - نقدا | U22: =_xlfn.XLOOKUP(Master_Employee[[#This Row],[Payment_Method]],Pay[Payment_Method],Pay[Pay_Code],"",0) -> C_0 | Y22: 1500 | AA22: 300 | AB22: 500 | AC22: =Master_Employee[[#This Row],[Basic_Salary]]+Master_Employee[[#This Row],[Living_Allowance]]+Master_Employee[[#This Row],[Transport_Allowance]]+Master_Employee[[#This Row],[Other_Allowance]] -> 2300 | AD22: =(Master_Employee[[#This Row],[Total_Salary]]/30) -> 76.666667 | AE22: =Master_Employee[[#This Row],[Daily_Rate]]/8 -> 9.5833333 | AF22: =(Master_Employee[[#This Row],[Basic_Salary]]/30/8)*(Master_Employee[[#This Row],[OT_Multiplier]]) -> 6.25 | AG22: =1 -> 1 | AH22: Worker | AI22: كفالة-Sponsership
A23: 19 | B23: =_xlfn.XLOOKUP(Master_Employee[[#This Row],[Name_AR]],Lists!AN:AN,Lists!AL:AL," ",0) -> O48 | C23: =_xlfn.XLOOKUP(Master_Employee[[#This Row],[Department]],tbl_Dept[Dept_Name],tbl_Dept[Dept_ID],"",0) -> FIN_D02 | D23: التشطيبات | E23: =_xlfn.XLOOKUP(Master_Employee[[#This Row],[Dept_ID]],tbl_Dept[Dept_ID],tbl_Dept[Dept_Name_EN],"",0) -> Finishes | G23: =_xlfn.XLOOKUP(Master_Employee[[#This Row],[Supervisor_Name]],EmpNames,EmpIDs,"",0) | H23: بنود كومار ساه | I23: =_xlfn.XLOOKUP(Master_Employee[[#This Row],[Emp_ID]],Lists!AL:AL,Lists!AO:AO,"",0) -> 0 | L23: =IF(Master_Employee[[#This Row],[Q_ID_Expire_Date]]="","",TODAY()-Master_Employee[[#This Row],[Q_ID_Expire_Date]]) | M23: نيبالي – Nepali | N23: فني بلاستر | R23: works - يعمل | S23: =_xlfn.XLOOKUP(Master_Employee[[#This Row],[Emp_Status]],Emp_Status[Emp_Status],Emp_Status[Status_Code],"",0) -> W_01 | T23: cash - نقدا | U23: =_xlfn.XLOOKUP(Master_Employee[[#This Row],[Payment_Method]],Pay[Payment_Method],Pay[Pay_Code],"",0) -> C_0 | Y23: 1500 | AA23: 300 | AB23: 700 | AC23: =Master_Employee[[#This Row],[Basic_Salary]]+Master_Employee[[#This Row],[Living_Allowance]]+Master_Employee[[#This Row],[Transport_Allowance]]+Master_Employee[[#This Row],[Other_Allowance]] -> 2500 | AD23: =(Master_Employee[[#This Row],[Total_Salary]]/30) -> 83.333333 | AE23: =Master_Employee[[#This Row],[Daily_Rate]]/8 -> 10.416667 | AF23: =(Master_Employee[[#This Row],[Basic_Salary]]/30/8)*(Master_Employee[[#This Row],[OT_Multiplier]]) -> 6.25 | AG23: =1 -> 1 | AH23: Worker | AI23: كفالة-Sponsership
A24: 20 | B24: =_xlfn.XLOOKUP(Master_Employee[[#This Row],[Name_AR]],Lists!AN:AN,Lists!AL:AL," ",0) -> O187 | C24: =_xlfn.XLOOKUP(Master_Employee[[#This Row],[Department]],tbl_Dept[Dept_Name],tbl_Dept[Dept_ID],"",0) -> FIN_D02 | D24: التشطيبات | E24: =_xlfn.XLOOKUP(Master_Employee[[#This Row],[Dept_ID]],tbl_Dept[Dept_ID],tbl_Dept[Dept_Name_EN],"",0) -> Finishes | G24: =_xlfn.XLOOKUP(Master_Employee[[#This Row],[Supervisor_Name]],EmpNames,EmpIDs,"",0) | H24: مد موجمل حقي | I24: =_xlfn.XLOOKUP(Master_Employee[[#This Row],[Emp_ID]],Lists!AL:AL,Lists!AO:AO,"",0) -> 0 | L24: =IF(Master_Employee[[#This Row],[Q_ID_Expire_Date]]="","",TODAY()-Master_Employee[[#This Row],[Q_ID_Expire_Date]]) | M24: نيبالي – Nepali | N24: ناطور | R24: works - يعمل | S24: =_xlfn.XLOOKUP(Master_Employee[[#This Row],[Emp_Status]],Emp_Status[Emp_Status],Emp_Status[Status_Code],"",0) -> W_01 | T24: cash - نقدا | U24: =_xlfn.XLOOKUP(Master_Employee[[#This Row],[Payment_Method]],Pay[Payment_Method],Pay[Pay_Code],"",0) -> C_0 | Y24: 1000 | AA24: 300 | AB24: 200 | AC24: =Master_Employee[[#This Row],[Basic_Salary]]+Master_Employee[[#This Row],[Living_Allowance]]+Master_Employee[[#This Row],[Transport_Allowance]]+Master_Employee[[#This Row],[Other_Allowance]] -> 1500 | AD24: =(Master_Employee[[#This Row],[Total_Salary]]/30) -> 50 | AE24: =Master_Employee[[#This Row],[Daily_Rate]]/8 -> 6.25 | AF24: =(Master_Employee[[#This Row],[Basic_Salary]]/30/8)*(Master_Employee[[#This Row],[OT_Multiplier]]) -> 4.1666667 | AG24: =1 -> 1 | AH24: Worker | AI24: كفالة-Sponsership
A25: 21 | B25: =_xlfn.XLOOKUP(Master_Employee[[#This Row],[Name_AR]],Lists!AN:AN,Lists!AL:AL," ",0) -> 146 | C25: =_xlfn.XLOOKUP(Master_Employee[[#This Row],[Department]],tbl_Dept[Dept_Name],tbl_Dept[Dept_ID],"",0) -> ADM_D01 | D25: الإدارة | E25: =_xlfn.XLOOKUP(Master_Employee[[#This Row],[Dept_ID]],tbl_Dept[Dept_ID],tbl_Dept[Dept_Name_EN],"",0) -> Administration | G25: =_xlfn.XLOOKUP(Master_Employee[[#This Row],[Supervisor_Name]],EmpNames,EmpIDs,"",0) | H25: ﻣﺎﻣﻮﻥ ﺍﺣﻤﺪ ﺷﻮﻧﻮ ﻣﻴﺎﻩ | I25: =_xlfn.XLOOKUP(Master_Employee[[#This Row],[Emp_ID]],Lists!AL:AL,Lists!AO:AO,"",0) -> 0 | L25: =IF(Master_Employee[[#This Row],[Q_ID_Expire_Date]]="","",TODAY()-Master_Employee[[#This Row],[Q_ID_Expire_Date]]) | M25: فلبيني – Filipino | N25: عامل | R25: works - يعمل | S25: =_xlfn.XLOOKUP(Master_Employee[[#This Row],[Emp_Status]],Emp_Status[Emp_Status],Emp_Status[Status_Code],"",0) -> W_01 | T25: Vodafone - فودافون | U25: =_xlfn.XLOOKUP(Master_Employee[[#This Row],[Payment_Method]],Pay[Payment_Method],Pay[Pay_Code],"",0) -> V_0 | Y25: 1000 | AA25: 300 | AB25: 0 | AC25: =Master_Employee[[#This Row],[Basic_Salary]]+Master_Employee[[#This Row],[Living_Allowance]]+Master_Employee[[#This Row],[Transport_Allowance]]+Master_Employee[[#This Row],[Other_Allowance]] -> 1300 | AD25: =(Master_Employee[[#This Row],[Total_Salary]]/30) -> 43.333333 | AE25: =Master_Employee[[#This Row],[Daily_Rate]]/8 -> 5.4166667 | AF25: =(Master_Employee[[#This Row],[Basic_Salary]]/30/8)*(Master_Employee[[#This Row],[OT_Multiplier]]) -> 4.1666667 | AG25: =1 -> 1 | AH25: Worker | AI25: كفالة-Sponsership
A26: 22 | B26: =_xlfn.XLOOKUP(Master_Employee[[#This Row],[Name_AR]],Lists!AN:AN,Lists!AL:AL," ",0) -> O304 | C26: =_xlfn.XLOOKUP(Master_Employee[[#This Row],[Department]],tbl_Dept[Dept_Name],tbl_Dept[Dept_ID],"",0) -> ADM_D01 | D26: الإدارة | E26: =_xlfn.XLOOKUP(Master_Employee[[#This Row],[Dept_ID]],tbl_Dept[Dept_ID],tbl_Dept[Dept_Name_EN],"",0) -> Administration | G26: =_xlfn.XLOOKUP(Master_Employee[[#This Row],[Supervisor_Name]],EmpNames,EmpIDs,"",0) | H26: صلاح عبدالرحمن الحاج احمد | I26: =_xlfn.XLOOKUP(Master_Employee[[#This Row],[Emp_ID]],Lists!AL:AL,Lists!AO:AO,"",0) -> 0 | L26: =IF(Master_Employee[[#This Row],[Q_ID_Expire_Date]]="","",TODAY()-Master_Employee[[#This Row],[Q_ID_Expire_Date]]) | M26: فلبيني – Filipino | N26: فورمان | R26: works - يعمل | S26: =_xlfn.XLOOKUP(Master_Employee[[#This Row],[Emp_Status]],Emp_Status[Emp_Status],Emp_Status[Status_Code],"",0) -> W_01 | T26: Bank - بنك | U26: =_xlfn.XLOOKUP(Master_Employee[[#This Row],[Payment_Method]],Pay[Payment_Method],Pay[Pay_Code],"",0) -> B_0 | Y26: 1000 | AA26: 300 | AB26: 500 | AC26: =Master_Employee[[#This Row],[Basic_Salary]]+Master_Employee[[#This Row],[Living_Allowance]]+Master_Employee[[#This Row],[Transport_Allowance]]+Master_Employee[[#This Row],[Other_Allowance]] -> 1800 | AD26: =(Master_Employee[[#This Row],[Total_Salary]]/30) -> 60 | AE26: =Master_Employee[[#This Row],[Daily_Rate]]/8 -> 7.5 | AF26: =(Master_Employee[[#This Row],[Basic_Salary]]/30/8)*(Master_Employee[[#This Row],[OT_Multiplier]]) -> 4.1666667 | AG26: =1 -> 1 | AH26: Worker | AI26: كفالة-Sponsership
... A30: 26 | B30: =_xlfn.XLOOKUP(Master_Employee[[#This Row],[Name_AR]],Lists!AN:AN,Lists!AL:AL," ",0) -> 314 | C30: =_xlfn.XLOOKUP(Master_Employee[[#This Row],[Department]],tbl_Dept[Dept_Name],tbl_Dept[Dept_ID],"",0) -> ADM_D01 | D30: الإدارة | E30: =_xlfn.XLOOKUP(Master_Employee[[#This Row],[Dept_ID]],tbl_Dept[Dept_ID],tbl_Dept[Dept_Name_EN],"",0) -> Administration | G30: =_xlfn.XLOOKUP(Master_Employee[[#This Row],[Supervisor_Name]],EmpNames,EmpIDs,"",0) | H30: محمد عرلاان | I30: =_xlfn.XLOOKUP(Master_Employee[[#This Row],[Emp_ID]],Lists!AL:AL,Lists!AO:AO,"",0) -> 0 | L30: =IF(Master_Employee[[#This Row],[Q_ID_Expire_Date]]="","",TODAY()-Master_Employee[[#This Row],[Q_ID_Expire_Date]]) | M30: إندونيسي – Indonesian | N30: فنى | R30: New appointment - تعيين جديد | S30: =_xlfn.XLOOKUP(Master_Employee[[#This Row],[Emp_Status]],Emp_Status[Emp_Status],Emp_Status[Status_Code],"",0) -> N_01 | T30: Bank - بنك | U30: =_xlfn.XLOOKUP(Master_Employee[[#This Row],[Payment_Method]],Pay[Payment_Method],Pay[Pay_Code],"",0) -> B_0 | Y30: 1500 | AA30: 300 | AB30: 700 | AC30: =Master_Employee[[#This Row],[Basic_Salary]]+Master_Employee[[#This Row],[Living_Allowance]]+Master_Employee[[#This Row],[Transport_Allowance]]+Master_Employee[[#This Row],[Other_Allowance]] -> 2500 | AD30: =(Master_Employee[[#This Row],[Total_Salary]]/30) -> 83.333333 | AE30: =Master_Employee[[#This Row],[Daily_Rate]]/8 -> 10.416667 | AF30: =(Master_Employee[[#This Row],[Basic_Salary]]/30/8)*(Master_Employee[[#This Row],[OT_Multiplier]]) -> 6.25 | AG30: =1 -> 1 | AH30: Worker | AI30: كفالة-Sponsership

Sheet Transactions
A1: 💳 Transactions – الحركات المالية (سلف / خصم / بونص)
A2: م | B2: رقم المعاملة | C2: كود الموظف | D2: اسم الموظف بالعربي | E2: اسم الموظف بالانجليزي | F2: القسم | G2: المشروع | H2: التاريخ | I2: النوع | K2: السبب | L2: المبلغ | M2: ملاحظات
A3: # | B3: Trans_ID | C3: Emp_ID | D3: Name_AR | E3: Name_EN | F3: Department | G3: Project_Name | H3: Date | I3: Type | J3: Type_Code | K3: Reasons | L3: Amount | M3: Notes
A4: 1 | B4: TRN-001 | C4: O60 | D4: =IFERROR(_xlfn.XLOOKUP(C4,Master_Employee[Emp_ID],Master_Employee[Name_AR],"",0),"") -> محمد اكبر صافي | E4: =IFERROR(_xlfn.XLOOKUP(C4,Master_Employee[Emp_ID],Master_Employee[Name_EN],"",0),"") -> Muhammad Akbar Safi | F4: =IFERROR(_xlfn.XLOOKUP(C4,Master_Employee[Emp_ID],Master_Employee[Department],"",0),"") -> الإنشاءات | H4: 46082 | I4: بونص - Bonus | J4: =_xlfn.XLOOKUP(tbl_Transactions[[#This Row],[Type]],Type[Trans_Type],Type[Type_Code],"",0) -> Bo_01 | L4: 100 | P4: في حالة السلفة (LO_01) يجب إدخال سبب قبل كتابة المبلغ
A5: 2 | B5: TRN-002 | C5: O61 | D5: =IFERROR(_xlfn.XLOOKUP(C5,Master_Employee[Emp_ID],Master_Employee[Name_AR],"",0),"") -> عبدالحكيم رستم انصاري | E5: =IFERROR(_xlfn.XLOOKUP(C5,Master_Employee[Emp_ID],Master_Employee[Name_EN],"",0),"") -> Abdul Hakim Rustam Ansari | F5: =IFERROR(_xlfn.XLOOKUP(C5,Master_Employee[Emp_ID],Master_Employee[Department],"",0),"") -> الإنشاءات | H5: 46083 | I5: خصم - Deduction | J5: =_xlfn.XLOOKUP(tbl_Transactions[[#This Row],[Type]],Type[Trans_Type],Type[Type_Code],"",0) -> De_01 | L5: 50 | P5: مينفعش ادخل أي داتا في صفوف البلانك
A6: 4 | B6: TRN-004 | C6: O175 | D6: =IFERROR(_xlfn.XLOOKUP(C6,Master_Employee[Emp_ID],Master_Employee[Name_AR],"",0),"") -> انوار انصاري رحيم انصاري | E6: =IFERROR(_xlfn.XLOOKUP(C6,Master_Employee[Emp_ID],Master_Employee[Name_EN],"",0),"") -> Anwar Ansari Rahim Ansari | F6: =IFERROR(_xlfn.XLOOKUP(C6,Master_Employee[Emp_ID],Master_Employee[Department],"",0),"") -> الإنشاءات | H6: 46085 | I6: سلف - Loans | J6: =_xlfn.XLOOKUP(tbl_Transactions[[#This Row],[Type]],Type[Trans_Type],Type[Type_Code],"",0) -> Lo_01 | L6: 500 | O6: كل الموظفين في كل الأقسام بحالتهم التلاته
A7: =IFERROR(IF(C7="","",ROW()-2),"") -> 5 | B7: TRN-005 | C7: O229 | D7: =IFERROR(_xlfn.XLOOKUP(C7,Master_Employee[Emp_ID],Master_Employee[Name_AR],"",0),"") -> محمد سهيل محمد سليم | E7: =IFERROR(_xlfn.XLOOKUP(C7,Master_Employee[Emp_ID],Master_Employee[Name_EN],"",0),"") -> Mohammed Suhail Mohammed Salim | F7: =IFERROR(_xlfn.XLOOKUP(C7,Master_Employee[Emp_ID],Master_Employee[Department],"",0),"") -> الإنشاءات | H7: 46082 | I7: سلف - Loans | J7: =_xlfn.XLOOKUP(tbl_Transactions[[#This Row],[Type]],Type[Trans_Type],Type[Type_Code],"",0) -> Lo_01 | L7: 100 | O7: {=_xlfn._xlws.FILTER( Master_Employee[Emp_ID], ISNUMBER(MATCH(Master_Employee[Status_Code],Valid_Status[],0)), "لا يوجد عمال" )} -> O60 | P7: =OR( J4<>"Lo_01", AND(J4="Lo_01",K4<>""), L4="" ) -> TRUE
A8: =IFERROR(IF(C8="","",ROW()-2),"") -> 6 | B8: TRN-006 | C8: 146 | D8: =IFERROR(_xlfn.XLOOKUP(C8,Master_Employee[Emp_ID],Master_Employee[Name_AR],"",0),"") -> ﻣﺎﻣﻮﻥ ﺍﺣﻤﺪ ﺷﻮﻧﻮ ﻣﻴﺎﻩ | E8: =IFERROR(_xlfn.XLOOKUP(C8,Master_Employee[Emp_ID],Master_Employee[Name_EN],"",0),"") -> 0 | F8: =IFERROR(_xlfn.XLOOKUP(C8,Master_Employee[Emp_ID],Master_Employee[Department],"",0),"") -> الإدارة | H8: 46091 | I8: خصم - Deduction | J8: =_xlfn.XLOOKUP(tbl_Transactions[[#This Row],[Type]],Type[Trans_Type],Type[Type_Code],"",0) -> De_01 | L8: 200 | O8: O61
A9: =IFERROR(IF(C9="","",ROW()-2),"") | B9: TRN-007 | D9: =IFERROR(_xlfn.XLOOKUP(C9,Master_Employee[Emp_ID],Master_Employee[Name_AR],"",0),"") | E9: =IFERROR(_xlfn.XLOOKUP(C9,Master_Employee[Emp_ID],Master_Employee[Name_EN],"",0),"") | F9: =IFERROR(_xlfn.XLOOKUP(C9,Master_Employee[Emp_ID],Master_Employee[Department],"",0),"") | J9: =_xlfn.XLOOKUP(tbl_Transactions[[#This Row],[Type]],Type[Trans_Type],Type[Type_Code],"",0) | O9: O175
A10: =IFERROR(IF(C10="","",ROW()-2),"") | B10: TRN-008 | D10: =IFERROR(_xlfn.XLOOKUP(C10,Master_Employee[Emp_ID],Master_Employee[Name_AR],"",0),"") | E10: =IFERROR(_xlfn.XLOOKUP(C10,Master_Employee[Emp_ID],Master_Employee[Name_EN],"",0),"") | F10: =IFERROR(_xlfn.XLOOKUP(C10,Master_Employee[Emp_ID],Master_Employee[Department],"",0),"") | J10: =_xlfn.XLOOKUP(tbl_Transactions[[#This Row],[Type]],Type[Trans_Type],Type[Type_Code],"",0) | O10: O180
A11: =IFERROR(IF(C11="","",ROW()-2),"") | B11: TRN-009 | D11: =IFERROR(_xlfn.XLOOKUP(C11,Master_Employee[Emp_ID],Master_Employee[Name_AR],"",0),"") | E11: =IFERROR(_xlfn.XLOOKUP(C11,Master_Employee[Emp_ID],Master_Employee[Name_EN],"",0),"") | F11: =IFERROR(_xlfn.XLOOKUP(C11,Master_Employee[Emp_ID],Master_Employee[Department],"",0),"") | J11: =_xlfn.XLOOKUP(tbl_Transactions[[#This Row],[Type]],Type[Trans_Type],Type[Type_Code],"",0) | O11: O201
A12: =IFERROR(IF(C12="","",ROW()-2),"") | B12: TRN-010 | D12: =IFERROR(_xlfn.XLOOKUP(C12,Master_Employee[Emp_ID],Master_Employee[Name_AR],"",0),"") | E12: =IFERROR(_xlfn.XLOOKUP(C12,Master_Employee[Emp_ID],Master_Employee[Name_EN],"",0),"") | F12: =IFERROR(_xlfn.XLOOKUP(C12,Master_Employee[Emp_ID],Master_Employee[Department],"",0),"") | J12: =_xlfn.XLOOKUP(tbl_Transactions[[#This Row],[Type]],Type[Trans_Type],Type[Type_Code],"",0) | O12: O229
A13: =IFERROR(IF(C13="","",ROW()-2),"") | B13: TRN-011 | D13: =IFERROR(_xlfn.XLOOKUP(C13,Master_Employee[Emp_ID],Master_Employee[Name_AR],"",0),"") | E13: =IFERROR(_xlfn.XLOOKUP(C13,Master_Employee[Emp_ID],Master_Employee[Name_EN],"",0),"") | F13: =IFERROR(_xlfn.XLOOKUP(C13,Master_Employee[Emp_ID],Master_Employee[Department],"",0),"") | J13: =_xlfn.XLOOKUP(tbl_Transactions[[#This Row],[Type]],Type[Trans_Type],Type[Type_Code],"",0) | O13: 244
A14: =IFERROR(IF(C14="","",ROW()-2),"") | B14: TRN-012 | D14: =IFERROR(_xlfn.XLOOKUP(C14,Master_Employee[Emp_ID],Master_Employee[Name_AR],"",0),"") | E14: =IFERROR(_xlfn.XLOOKUP(C14,Master_Employee[Emp_ID],Master_Employee[Name_EN],"",0),"") | F14: =IFERROR(_xlfn.XLOOKUP(C14,Master_Employee[Emp_ID],Master_Employee[Department],"",0),"") | J14: =_xlfn.XLOOKUP(tbl_Transactions[[#This Row],[Type]],Type[Trans_Type],Type[Type_Code],"",0) | O14: 243
A15: =IFERROR(IF(C15="","",ROW()-2),"") | B15: TRN-013 | D15: =IFERROR(_xlfn.XLOOKUP(C15,Master_Employee[Emp_ID],Master_Employee[Name_AR],"",0),"") | E15: =IFERROR(_xlfn.XLOOKUP(C15,Master_Employee[Emp_ID],Master_Employee[Name_EN],"",0),"") | F15: =IFERROR(_xlfn.XLOOKUP(C15,Master_Employee[Emp_ID],Master_Employee[Department],"",0),"") | J15: =_xlfn.XLOOKUP(tbl_Transactions[[#This Row],[Type]],Type[Trans_Type],Type[Type_Code],"",0) | O15: 389
A16: =IFERROR(IF(C16="","",ROW()-2),"") | D16: =IFERROR(_xlfn.XLOOKUP(C16,Master_Employee[Emp_ID],Master_Employee[Name_AR],"",0),"") | E16: =IFERROR(_xlfn.XLOOKUP(C16,Master_Employee[Emp_ID],Master_Employee[Name_EN],"",0),"") | F16: =IFERROR(_xlfn.XLOOKUP(C16,Master_Employee[Emp_ID],Master_Employee[Department],"",0),"") | J16: =_xlfn.XLOOKUP(tbl_Transactions[[#This Row],[Type]],Type[Trans_Type],Type[Type_Code],"",0) | O16: 411
A17: =IFERROR(IF(C17="","",ROW()-2),"") | D17: =IFERROR(_xlfn.XLOOKUP(C17,Master_Employee[Emp_ID],Master_Employee[Name_AR],"",0),"") | E17: =IFERROR(_xlfn.XLOOKUP(C17,Master_Employee[Emp_ID],Master_Employee[Name_EN],"",0),"") | F17: =IFERROR(_xlfn.XLOOKUP(C17,Master_Employee[Emp_ID],Master_Employee[Department],"",0),"") | J17: =_xlfn.XLOOKUP(tbl_Transactions[[#This Row],[Type]],Type[Trans_Type],Type[Type_Code],"",0) | O17: 448
A18: =IFERROR(IF(C18="","",ROW()-2),"") | D18: =IFERROR(_xlfn.XLOOKUP(C18,Master_Employee[Emp_ID],Master_Employee[Name_AR],"",0),"") | E18: =IFERROR(_xlfn.XLOOKUP(C18,Master_Employee[Emp_ID],Master_Employee[Name_EN],"",0),"") | F18: =IFERROR(_xlfn.XLOOKUP(C18,Master_Employee[Emp_ID],Master_Employee[Department],"",0),"") | J18: =_xlfn.XLOOKUP(tbl_Transactions[[#This Row],[Type]],Type[Trans_Type],Type[Type_Code],"",0) | O18: 247
A19: =IFERROR(IF(C19="","",ROW()-2),"") | D19: =IFERROR(_xlfn.XLOOKUP(C19,Master_Employee[Emp_ID],Master_Employee[Name_AR],"",0),"") | E19: =IFERROR(_xlfn.XLOOKUP(C19,Master_Employee[Emp_ID],Master_Employee[Name_EN],"",0),"") | F19: =IFERROR(_xlfn.XLOOKUP(C19,Master_Employee[Emp_ID],Master_Employee[Department],"",0),"") | J19: =_xlfn.XLOOKUP(tbl_Transactions[[#This Row],[Type]],Type[Trans_Type],Type[Type_Code],"",0) | O19: O204
A20: =IFERROR(IF(C20="","",ROW()-2),"") | D20: =IFERROR(_xlfn.XLOOKUP(C20,Master_Employee[Emp_ID],Master_Employee[Name_AR],"",0),"") | E20: =IFERROR(_xlfn.XLOOKUP(C20,Master_Employee[Emp_ID],Master_Employee[Name_EN],"",0),"") | F20: =IFERROR(_xlfn.XLOOKUP(C20,Master_Employee[Emp_ID],Master_Employee[Department],"",0),"") | J20: =_xlfn.XLOOKUP(tbl_Transactions[[#This Row],[Type]],Type[Trans_Type],Type[Type_Code],"",0) | O20: O207
A21: =IFERROR(IF(C21="","",ROW()-2),"") | D21: =IFERROR(_xlfn.XLOOKUP(C21,Master_Employee[Emp_ID],Master_Employee[Name_AR],"",0),"") | E21: =IFERROR(_xlfn.XLOOKUP(C21,Master_Employee[Emp_ID],Master_Employee[Name_EN],"",0),"") | F21: =IFERROR(_xlfn.XLOOKUP(C21,Master_Employee[Emp_ID],Master_Employee[Department],"",0),"") | J21: =_xlfn.XLOOKUP(tbl_Transactions[[#This Row],[Type]],Type[Trans_Type],Type[Type_Code],"",0) | O21: O163
A22: =IFERROR(IF(C22="","",ROW()-2),"") | D22: =IFERROR(_xlfn.XLOOKUP(C22,Master_Employee[Emp_ID],Master_Employee[Name_AR],"",0),"") | E22: =IFERROR(_xlfn.XLOOKUP(C22,Master_Employee[Emp_ID],Master_Employee[Name_EN],"",0),"") | F22: =IFERROR(_xlfn.XLOOKUP(C22,Master_Employee[Emp_ID],Master_Employee[Department],"",0),"") | J22: =_xlfn.XLOOKUP(tbl_Transactions[[#This Row],[Type]],Type[Trans_Type],Type[Type_Code],"",0) | O22: O48
A23: =IFERROR(IF(C23="","",ROW()-2),"") | D23: =IFERROR(_xlfn.XLOOKUP(C23,Master_Employee[Emp_ID],Master_Employee[Name_AR],"",0),"") | E23: =IFERROR(_xlfn.XLOOKUP(C23,Master_Employee[Emp_ID],Master_Employee[Name_EN],"",0),"") | F23: =IFERROR(_xlfn.XLOOKUP(C23,Master_Employee[Emp_ID],Master_Employee[Department],"",0),"") | J23: =_xlfn.XLOOKUP(tbl_Transactions[[#This Row],[Type]],Type[Trans_Type],Type[Type_Code],"",0) | O23: O187
A24: =IFERROR(IF(C24="","",ROW()-2),"") | D24: =IFERROR(_xlfn.XLOOKUP(C24,Master_Employee[Emp_ID],Master_Employee[Name_AR],"",0),"") | E24: =IFERROR(_xlfn.XLOOKUP(C24,Master_Employee[Emp_ID],Master_Employee[Name_EN],"",0),"") | F24: =IFERROR(_xlfn.XLOOKUP(C24,Master_Employee[Emp_ID],Master_Employee[Department],"",0),"") | J24: =_xlfn.XLOOKUP(tbl_Transactions[[#This Row],[Type]],Type[Trans_Type],Type[Type_Code],"",0) | O24: 146
A25: =IFERROR(IF(C25="","",ROW()-2),"") | D25: =IFERROR(_xlfn.XLOOKUP(C25,Master_Employee[Emp_ID],Master_Employee[Name_AR],"",0),"") | E25: =IFERROR(_xlfn.XLOOKUP(C25,Master_Employee[Emp_ID],Master_Employee[Name_EN],"",0),"") | F25: =IFERROR(_xlfn.XLOOKUP(C25,Master_Employee[Emp_ID],Master_Employee[Department],"",0),"") | J25: =_xlfn.XLOOKUP(tbl_Transactions[[#This Row],[Type]],Type[Trans_Type],Type[Type_Code],"",0) | O25: O304
A26: =IFERROR(IF(C26="","",ROW()-2),"") | D26: =IFERROR(_xlfn.XLOOKUP(C26,Master_Employee[Emp_ID],Master_Employee[Name_AR],"",0),"") | E26: =IFERROR(_xlfn.XLOOKUP(C26,Master_Employee[Emp_ID],Master_Employee[Name_EN],"",0),"") | F26: =IFERROR(_xlfn.XLOOKUP(C26,Master_Employee[Emp_ID],Master_Employee[Department],"",0),"") | J26: =_xlfn.XLOOKUP(tbl_Transactions[[#This Row],[Type]],Type[Trans_Type],Type[Type_Code],"",0) | O26: 494
A27: =IFERROR(IF(C27="","",ROW()-2),"") | D27: =IFERROR(_xlfn.XLOOKUP(C27,Master_Employee[Emp_ID],Master_Employee[Name_AR],"",0),"") | E27: =IFERROR(_xlfn.XLOOKUP(C27,Master_Employee[Emp_ID],Master_Employee[Name_EN],"",0),"") | F27: =IFERROR(_xlfn.XLOOKUP(C27,Master_Employee[Emp_ID],Master_Employee[Department],"",0),"") | J27: =_xlfn.XLOOKUP(tbl_Transactions[[#This Row],[Type]],Type[Trans_Type],Type[Type_Code],"",0) | O27: O246
A28: =IFERROR(IF(C28="","",ROW()-2),"") | D28: =IFERROR(_xlfn.XLOOKUP(C28,Master_Employee[Emp_ID],Master_Employee[Name_AR],"",0),"") | E28: =IFERROR(_xlfn.XLOOKUP(C28,Master_Employee[Emp_ID],Master_Employee[Name_EN],"",0),"") | F28: =IFERROR(_xlfn.XLOOKUP(C28,Master_Employee[Emp_ID],Master_Employee[Department],"",0),"") | J28: =_xlfn.XLOOKUP(tbl_Transactions[[#This Row],[Type]],Type[Trans_Type],Type[Type_Code],"",0) | O28: O309
A29: =IFERROR(IF(C29="","",ROW()-2),"") | D29: =IFERROR(_xlfn.XLOOKUP(C29,Master_Employee[Emp_ID],Master_Employee[Name_AR],"",0),"") | E29: =IFERROR(_xlfn.XLOOKUP(C29,Master_Employee[Emp_ID],Master_Employee[Name_EN],"",0),"") | F29: =IFERROR(_xlfn.XLOOKUP(C29,Master_Employee[Emp_ID],Master_Employee[Department],"",0),"") | J29: =_xlfn.XLOOKUP(tbl_Transactions[[#This Row],[Type]],Type[Trans_Type],Type[Type_Code],"",0) | O29: 314
A30: =IFERROR(IF(C30="","",ROW()-2),"") | D30: =IFERROR(_xlfn.XLOOKUP(C30,Master_Employee[Emp_ID],Master_Employee[Name_AR],"",0),"") | E30: =IFERROR(_xlfn.XLOOKUP(C30,Master_Employee[Emp_ID],Master_Employee[Name_EN],"",0),"") | F30: =IFERROR(_xlfn.XLOOKUP(C30,Master_Employee[Emp_ID],Master_Employee[Department],"",0),"") | J30: =_xlfn.XLOOKUP(tbl_Transactions[[#This Row],[Type]],Type[Trans_Type],Type[Type_Code],"",0)
A31: =IFERROR(IF(C31="","",ROW()-2),"") | D31: =IFERROR(_xlfn.XLOOKUP(C31,Master_Employee[Emp_ID],Master_Employee[Name_AR],"",0),"") | E31: =IFERROR(_xlfn.XLOOKUP(C31,Master_Employee[Emp_ID],Master_Employee[Name_EN],"",0),"") | F31: =IFERROR(_xlfn.XLOOKUP(C31,Master_Employee[Emp_ID],Master_Employee[Department],"",0),"") | J31: =_xlfn.XLOOKUP(tbl_Transactions[[#This Row],[Type]],Type[Trans_Type],Type[Type_Code],"",0)
A32: =IFERROR(IF(C32="","",ROW()-2),"") | D32: =IFERROR(_xlfn.XLOOKUP(C32,Master_Employee[Emp_ID],Master_Employee[Name_AR],"",0),"") | E32: =IFERROR(_xlfn.XLOOKUP(C32,Master_Employee[Emp_ID],Master_Employee[Name_EN],"",0),"") | F32: =IFERROR(_xlfn.XLOOKUP(C32,Master_Employee[Emp_ID],Master_Employee[Department],"",0),"") | J32: =_xlfn.XLOOKUP(tbl_Transactions[[#This Row],[Type]],Type[Trans_Type],Type[Type_Code],"",0)
A33: =IFERROR(IF(C33="","",ROW()-2),"") | D33: =IFERROR(_xlfn.XLOOKUP(C33,Master_Employee[Emp_ID],Master_Employee[Name_AR],"",0),"") | E33: =IFERROR(_xlfn.XLOOKUP(C33,Master_Employee[Emp_ID],Master_Employee[Name_EN],"",0),"") | F33: =IFERROR(_xlfn.XLOOKUP(C33,Master_Employee[Emp_ID],Master_Employee[Department],"",0),"") | J33: =_xlfn.XLOOKUP(tbl_Transactions[[#This Row],[Type]],Type[Trans_Type],Type[Type_Code],"",0)
A34: =IFERROR(IF(C34="","",ROW()-2),"") | D34: =IFERROR(_xlfn.XLOOKUP(C34,Master_Employee[Emp_ID],Master_Employee[Name_AR],"",0),"") | E34: =IFERROR(_xlfn.XLOOKUP(C34,Master_Employee[Emp_ID],Master_Employee[Name_EN],"",0),"") | F34: =IFERROR(_xlfn.XLOOKUP(C34,Master_Employee[Emp_ID],Master_Employee[Department],"",0),"") | J34: =_xlfn.XLOOKUP(tbl_Transactions[[#This Row],[Type]],Type[Trans_Type],Type[Type_Code],"",0)
A35: =IFERROR(IF(C35="","",ROW()-2),"") | D35: =IFERROR(_xlfn.XLOOKUP(C35,Master_Employee[Emp_ID],Master_Employee[Name_AR],"",0),"") | E35: =IFERROR(_xlfn.XLOOKUP(C35,Master_Employee[Emp_ID],Master_Employee[Name_EN],"",0),"") | F35: =IFERROR(_xlfn.XLOOKUP(C35,Master_Employee[Emp_ID],Master_Employee[Department],"",0),"") | J35: =_xlfn.XLOOKUP(tbl_Transactions[[#This Row],[Type]],Type[Trans_Type],Type[Type_Code],"",0)
A36: =IFERROR(IF(C36="","",ROW()-2),"") | D36: =IFERROR(_xlfn.XLOOKUP(C36,Master_Employee[Emp_ID],Master_Employee[Name_AR],"",0),"") | E36: =IFERROR(_xlfn.XLOOKUP(C36,Master_Employee[Emp_ID],Master_Employee[Name_EN],"",0),"") | F36: =IFERROR(_xlfn.XLOOKUP(C36,Master_Employee[Emp_ID],Master_Employee[Department],"",0),"") | J36: =_xlfn.XLOOKUP(tbl_Transactions[[#This Row],[Type]],Type[Trans_Type],Type[Type_Code],"",0)
A37: =IFERROR(IF(C37="","",ROW()-2),"") | D37: =IFERROR(_xlfn.XLOOKUP(C37,Master_Employee[Emp_ID],Master_Employee[Name_AR],"",0),"") | E37: =IFERROR(_xlfn.XLOOKUP(C37,Master_Employee[Emp_ID],Master_Employee[Name_EN],"",0),"") | F37: =IFERROR(_xlfn.XLOOKUP(C37,Master_Employee[Emp_ID],Master_Employee[Department],"",0),"") | J37: =_xlfn.XLOOKUP(tbl_Transactions[[#This Row],[Type]],Type[Trans_Type],Type[Type_Code],"",0)
A38: =IFERROR(IF(C38="","",ROW()-2),"") | D38: =IFERROR(_xlfn.XLOOKUP(C38,Master_Employee[Emp_ID],Master_Employee[Name_AR],"",0),"") | E38: =IFERROR(_xlfn.XLOOKUP(C38,Master_Employee[Emp_ID],Master_Employee[Name_EN],"",0),"") | F38: =IFERROR(_xlfn.XLOOKUP(C38,Master_Employee[Emp_ID],Master_Employee[Department],"",0),"") | J38: =_xlfn.XLOOKUP(tbl_Transactions[[#This Row],[Type]],Type[Trans_Type],Type[Type_Code],"",0)
A39: =IFERROR(IF(C39="","",ROW()-2),"") | D39: =IFERROR(_xlfn.XLOOKUP(C39,Master_Employee[Emp_ID],Master_Employee[Name_AR],"",0),"") | E39: =IFERROR(_xlfn.XLOOKUP(C39,Master_Employee[Emp_ID],Master_Employee[Name_EN],"",0),"") | F39: =IFERROR(_xlfn.XLOOKUP(C39,Master_Employee[Emp_ID],Master_Employee[Department],"",0),"") | J39: =_xlfn.XLOOKUP(tbl_Transactions[[#This Row],[Type]],Type[Trans_Type],Type[Type_Code],"",0)
A40: =IFERROR(IF(C40="","",ROW()-2),"") | D40: =IFERROR(_xlfn.XLOOKUP(C40,Master_Employee[Emp_ID],Master_Employee[Name_AR],"",0),"") | E40: =IFERROR(_xlfn.XLOOKUP(C40,Master_Employee[Emp_ID],Master_Employee[Name_EN],"",0),"") | F40: =IFERROR(_xlfn.XLOOKUP(C40,Master_Employee[Emp_ID],Master_Employee[Department],"",0),"") | J40: =_xlfn.XLOOKUP(tbl_Transactions[[#This Row],[Type]],Type[Trans_Type],Type[Type_Code],"",0)
A41: =IFERROR(IF(C41="","",ROW()-2),"") | D41: =IFERROR(_xlfn.XLOOKUP(C41,Master_Employee[Emp_ID],Master_Employee[Name_AR],"",0),"") | E41: =IFERROR(_xlfn.XLOOKUP(C41,Master_Employee[Emp_ID],Master_Employee[Name_EN],"",0),"") | F41: =IFERROR(_xlfn.XLOOKUP(C41,Master_Employee[Emp_ID],Master_Employee[Department],"",0),"") | J41: =_xlfn.XLOOKUP(tbl_Transactions[[#This Row],[Type]],Type[Trans_Type],Type[Type_Code],"",0)
... A306: =IFERROR(IF(C306="","",ROW()-2),"") | D306: =IFERROR(_xlfn.XLOOKUP(C306,Master_Employee[Emp_ID],Master_Employee[Name_AR],"",0),"") | E306: =IFERROR(_xlfn.XLOOKUP(C306,Master_Employee[Emp_ID],Master_Employee[Name_EN],"",0),"") | F306: =IFERROR(_xlfn.XLOOKUP(C306,Master_Employee[Emp_ID],Master_Employee[Department],"",0),"") | J306: =_xlfn.XLOOKUP(tbl_Transactions[[#This Row],[Type]],Type[Trans_Type],Type[Type_Code],"",0)

Sheet Daily_Work
F1: 📅 Daily Work Log – سجل العمل اليومي
A2: 📌 فلتر القسم Dept Filter | D2: الإدارة
F3: =_xlfn.XLOOKUP(D2,tbl_Dept[Dept_Name],tbl_Dept[Dept_ID],"",0) -> ADM_D01
A4: م | B4: الشهر | C4: اسم الموظف بالعربي | D4: اسم الموظف بالانجليزي | E4: كود الموظف | F4: القسم | G4: المشرف | H4: اسم المشروع | I4: كود المشروع | J4: حالة الموظف | L4: عدد أيام العمل | M4: ساعات إضافية | N4: ساعات عادية | O4: تكلفة عادية | P4: تكلفة الوقت الإضافي
A5: # # | B5: Month | C5: Emp_ID | D5: Name_AR | E5: Name_EN | F5: Department | G5: Supervisor | H5: Project_Name | I5: Project_ID | J5: Emp_Status | K5: Status_Code | L5: Days_Work | M5: OT_Hrs | N5: Normal_Hrs | O5: Normal_Cost | P5: OT_Cost
A6: 1 | B6: 46082 | C6: O60 | D6: =_xlfn.XLOOKUP(Daily_Work[[#This Row],[Emp_ID]],Master_Employee[Emp_ID],Master_Employee[Name_AR],"",0) -> محمد اكبر صافي | E6: =_xlfn.XLOOKUP(Daily_Work[[#This Row],[Emp_ID]],Master_Employee[Emp_ID],Master_Employee[Name_EN],"",0) -> Muhammad Akbar Safi | F6: {=IF(Daily_Work[[#This Row],[Emp_ID]]=0,"", _xlfn.XLOOKUP(Daily_Work[[#This Row],[Emp_ID]],Master_Employee[Emp_ID],EmpDepts,"",0) )} -> الإنشاءات | G6: محمد عمران انصاري | H6: سعود وعبدالرحمن ناقادان | I6: =IF(Daily_Work[[#This Row],[Project_Name]]="","",_xlfn.XLOOKUP(Daily_Work[[#This Row],[Project_Name]],ProjectNames,ProjectList,"",0)) -> S004C | J6: Work | K6: =IF(Daily_Work[[#This Row],[Emp_Status]]="Absent",0,1) -> 1 | L6: 2 | N6: =Daily_Work[[#This Row],[Days_Work]]*8 -> 16 | O6: =IFERROR(Daily_Work[[#This Row],[Days_Work]]*_xlfn.XLOOKUP(Daily_Work[[#This Row],[Emp_ID]],Master_Employee[Emp_ID],Master_Employee[Daily_Rate],"",0),0) -> 113.33333 | P6: =IFERROR(Daily_Work[[#This Row],[OT_Hrs]]*_xlfn.XLOOKUP(Daily_Work[[#This Row],[Emp_ID]],Master_Employee[Emp_ID],Master_Employee[OT_Hr_Rate],0),0) -> 0 | Q6: مشرف القسم | S6: موظفين القسم | X6: موظفين القسم بشرطروط التلاته | AA6: Status | AD6: {=IF(Emp_Status[]="Absent",0,1)} -> 1 | AE6: 1
A7: 2 | B7: 46082 | C7: O60 | D7: =_xlfn.XLOOKUP(Daily_Work[[#This Row],[Emp_ID]],Master_Employee[Emp_ID],Master_Employee[Name_AR],"",0) -> محمد اكبر صافي | E7: =_xlfn.XLOOKUP(Daily_Work[[#This Row],[Emp_ID]],Master_Employee[Emp_ID],Master_Employee[Name_EN],"",0) -> Muhammad Akbar Safi | F7: {=IF(Daily_Work[[#This Row],[Emp_ID]]=0,"", _xlfn.XLOOKUP(Daily_Work[[#This Row],[Emp_ID]],Master_Employee[Emp_ID],EmpDepts,"",0) )} -> الإنشاءات | G7: محمد عمران انصاري | H7: سعود الفهد | I7: =IF(Daily_Work[[#This Row],[Project_Name]]="","",_xlfn.XLOOKUP(Daily_Work[[#This Row],[Project_Name]],ProjectNames,ProjectList,"",0)) -> S001F | J7: Work | K7: =IF(Daily_Work[[#This Row],[Emp_Status]]="Absent",0,1) -> 1 | L7: 3 | M7: 4 | N7: =Daily_Work[[#This Row],[Days_Work]]*8 -> 24 | O7: =IFERROR(Daily_Work[[#This Row],[Days_Work]]*_xlfn.XLOOKUP(Daily_Work[[#This Row],[Emp_ID]],Master_Employee[Emp_ID],Master_Employee[Daily_Rate],"",0),0) -> 170 | P7: =IFERROR(Daily_Work[[#This Row],[OT_Hrs]]*_xlfn.XLOOKUP(Daily_Work[[#This Row],[Emp_ID]],Master_Employee[Emp_ID],Master_Employee[OT_Hr_Rate],0),0) -> 28.333333 | U7: ياسر كمال | AA7: W_01 | AC7: يعمل | AD7: 1 | AE7: 1
A8: 3 | B8: 46082 | C8: O60 | D8: =_xlfn.XLOOKUP(Daily_Work[[#This Row],[Emp_ID]],Master_Employee[Emp_ID],Master_Employee[Name_AR],"",0) -> محمد اكبر صافي | E8: =_xlfn.XLOOKUP(Daily_Work[[#This Row],[Emp_ID]],Master_Employee[Emp_ID],Master_Employee[Name_EN],"",0) -> Muhammad Akbar Safi | F8: {=IF(Daily_Work[[#This Row],[Emp_ID]]=0,"", _xlfn.XLOOKUP(Daily_Work[[#This Row],[Emp_ID]],Master_Employee[Emp_ID],EmpDepts,"",0) )} -> الإنشاءات | G8: ﻣﺪ ﺟﻠﺪﻳﻦ ﻣﻴﺎ | H8: حمد المعاضيد | I8: =IF(Daily_Work[[#This Row],[Project_Name]]="","",_xlfn.XLOOKUP(Daily_Work[[#This Row],[Project_Name]],ProjectNames,ProjectList,"",0)) -> H001C | J8: Work | K8: =IF(Daily_Work[[#This Row],[Emp_Status]]="Absent",0,1) -> 1 | L8: 5 | M8: 11 | N8: =Daily_Work[[#This Row],[Days_Work]]*8 -> 40 | O8: =IFERROR(Daily_Work[[#This Row],[Days_Work]]*_xlfn.XLOOKUP(Daily_Work[[#This Row],[Emp_ID]],Master_Employee[Emp_ID],Master_Employee[Daily_Rate],"",0),0) -> 283.33333 | P8: =IFERROR(Daily_Work[[#This Row],[OT_Hrs]]*_xlfn.XLOOKUP(Daily_Work[[#This Row],[Emp_ID]],Master_Employee[Emp_ID],Master_Employee[OT_Hr_Rate],0),0) -> 77.916667 | Q8: {=_xlfn._xlws.FILTER( Master_Employee[Name_AR], IF(OR(D2="", D2="كل الأقسام"), (Master_Employee[Job_Title]="مشرف موقع"), (Master_Employee[Department]=D2) * (Master_Employee[Job_Title]="مشرف موقع") ), "لا يوجد مشرفين" )} -> لا يوجد مشرفين | S8: {=_xlfn._xlws.FILTER( Master_Employee[Name_AR], IF(D2="All_D11", (Master_Employee[Status_Code]="W_01"), (Master_Employee[Department]=D2) * (Master_Employee[Status_Code]="W_01") ), "لا يوجد عمال" )} -> ﻣﺎﻣﻮﻥ ﺍﺣﻤﺪ ﺷﻮﻧﻮ ﻣﻴﺎﻩ | X8: {=_xlfn._xlws.FILTER( Master_Employee[Emp_ID], IF(D2="All_D11", ISNUMBER(MATCH(Master_Employee[Status_Code],Valid_Status[],0)), (Master_Employee[Department]=D2) * ISNUMBER(MATCH(Master_Employee[Status_Code],Valid_Status[],0)) ), "لا يوجد عمال" )} -> 146 | AA8: B_01 | AC8: عودة للعمل | AD8: 1 | AE8: 1
A9: 4 | B9: 46082 | C9: O60 | D9: =_xlfn.XLOOKUP(Daily_Work[[#This Row],[Emp_ID]],Master_Employee[Emp_ID],Master_Employee[Name_AR],"",0) -> محمد اكبر صافي | E9: =_xlfn.XLOOKUP(Daily_Work[[#This Row],[Emp_ID]],Master_Employee[Emp_ID],Master_Employee[Name_EN],"",0) -> Muhammad Akbar Safi | F9: {=IF(Daily_Work[[#This Row],[Emp_ID]]=0,"", _xlfn.XLOOKUP(Daily_Work[[#This Row],[Emp_ID]],Master_Employee[Emp_ID],EmpDepts,"",0) )} -> الإنشاءات | G9: ﻣﺪ ﺟﻠﺪﻳﻦ ﻣﻴﺎ | H9: عبد الهادي السهلي | I9: =IF(Daily_Work[[#This Row],[Project_Name]]="","",_xlfn.XLOOKUP(Daily_Work[[#This Row],[Project_Name]],ProjectNames,ProjectList,"",0)) -> A005C | J9: Work | K9: =IF(Daily_Work[[#This Row],[Emp_Status]]="Absent",0,1) -> 1 | L9: 4 | N9: =Daily_Work[[#This Row],[Days_Work]]*8 -> 32 | O9: =IFERROR(Daily_Work[[#This Row],[Days_Work]]*_xlfn.XLOOKUP(Daily_Work[[#This Row],[Emp_ID]],Master_Employee[Emp_ID],Master_Employee[Daily_Rate],"",0),0) -> 226.66667 | P9: =IFERROR(Daily_Work[[#This Row],[OT_Hrs]]*_xlfn.XLOOKUP(Daily_Work[[#This Row],[Emp_ID]],Master_Employee[Emp_ID],Master_Employee[OT_Hr_Rate],0),0) -> 0 | S9: صلاح عبدالرحمن الحاج احمد | X9: O304 | AA9: N_01 | AC9: تعيين جديد | AD9: 1 | AE9: 1
A10: 5 | B10: 46082 | C10: O60 | D10: =_xlfn.XLOOKUP(Daily_Work[[#This Row],[Emp_ID]],Master_Employee[Emp_ID],Master_Employee[Name_AR],"",0) -> محمد اكبر صافي | E10: =_xlfn.XLOOKUP(Daily_Work[[#This Row],[Emp_ID]],Master_Employee[Emp_ID],Master_Employee[Name_EN],"",0) -> Muhammad Akbar Safi | F10: {=IF(Daily_Work[[#This Row],[Emp_ID]]=0,"", _xlfn.XLOOKUP(Daily_Work[[#This Row],[Emp_ID]],Master_Employee[Emp_ID],EmpDepts,"",0) )} -> الإنشاءات | G10: ﻣﺪ ﺟﻠﺪﻳﻦ ﻣﻴﺎ | H10: فهد ونواف الكربى | I10: =IF(Daily_Work[[#This Row],[Project_Name]]="","",_xlfn.XLOOKUP(Daily_Work[[#This Row],[Project_Name]],ProjectNames,ProjectList,"",0)) -> F006C | J10: Work | K10: =IF(Daily_Work[[#This Row],[Emp_Status]]="Absent",0,1) -> 1 | L10: 10 | M10: 12 | N10: =Daily_Work[[#This Row],[Days_Work]]*8 -> 80 | O10: =IFERROR(Daily_Work[[#This Row],[Days_Work]]*_xlfn.XLOOKUP(Daily_Work[[#This Row],[Emp_ID]],Master_Employee[Emp_ID],Master_Employee[Daily_Rate],"",0),0) -> 566.66667 | P10: =IFERROR(Daily_Work[[#This Row],[OT_Hrs]]*_xlfn.XLOOKUP(Daily_Work[[#This Row],[Emp_ID]],Master_Employee[Emp_ID],Master_Employee[OT_Hr_Rate],0),0) -> 85 | S10: منصور عالم مجنو مياه | X10: 494 | AD10: 1 | AE10: 1
A11: 6 | B11: 46082 | C11: O60 | D11: =_xlfn.XLOOKUP(Daily_Work[[#This Row],[Emp_ID]],Master_Employee[Emp_ID],Master_Employee[Name_AR],"",0) -> محمد اكبر صافي | E11: =_xlfn.XLOOKUP(Daily_Work[[#This Row],[Emp_ID]],Master_Employee[Emp_ID],Master_Employee[Name_EN],"",0) -> Muhammad Akbar Safi | F11: {=IF(Daily_Work[[#This Row],[Emp_ID]]=0,"", _xlfn.XLOOKUP(Daily_Work[[#This Row],[Emp_ID]],Master_Employee[Emp_ID],EmpDepts,"",0) )} -> الإنشاءات | G11: ﻣﺪ ﺟﻠﺪﻳﻦ ﻣﻴﺎ | H11: عبد الهادي السهلي | I11: =IF(Daily_Work[[#This Row],[Project_Name]]="","",_xlfn.XLOOKUP(Daily_Work[[#This Row],[Project_Name]],ProjectNames,ProjectList,"",0)) -> A005C | J11: Absent | K11: =IF(Daily_Work[[#This Row],[Emp_Status]]="Absent",0,1) -> 0 | N11: =Daily_Work[[#This Row],[Days_Work]]*8 -> 0 | O11: =IFERROR(Daily_Work[[#This Row],[Days_Work]]*_xlfn.XLOOKUP(Daily_Work[[#This Row],[Emp_ID]],Master_Employee[Emp_ID],Master_Employee[Daily_Rate],"",0),0) -> 0 | P11: =IFERROR(Daily_Work[[#This Row],[OT_Hrs]]*_xlfn.XLOOKUP(Daily_Work[[#This Row],[Emp_ID]],Master_Employee[Emp_ID],Master_Employee[OT_Hr_Rate],0),0) -> 0 | S11: أرسلان احمد الطاف حسين | X11: O246 | AD11: 1 | AE11: 1
A12: 7 | B12: 46082 | C12: O60 | D12: =_xlfn.XLOOKUP(Daily_Work[[#This Row],[Emp_ID]],Master_Employee[Emp_ID],Master_Employee[Name_AR],"",0) -> محمد اكبر صافي | E12: =_xlfn.XLOOKUP(Daily_Work[[#This Row],[Emp_ID]],Master_Employee[Emp_ID],Master_Employee[Name_EN],"",0) -> Muhammad Akbar Safi | F12: {=IF(Daily_Work[[#This Row],[Emp_ID]]=0,"", _xlfn.XLOOKUP(Daily_Work[[#This Row],[Emp_ID]],Master_Employee[Emp_ID],EmpDepts,"",0) )} -> الإنشاءات | G12: ﻣﺪ ﺟﻠﺪﻳﻦ ﻣﻴﺎ | H12: سعد الدوسري | I12: =IF(Daily_Work[[#This Row],[Project_Name]]="","",_xlfn.XLOOKUP(Daily_Work[[#This Row],[Project_Name]],ProjectNames,ProjectList,"",0)) -> S005C | J12: Friday | K12: =IF(Daily_Work[[#This Row],[Emp_Status]]="Absent",0,1) -> 1 | L12: 3 | N12: =Daily_Work[[#This Row],[Days_Work]]*8 -> 24 | O12: =IFERROR(Daily_Work[[#This Row],[Days_Work]]*_xlfn.XLOOKUP(Daily_Work[[#This Row],[Emp_ID]],Master_Employee[Emp_ID],Master_Employee[Daily_Rate],"",0),0) -> 170 | P12: =IFERROR(Daily_Work[[#This Row],[OT_Hrs]]*_xlfn.XLOOKUP(Daily_Work[[#This Row],[Emp_ID]],Master_Employee[Emp_ID],Master_Employee[OT_Hr_Rate],0),0) -> 0 | S12: محمد أبو محمد حانف | X12: O309 | AD12: 1 | AE12: 1
A13: 8 | B13: 46082 | C13: O60 | D13: =_xlfn.XLOOKUP(Daily_Work[[#This Row],[Emp_ID]],Master_Employee[Emp_ID],Master_Employee[Name_AR],"",0) -> محمد اكبر صافي | E13: =_xlfn.XLOOKUP(Daily_Work[[#This Row],[Emp_ID]],Master_Employee[Emp_ID],Master_Employee[Name_EN],"",0) -> Muhammad Akbar Safi | F13: {=IF(Daily_Work[[#This Row],[Emp_ID]]=0,"", _xlfn.XLOOKUP(Daily_Work[[#This Row],[Emp_ID]],Master_Employee[Emp_ID],EmpDepts,"",0) )} -> الإنشاءات | G13: ﻣﺪ ﺟﻠﺪﻳﻦ ﻣﻴﺎ | H13: هزاع مبارك الهاجري | I13: =IF(Daily_Work[[#This Row],[Project_Name]]="","",_xlfn.XLOOKUP(Daily_Work[[#This Row],[Project_Name]],ProjectNames,ProjectList,"",0)) -> H005C | J13: Friday | K13: =IF(Daily_Work[[#This Row],[Emp_Status]]="Absent",0,1) -> 1 | L13: 2 | N13: =Daily_Work[[#This Row],[Days_Work]]*8 -> 16 | O13: =IFERROR(Daily_Work[[#This Row],[Days_Work]]*_xlfn.XLOOKUP(Daily_Work[[#This Row],[Emp_ID]],Master_Employee[Emp_ID],Master_Employee[Daily_Rate],"",0),0) -> 113.33333 | P13: =IFERROR(Daily_Work[[#This Row],[OT_Hrs]]*_xlfn.XLOOKUP(Daily_Work[[#This Row],[Emp_ID]],Master_Employee[Emp_ID],Master_Employee[OT_Hr_Rate],0),0) -> 0 | R13: =SUM(O6:O13) -> 1643.3333 | S13: =SUM(O6:O13)+SUM(P6:P13) -> 1834.5833 | X13: 314 | AD13: 1 | AE13: 1
A14: 9 | B14: 46082 | C14: O61 | D14: =_xlfn.XLOOKUP(Daily_Work[[#This Row],[Emp_ID]],Master_Employee[Emp_ID],Master_Employee[Name_AR],"",0) -> عبدالحكيم رستم انصاري | E14: =_xlfn.XLOOKUP(Daily_Work[[#This Row],[Emp_ID]],Master_Employee[Emp_ID],Master_Employee[Name_EN],"",0) -> Abdul Hakim Rustam Ansari | F14: {=IF(Daily_Work[[#This Row],[Emp_ID]]=0,"", _xlfn.XLOOKUP(Daily_Work[[#This Row],[Emp_ID]],Master_Employee[Emp_ID],EmpDepts,"",0) )} -> الإنشاءات | G14: ﻣﺪ ﺟﻠﺪﻳﻦ ﻣﻴﺎ | H14: سعود وعبدالرحمن ناقادان | I14: =IF(Daily_Work[[#This Row],[Project_Name]]="","",_xlfn.XLOOKUP(Daily_Work[[#This Row],[Project_Name]],ProjectNames,ProjectList,"",0)) -> S004C | J14: Work | K14: =IF(Daily_Work[[#This Row],[Emp_Status]]="Absent",0,1) -> 1 | L14: 2 | N14: =Daily_Work[[#This Row],[Days_Work]]*8 -> 16 | O14: =IFERROR(Daily_Work[[#This Row],[Days_Work]]*_xlfn.XLOOKUP(Daily_Work[[#This Row],[Emp_ID]],Master_Employee[Emp_ID],Master_Employee[Daily_Rate],"",0),0) -> 93.333333 | P14: =IFERROR(Daily_Work[[#This Row],[OT_Hrs]]*_xlfn.XLOOKUP(Daily_Work[[#This Row],[Emp_ID]],Master_Employee[Emp_ID],Master_Employee[OT_Hr_Rate],0),0) -> 0 | AD14: 1 | AE14: 1
A15: 10 | B15: 46082 | C15: O61 | D15: =_xlfn.XLOOKUP(Daily_Work[[#This Row],[Emp_ID]],Master_Employee[Emp_ID],Master_Employee[Name_AR],"",0) -> عبدالحكيم رستم انصاري | E15: =_xlfn.XLOOKUP(Daily_Work[[#This Row],[Emp_ID]],Master_Employee[Emp_ID],Master_Employee[Name_EN],"",0) -> Abdul Hakim Rustam Ansari | F15: {=IF(Daily_Work[[#This Row],[Emp_ID]]=0,"", _xlfn.XLOOKUP(Daily_Work[[#This Row],[Emp_ID]],Master_Employee[Emp_ID],EmpDepts,"",0) )} -> الإنشاءات | G15: ﻣﺪ ﺟﻠﺪﻳﻦ ﻣﻴﺎ | H15: هزاع مبارك الهاجري | I15: =IF(Daily_Work[[#This Row],[Project_Name]]="","",_xlfn.XLOOKUP(Daily_Work[[#This Row],[Project_Name]],ProjectNames,ProjectList,"",0)) -> H005C | J15: Work | K15: =IF(Daily_Work[[#This Row],[Emp_Status]]="Absent",0,1) -> 1 | L15: 1 | M15: 3 | N15: =Daily_Work[[#This Row],[Days_Work]]*8 -> 8 | O15: =IFERROR(Daily_Work[[#This Row],[Days_Work]]*_xlfn.XLOOKUP(Daily_Work[[#This Row],[Emp_ID]],Master_Employee[Emp_ID],Master_Employee[Daily_Rate],"",0),0) -> 46.666667 | P15: =IFERROR(Daily_Work[[#This Row],[OT_Hrs]]*_xlfn.XLOOKUP(Daily_Work[[#This Row],[Emp_ID]],Master_Employee[Emp_ID],Master_Employee[OT_Hr_Rate],0),0) -> 17.5 | R15: =R13+S15 -> 1835.0333 | S15: =27*7.1 -> 191.7
A16: 11 | B16: 46082 | C16: O61 | D16: =_xlfn.XLOOKUP(Daily_Work[[#This Row],[Emp_ID]],Master_Employee[Emp_ID],Master_Employee[Name_AR],"",0) -> عبدالحكيم رستم انصاري | E16: =_xlfn.XLOOKUP(Daily_Work[[#This Row],[Emp_ID]],Master_Employee[Emp_ID],Master_Employee[Name_EN],"",0) -> Abdul Hakim Rustam Ansari | F16: {=IF(Daily_Work[[#This Row],[Emp_ID]]=0,"", _xlfn.XLOOKUP(Daily_Work[[#This Row],[Emp_ID]],Master_Employee[Emp_ID],EmpDepts,"",0) )} -> الإنشاءات | G16: ﻣﺪ ﺟﻠﺪﻳﻦ ﻣﻴﺎ | H16: فهد ونواف الكربى | I16: =IF(Daily_Work[[#This Row],[Project_Name]]="","",_xlfn.XLOOKUP(Daily_Work[[#This Row],[Project_Name]],ProjectNames,ProjectList,"",0)) -> F006C | J16: Work | K16: =IF(Daily_Work[[#This Row],[Emp_Status]]="Absent",0,1) -> 1 | L16: 9 | M16: 12 | N16: =Daily_Work[[#This Row],[Days_Work]]*8 -> 72 | O16: =IFERROR(Daily_Work[[#This Row],[Days_Work]]*_xlfn.XLOOKUP(Daily_Work[[#This Row],[Emp_ID]],Master_Employee[Emp_ID],Master_Employee[Daily_Rate],"",0),0) -> 420 | P16: =IFERROR(Daily_Work[[#This Row],[OT_Hrs]]*_xlfn.XLOOKUP(Daily_Work[[#This Row],[Emp_ID]],Master_Employee[Emp_ID],Master_Employee[OT_Hr_Rate],0),0) -> 70
A17: 12 | B17: 46082 | C17: O61 | D17: =_xlfn.XLOOKUP(Daily_Work[[#This Row],[Emp_ID]],Master_Employee[Emp_ID],Master_Employee[Name_AR],"",0) -> عبدالحكيم رستم انصاري | E17: =_xlfn.XLOOKUP(Daily_Work[[#This Row],[Emp_ID]],Master_Employee[Emp_ID],Master_Employee[Name_EN],"",0) -> Abdul Hakim Rustam Ansari | F17: {=IF(Daily_Work[[#This Row],[Emp_ID]]=0,"", _xlfn.XLOOKUP(Daily_Work[[#This Row],[Emp_ID]],Master_Employee[Emp_ID],EmpDepts,"",0) )} -> الإنشاءات | G17: ﻣﺪ ﺟﻠﺪﻳﻦ ﻣﻴﺎ | H17: حمد عايض حسين الاحبابي | I17: =IF(Daily_Work[[#This Row],[Project_Name]]="","",_xlfn.XLOOKUP(Daily_Work[[#This Row],[Project_Name]],ProjectNames,ProjectList,"",0)) -> H003C | J17: Work | K17: =IF(Daily_Work[[#This Row],[Emp_Status]]="Absent",0,1) -> 1 | L17: 2 | N17: =Daily_Work[[#This Row],[Days_Work]]*8 -> 16 | O17: =IFERROR(Daily_Work[[#This Row],[Days_Work]]*_xlfn.XLOOKUP(Daily_Work[[#This Row],[Emp_ID]],Master_Employee[Emp_ID],Master_Employee[Daily_Rate],"",0),0) -> 93.333333 | P17: =IFERROR(Daily_Work[[#This Row],[OT_Hrs]]*_xlfn.XLOOKUP(Daily_Work[[#This Row],[Emp_ID]],Master_Employee[Emp_ID],Master_Employee[OT_Hr_Rate],0),0) -> 0 | R17: =SUM(L6:L13) -> 29 | S17: =S15+R13 -> 1835.0333
A18: 13 | B18: 46082 | C18: O61 | D18: =_xlfn.XLOOKUP(Daily_Work[[#This Row],[Emp_ID]],Master_Employee[Emp_ID],Master_Employee[Name_AR],"",0) -> عبدالحكيم رستم انصاري | E18: =_xlfn.XLOOKUP(Daily_Work[[#This Row],[Emp_ID]],Master_Employee[Emp_ID],Master_Employee[Name_EN],"",0) -> Abdul Hakim Rustam Ansari | F18: {=IF(Daily_Work[[#This Row],[Emp_ID]]=0,"", _xlfn.XLOOKUP(Daily_Work[[#This Row],[Emp_ID]],Master_Employee[Emp_ID],EmpDepts,"",0) )} -> الإنشاءات | G18: ﻣﺪ ﺟﻠﺪﻳﻦ ﻣﻴﺎ | H18: حمد المعاضيد | I18: =IF(Daily_Work[[#This Row],[Project_Name]]="","",_xlfn.XLOOKUP(Daily_Work[[#This Row],[Project_Name]],ProjectNames,ProjectList,"",0)) -> H001C | J18: Work | K18: =IF(Daily_Work[[#This Row],[Emp_Status]]="Absent",0,1) -> 1 | L18: 5 | M18: 11 | N18: =Daily_Work[[#This Row],[Days_Work]]*8 -> 40 | O18: =IFERROR(Daily_Work[[#This Row],[Days_Work]]*_xlfn.XLOOKUP(Daily_Work[[#This Row],[Emp_ID]],Master_Employee[Emp_ID],Master_Employee[Daily_Rate],"",0),0) -> 233.33333 | P18: =IFERROR(Daily_Work[[#This Row],[OT_Hrs]]*_xlfn.XLOOKUP(Daily_Work[[#This Row],[Emp_ID]],Master_Employee[Emp_ID],Master_Employee[OT_Hr_Rate],0),0) -> 64.166667
A19: 14 | B19: 46082 | C19: O61 | D19: =_xlfn.XLOOKUP(Daily_Work[[#This Row],[Emp_ID]],Master_Employee[Emp_ID],Master_Employee[Name_AR],"",0) -> عبدالحكيم رستم انصاري | E19: =_xlfn.XLOOKUP(Daily_Work[[#This Row],[Emp_ID]],Master_Employee[Emp_ID],Master_Employee[Name_EN],"",0) -> Abdul Hakim Rustam Ansari | F19: {=IF(Daily_Work[[#This Row],[Emp_ID]]=0,"", _xlfn.XLOOKUP(Daily_Work[[#This Row],[Emp_ID]],Master_Employee[Emp_ID],EmpDepts,"",0) )} -> الإنشاءات | G19: ﻣﺪ ﺟﻠﺪﻳﻦ ﻣﻴﺎ | H19: عبد الهادي السهلي | I19: =IF(Daily_Work[[#This Row],[Project_Name]]="","",_xlfn.XLOOKUP(Daily_Work[[#This Row],[Project_Name]],ProjectNames,ProjectList,"",0)) -> A005C | J19: Work | K19: =IF(Daily_Work[[#This Row],[Emp_Status]]="Absent",0,1) -> 1 | L19: 5 | M19: 8 | N19: =Daily_Work[[#This Row],[Days_Work]]*8 -> 40 | O19: =IFERROR(Daily_Work[[#This Row],[Days_Work]]*_xlfn.XLOOKUP(Daily_Work[[#This Row],[Emp_ID]],Master_Employee[Emp_ID],Master_Employee[Daily_Rate],"",0),0) -> 233.33333 | P19: =IFERROR(Daily_Work[[#This Row],[OT_Hrs]]*_xlfn.XLOOKUP(Daily_Work[[#This Row],[Emp_ID]],Master_Employee[Emp_ID],Master_Employee[OT_Hr_Rate],0),0) -> 46.666667 | R19: 25
A20: 15 | B20: 46082 | C20: O61 | D20: =_xlfn.XLOOKUP(Daily_Work[[#This Row],[Emp_ID]],Master_Employee[Emp_ID],Master_Employee[Name_AR],"",0) -> عبدالحكيم رستم انصاري | E20: =_xlfn.XLOOKUP(Daily_Work[[#This Row],[Emp_ID]],Master_Employee[Emp_ID],Master_Employee[Name_EN],"",0) -> Abdul Hakim Rustam Ansari | F20: {=IF(Daily_Work[[#This Row],[Emp_ID]]=0,"", _xlfn.XLOOKUP(Daily_Work[[#This Row],[Emp_ID]],Master_Employee[Emp_ID],EmpDepts,"",0) )} -> الإنشاءات | G20: ﻣﺪ ﺟﻠﺪﻳﻦ ﻣﻴﺎ | H20: فهد ونواف الكربى | I20: =IF(Daily_Work[[#This Row],[Project_Name]]="","",_xlfn.XLOOKUP(Daily_Work[[#This Row],[Project_Name]],ProjectNames,ProjectList,"",0)) -> F006C | J20: Friday | K20: =IF(Daily_Work[[#This Row],[Emp_Status]]="Absent",0,1) -> 1 | L20: 4 | M20: 1 | N20: =Daily_Work[[#This Row],[Days_Work]]*8 -> 32 | O20: =IFERROR(Daily_Work[[#This Row],[Days_Work]]*_xlfn.XLOOKUP(Daily_Work[[#This Row],[Emp_ID]],Master_Employee[Emp_ID],Master_Employee[Daily_Rate],"",0),0) -> 186.66667 | P20: =IFERROR(Daily_Work[[#This Row],[OT_Hrs]]*_xlfn.XLOOKUP(Daily_Work[[#This Row],[Emp_ID]],Master_Employee[Emp_ID],Master_Employee[OT_Hr_Rate],0),0) -> 5.8333333 | R20: 4
A21: 16 | B21: 46082 | C21: 243 | D21: =_xlfn.XLOOKUP(Daily_Work[[#This Row],[Emp_ID]],Master_Employee[Emp_ID],Master_Employee[Name_AR],"",0) -> محمد عزيز لاحق | E21: =_xlfn.XLOOKUP(Daily_Work[[#This Row],[Emp_ID]],Master_Employee[Emp_ID],Master_Employee[Name_EN],"",0) -> 0 | F21: {=IF(Daily_Work[[#This Row],[Emp_ID]]=0,"", _xlfn.XLOOKUP(Daily_Work[[#This Row],[Emp_ID]],Master_Employee[Emp_ID],EmpDepts,"",0) )} -> التشطيبات | G21: ﻣﺪ ﺟﻠﺪﻳﻦ ﻣﻴﺎ | H21: سعود الفهد | I21: =IF(Daily_Work[[#This Row],[Project_Name]]="","",_xlfn.XLOOKUP(Daily_Work[[#This Row],[Project_Name]],ProjectNames,ProjectList,"",0)) -> S001F | J21: Work | K21: =IF(Daily_Work[[#This Row],[Emp_Status]]="Absent",0,1) -> 1 | L21: 10 | M21: 1 | N21: =Daily_Work[[#This Row],[Days_Work]]*8 -> 80 | O21: =IFERROR(Daily_Work[[#This Row],[Days_Work]]*_xlfn.XLOOKUP(Daily_Work[[#This Row],[Emp_ID]],Master_Employee[Emp_ID],Master_Employee[Daily_Rate],"",0),0) -> 466.66667 | P21: =IFERROR(Daily_Work[[#This Row],[OT_Hrs]]*_xlfn.XLOOKUP(Daily_Work[[#This Row],[Emp_ID]],Master_Employee[Emp_ID],Master_Employee[OT_Hr_Rate],0),0) -> 4.1666667
A22: 17 | B22: 46082 | C22: 243 | D22: =_xlfn.XLOOKUP(Daily_Work[[#This Row],[Emp_ID]],Master_Employee[Emp_ID],Master_Employee[Name_AR],"",0) -> محمد عزيز لاحق | E22: =_xlfn.XLOOKUP(Daily_Work[[#This Row],[Emp_ID]],Master_Employee[Emp_ID],Master_Employee[Name_EN],"",0) -> 0 | F22: {=IF(Daily_Work[[#This Row],[Emp_ID]]=0,"", _xlfn.XLOOKUP(Daily_Work[[#This Row],[Emp_ID]],Master_Employee[Emp_ID],EmpDepts,"",0) )} -> التشطيبات | G22: ﻣﺪ ﺟﻠﺪﻳﻦ ﻣﻴﺎ | H22: سعيد صالح الجحيش | I22: =IF(Daily_Work[[#This Row],[Project_Name]]="","",_xlfn.XLOOKUP(Daily_Work[[#This Row],[Project_Name]],ProjectNames,ProjectList,"",0)) -> S002F | J22: Work | K22: =IF(Daily_Work[[#This Row],[Emp_Status]]="Absent",0,1) -> 1 | L22: 12 | M22: 3 | N22: =Daily_Work[[#This Row],[Days_Work]]*8 -> 96 | O22: =IFERROR(Daily_Work[[#This Row],[Days_Work]]*_xlfn.XLOOKUP(Daily_Work[[#This Row],[Emp_ID]],Master_Employee[Emp_ID],Master_Employee[Daily_Rate],"",0),0) -> 560 | P22: =IFERROR(Daily_Work[[#This Row],[OT_Hrs]]*_xlfn.XLOOKUP(Daily_Work[[#This Row],[Emp_ID]],Master_Employee[Emp_ID],Master_Employee[OT_Hr_Rate],0),0) -> 12.5 | R22: =SUM(O14:O20)+SUM(P14:P20) -> 1510.8333
A23: 18 | B23: 46082 | C23: 243 | D23: =_xlfn.XLOOKUP(Daily_Work[[#This Row],[Emp_ID]],Master_Employee[Emp_ID],Master_Employee[Name_AR],"",0) -> محمد عزيز لاحق | E23: =_xlfn.XLOOKUP(Daily_Work[[#This Row],[Emp_ID]],Master_Employee[Emp_ID],Master_Employee[Name_EN],"",0) -> 0 | F23: {=IF(Daily_Work[[#This Row],[Emp_ID]]=0,"", _xlfn.XLOOKUP(Daily_Work[[#This Row],[Emp_ID]],Master_Employee[Emp_ID],EmpDepts,"",0) )} -> التشطيبات | G23: ﻣﺪ ﺟﻠﺪﻳﻦ ﻣﻴﺎ | H23: جابر قحيز المري | I23: =IF(Daily_Work[[#This Row],[Project_Name]]="","",_xlfn.XLOOKUP(Daily_Work[[#This Row],[Project_Name]],ProjectNames,ProjectList,"",0)) -> J001F | J23: Friday | K23: =IF(Daily_Work[[#This Row],[Emp_Status]]="Absent",0,1) -> 1 | L23: 4 | M23: 5 | N23: =Daily_Work[[#This Row],[Days_Work]]*8 -> 32 | O23: =IFERROR(Daily_Work[[#This Row],[Days_Work]]*_xlfn.XLOOKUP(Daily_Work[[#This Row],[Emp_ID]],Master_Employee[Emp_ID],Master_Employee[Daily_Rate],"",0),0) -> 186.66667 | P23: =IFERROR(Daily_Work[[#This Row],[OT_Hrs]]*_xlfn.XLOOKUP(Daily_Work[[#This Row],[Emp_ID]],Master_Employee[Emp_ID],Master_Employee[OT_Hr_Rate],0),0) -> 20.833333 | R23: =SUM(O14:O20) -> 1306.6667
A24: 19 | B24: 46082 | C24: 243 | D24: =_xlfn.XLOOKUP(Daily_Work[[#This Row],[Emp_ID]],Master_Employee[Emp_ID],Master_Employee[Name_AR],"",0) -> محمد عزيز لاحق | E24: =_xlfn.XLOOKUP(Daily_Work[[#This Row],[Emp_ID]],Master_Employee[Emp_ID],Master_Employee[Name_EN],"",0) -> 0 | F24: {=IF(Daily_Work[[#This Row],[Emp_ID]]=0,"", _xlfn.XLOOKUP(Daily_Work[[#This Row],[Emp_ID]],Master_Employee[Emp_ID],EmpDepts,"",0) )} -> التشطيبات | G24: ﻣﺪ ﺟﻠﺪﻳﻦ ﻣﻴﺎ | H24: عبدالعزيز قحيز المري | I24: =IF(Daily_Work[[#This Row],[Project_Name]]="","",_xlfn.XLOOKUP(Daily_Work[[#This Row],[Project_Name]],ProjectNames,ProjectList,"",0)) -> A001F | J24: Work | K24: =IF(Daily_Work[[#This Row],[Emp_Status]]="Absent",0,1) -> 1 | L24: 4 | N24: =Daily_Work[[#This Row],[Days_Work]]*8 -> 32 | O24: =IFERROR(Daily_Work[[#This Row],[Days_Work]]*_xlfn.XLOOKUP(Daily_Work[[#This Row],[Emp_ID]],Master_Employee[Emp_ID],Master_Employee[Daily_Rate],"",0),0) -> 186.66667 | P24: =IFERROR(Daily_Work[[#This Row],[OT_Hrs]]*_xlfn.XLOOKUP(Daily_Work[[#This Row],[Emp_ID]],Master_Employee[Emp_ID],Master_Employee[OT_Hr_Rate],0),0) -> 0
A25: 20 | B25: 46082 | C25: 389 | D25: =_xlfn.XLOOKUP(Daily_Work[[#This Row],[Emp_ID]],Master_Employee[Emp_ID],Master_Employee[Name_AR],"",0) -> محمد نور نبي | E25: =_xlfn.XLOOKUP(Daily_Work[[#This Row],[Emp_ID]],Master_Employee[Emp_ID],Master_Employee[Name_EN],"",0) -> 0 | F25: {=IF(Daily_Work[[#This Row],[Emp_ID]]=0,"", _xlfn.XLOOKUP(Daily_Work[[#This Row],[Emp_ID]],Master_Employee[Emp_ID],EmpDepts,"",0) )} -> التشطيبات | G25: ﻣﺪ ﺟﻠﺪﻳﻦ ﻣﻴﺎ | H25: عبدالهادي الماجد | I25: =IF(Daily_Work[[#This Row],[Project_Name]]="","",_xlfn.XLOOKUP(Daily_Work[[#This Row],[Project_Name]],ProjectNames,ProjectList,"",0)) -> A002F | J25: Work | K25: =IF(Daily_Work[[#This Row],[Emp_Status]]="Absent",0,1) -> 1 | L25: 10 | M25: 2 | N25: =Daily_Work[[#This Row],[Days_Work]]*8 -> 80 | O25: =IFERROR(Daily_Work[[#This Row],[Days_Work]]*_xlfn.XLOOKUP(Daily_Work[[#This Row],[Emp_ID]],Master_Employee[Emp_ID],Master_Employee[Daily_Rate],"",0),0) -> 433.33333 | P25: =IFERROR(Daily_Work[[#This Row],[OT_Hrs]]*_xlfn.XLOOKUP(Daily_Work[[#This Row],[Emp_ID]],Master_Employee[Emp_ID],Master_Employee[OT_Hr_Rate],0),0) -> 8.3333333
A26: 21 | B26: 46082 | C26: 389 | D26: =_xlfn.XLOOKUP(Daily_Work[[#This Row],[Emp_ID]],Master_Employee[Emp_ID],Master_Employee[Name_AR],"",0) -> محمد نور نبي | E26: =_xlfn.XLOOKUP(Daily_Work[[#This Row],[Emp_ID]],Master_Employee[Emp_ID],Master_Employee[Name_EN],"",0) -> 0 | F26: {=IF(Daily_Work[[#This Row],[Emp_ID]]=0,"", _xlfn.XLOOKUP(Daily_Work[[#This Row],[Emp_ID]],Master_Employee[Emp_ID],EmpDepts,"",0) )} -> التشطيبات | G26: ﻣﺪ ﺟﻠﺪﻳﻦ ﻣﻴﺎ | H26: مصطفى | I26: =IF(Daily_Work[[#This Row],[Project_Name]]="","",_xlfn.XLOOKUP(Daily_Work[[#This Row],[Project_Name]],ProjectNames,ProjectList,"",0)) -> EF0F | J26: Work | K26: =IF(Daily_Work[[#This Row],[Emp_Status]]="Absent",0,1) -> 1 | L26: 16 | M26: 6 | N26: =Daily_Work[[#This Row],[Days_Work]]*8 -> 128 | O26: =IFERROR(Daily_Work[[#This Row],[Days_Work]]*_xlfn.XLOOKUP(Daily_Work[[#This Row],[Emp_ID]],Master_Employee[Emp_ID],Master_Employee[Daily_Rate],"",0),0) -> 693.33333 | P26: =IFERROR(Daily_Work[[#This Row],[OT_Hrs]]*_xlfn.XLOOKUP(Daily_Work[[#This Row],[Emp_ID]],Master_Employee[Emp_ID],Master_Employee[OT_Hr_Rate],0),0) -> 25
A27: 22 | B27: 46082 | C27: 389 | D27: =_xlfn.XLOOKUP(Daily_Work[[#This Row],[Emp_ID]],Master_Employee[Emp_ID],Master_Employee[Name_AR],"",0) -> محمد نور نبي | E27: =_xlfn.XLOOKUP(Daily_Work[[#This Row],[Emp_ID]],Master_Employee[Emp_ID],Master_Employee[Name_EN],"",0) -> 0 | F27: {=IF(Daily_Work[[#This Row],[Emp_ID]]=0,"", _xlfn.XLOOKUP(Daily_Work[[#This Row],[Emp_ID]],Master_Employee[Emp_ID],EmpDepts,"",0) )} -> التشطيبات | G27: ﻣﺪ ﺟﻠﺪﻳﻦ ﻣﻴﺎ | H27: عبدالهادي الماجد | I27: =IF(Daily_Work[[#This Row],[Project_Name]]="","",_xlfn.XLOOKUP(Daily_Work[[#This Row],[Project_Name]],ProjectNames,ProjectList,"",0)) -> A002F | J27: Friday | K27: =IF(Daily_Work[[#This Row],[Emp_Status]]="Absent",0,1) -> 1 | L27: 4 | N27: =Daily_Work[[#This Row],[Days_Work]]*8 -> 32 | O27: =IFERROR(Daily_Work[[#This Row],[Days_Work]]*_xlfn.XLOOKUP(Daily_Work[[#This Row],[Emp_ID]],Master_Employee[Emp_ID],Master_Employee[Daily_Rate],"",0),0) -> 173.33333 | P27: =IFERROR(Daily_Work[[#This Row],[OT_Hrs]]*_xlfn.XLOOKUP(Daily_Work[[#This Row],[Emp_ID]],Master_Employee[Emp_ID],Master_Employee[OT_Hr_Rate],0),0) -> 0
A28: 23 | B28: 46113 | C28: O207 | D28: =_xlfn.XLOOKUP(Daily_Work[[#This Row],[Emp_ID]],Master_Employee[Emp_ID],Master_Employee[Name_AR],"",0) -> محمد نور الأسلام | E28: =_xlfn.XLOOKUP(Daily_Work[[#This Row],[Emp_ID]],Master_Employee[Emp_ID],Master_Employee[Name_EN],"",0) -> 0 | F28: {=IF(Daily_Work[[#This Row],[Emp_ID]]=0,"", _xlfn.XLOOKUP(Daily_Work[[#This Row],[Emp_ID]],Master_Employee[Emp_ID],EmpDepts,"",0) )} -> التشطيبات | G28: ﻣﺪ ﺟﻠﺪﻳﻦ ﻣﻴﺎ | H28: سعود نقدان | I28: =IF(Daily_Work[[#This Row],[Project_Name]]="","",_xlfn.XLOOKUP(Daily_Work[[#This Row],[Project_Name]],ProjectNames,ProjectList,"",0)) -> S003F | J28: Work | K28: =IF(Daily_Work[[#This Row],[Emp_Status]]="Absent",0,1) -> 1 | L28: 10 | N28: =Daily_Work[[#This Row],[Days_Work]]*8 -> 80 | O28: =IFERROR(Daily_Work[[#This Row],[Days_Work]]*_xlfn.XLOOKUP(Daily_Work[[#This Row],[Emp_ID]],Master_Employee[Emp_ID],Master_Employee[Daily_Rate],"",0),0) -> 733.33333 | P28: =IFERROR(Daily_Work[[#This Row],[OT_Hrs]]*_xlfn.XLOOKUP(Daily_Work[[#This Row],[Emp_ID]],Master_Employee[Emp_ID],Master_Employee[OT_Hr_Rate],0),0) -> 0
A29: 24 | B29: 46113 | C29: O207 | D29: =_xlfn.XLOOKUP(Daily_Work[[#This Row],[Emp_ID]],Master_Employee[Emp_ID],Master_Employee[Name_AR],"",0) -> محمد نور الأسلام | E29: =_xlfn.XLOOKUP(Daily_Work[[#This Row],[Emp_ID]],Master_Employee[Emp_ID],Master_Employee[Name_EN],"",0) -> 0 | F29: {=IF(Daily_Work[[#This Row],[Emp_ID]]=0,"", _xlfn.XLOOKUP(Daily_Work[[#This Row],[Emp_ID]],Master_Employee[Emp_ID],EmpDepts,"",0) )} -> التشطيبات | G29: ﻣﺪ ﺟﻠﺪﻳﻦ ﻣﻴﺎ | H29: عبدالعزيز قحيز المري | I29: =IF(Daily_Work[[#This Row],[Project_Name]]="","",_xlfn.XLOOKUP(Daily_Work[[#This Row],[Project_Name]],ProjectNames,ProjectList,"",0)) -> A001F | J29: Work | K29: =IF(Daily_Work[[#This Row],[Emp_Status]]="Absent",0,1) -> 1 | L29: 5 | N29: =Daily_Work[[#This Row],[Days_Work]]*8 -> 40 | O29: =IFERROR(Daily_Work[[#This Row],[Days_Work]]*_xlfn.XLOOKUP(Daily_Work[[#This Row],[Emp_ID]],Master_Employee[Emp_ID],Master_Employee[Daily_Rate],"",0),0) -> 366.66667 | P29: =IFERROR(Daily_Work[[#This Row],[OT_Hrs]]*_xlfn.XLOOKUP(Daily_Work[[#This Row],[Emp_ID]],Master_Employee[Emp_ID],Master_Employee[OT_Hr_Rate],0),0) -> 0
A30: 25 | B30: 46113 | C30: O207 | D30: =_xlfn.XLOOKUP(Daily_Work[[#This Row],[Emp_ID]],Master_Employee[Emp_ID],Master_Employee[Name_AR],"",0) -> محمد نور الأسلام | E30: =_xlfn.XLOOKUP(Daily_Work[[#This Row],[Emp_ID]],Master_Employee[Emp_ID],Master_Employee[Name_EN],"",0) -> 0 | F30: {=IF(Daily_Work[[#This Row],[Emp_ID]]=0,"", _xlfn.XLOOKUP(Daily_Work[[#This Row],[Emp_ID]],Master_Employee[Emp_ID],EmpDepts,"",0) )} -> التشطيبات | G30: عمر مصباح عمر | H30: عمير راشد المري | I30: =IF(Daily_Work[[#This Row],[Project_Name]]="","",_xlfn.XLOOKUP(Daily_Work[[#This Row],[Project_Name]],ProjectNames,ProjectList,"",0)) -> U001F | J30: Work | K30: =IF(Daily_Work[[#This Row],[Emp_Status]]="Absent",0,1) -> 1 | L30: 4 | N30: =Daily_Work[[#This Row],[Days_Work]]*8 -> 32 | O30: =IFERROR(Daily_Work[[#This Row],[Days_Work]]*_xlfn.XLOOKUP(Daily_Work[[#This Row],[Emp_ID]],Master_Employee[Emp_ID],Master_Employee[Daily_Rate],"",0),0) -> 293.33333 | P30: =IFERROR(Daily_Work[[#This Row],[OT_Hrs]]*_xlfn.XLOOKUP(Daily_Work[[#This Row],[Emp_ID]],Master_Employee[Emp_ID],Master_Employee[OT_Hr_Rate],0),0) -> 0
A31: 26 | B31: 46113 | C31: O207 | D31: =_xlfn.XLOOKUP(Daily_Work[[#This Row],[Emp_ID]],Master_Employee[Emp_ID],Master_Employee[Name_AR],"",0) -> محمد نور الأسلام | E31: =_xlfn.XLOOKUP(Daily_Work[[#This Row],[Emp_ID]],Master_Employee[Emp_ID],Master_Employee[Name_EN],"",0) -> 0 | F31: {=IF(Daily_Work[[#This Row],[Emp_ID]]=0,"", _xlfn.XLOOKUP(Daily_Work[[#This Row],[Emp_ID]],Master_Employee[Emp_ID],EmpDepts,"",0) )} -> التشطيبات | G31: عمر مصباح عمر | H31: عمارة الدوسري | I31: =IF(Daily_Work[[#This Row],[Project_Name]]="","",_xlfn.XLOOKUP(Daily_Work[[#This Row],[Project_Name]],ProjectNames,ProjectList,"",0)) -> A004F | J31: Work | K31: =IF(Daily_Work[[#This Row],[Emp_Status]]="Absent",0,1) -> 1 | L31: 11 | N31: =Daily_Work[[#This Row],[Days_Work]]*8 -> 88 | O31: =IFERROR(Daily_Work[[#This Row],[Days_Work]]*_xlfn.XLOOKUP(Daily_Work[[#This Row],[Emp_ID]],Master_Employee[Emp_ID],Master_Employee[Daily_Rate],"",0),0) -> 806.66667 | P31: =IFERROR(Daily_Work[[#This Row],[OT_Hrs]]*_xlfn.XLOOKUP(Daily_Work[[#This Row],[Emp_ID]],Master_Employee[Emp_ID],Master_Employee[OT_Hr_Rate],0),0) -> 0
A32: 27 | B32: 46113 | C32: O163 | D32: =_xlfn.XLOOKUP(Daily_Work[[#This Row],[Emp_ID]],Master_Employee[Emp_ID],Master_Employee[Name_AR],"",0) -> عبد الباسي عبد الرحمن اشير | E32: =_xlfn.XLOOKUP(Daily_Work[[#This Row],[Emp_ID]],Master_Employee[Emp_ID],Master_Employee[Name_EN],"",0) -> 0 | F32: {=IF(Daily_Work[[#This Row],[Emp_ID]]=0,"", _xlfn.XLOOKUP(Daily_Work[[#This Row],[Emp_ID]],Master_Employee[Emp_ID],EmpDepts,"",0) )} -> التشطيبات | G32: عمر مصباح عمر | H32: فيصل محمد العذبة | I32: =IF(Daily_Work[[#This Row],[Project_Name]]="","",_xlfn.XLOOKUP(Daily_Work[[#This Row],[Project_Name]],ProjectNames,ProjectList,"",0)) -> F003F | J32: Work | K32: =IF(Daily_Work[[#This Row],[Emp_Status]]="Absent",0,1) -> 1 | L32: 10 | N32: =Daily_Work[[#This Row],[Days_Work]]*8 -> 80 | O32: =IFERROR(Daily_Work[[#This Row],[Days_Work]]*_xlfn.XLOOKUP(Daily_Work[[#This Row],[Emp_ID]],Master_Employee[Emp_ID],Master_Employee[Daily_Rate],"",0),0) -> 766.66667 | P32: =IFERROR(Daily_Work[[#This Row],[OT_Hrs]]*_xlfn.XLOOKUP(Daily_Work[[#This Row],[Emp_ID]],Master_Employee[Emp_ID],Master_Employee[OT_Hr_Rate],0),0) -> 0
A33: 28 | B33: 46113 | C33: O163 | D33: =_xlfn.XLOOKUP(Daily_Work[[#This Row],[Emp_ID]],Master_Employee[Emp_ID],Master_Employee[Name_AR],"",0) -> عبد الباسي عبد الرحمن اشير | E33: =_xlfn.XLOOKUP(Daily_Work[[#This Row],[Emp_ID]],Master_Employee[Emp_ID],Master_Employee[Name_EN],"",0) -> 0 | F33: {=IF(Daily_Work[[#This Row],[Emp_ID]]=0,"", _xlfn.XLOOKUP(Daily_Work[[#This Row],[Emp_ID]],Master_Employee[Emp_ID],EmpDepts,"",0) )} -> التشطيبات | G33: عمر مصباح عمر | H33: سعود الأحبابي | I33: =IF(Daily_Work[[#This Row],[Project_Name]]="","",_xlfn.XLOOKUP(Daily_Work[[#This Row],[Project_Name]],ProjectNames,ProjectList,"",0)) -> S001C | J33: Work | K33: =IF(Daily_Work[[#This Row],[Emp_Status]]="Absent",0,1) -> 1 | L33: 9 | N33: =Daily_Work[[#This Row],[Days_Work]]*8 -> 72 | O33: =IFERROR(Daily_Work[[#This Row],[Days_Work]]*_xlfn.XLOOKUP(Daily_Work[[#This Row],[Emp_ID]],Master_Employee[Emp_ID],Master_Employee[Daily_Rate],"",0),0) -> 690 | P33: =IFERROR(Daily_Work[[#This Row],[OT_Hrs]]*_xlfn.XLOOKUP(Daily_Work[[#This Row],[Emp_ID]],Master_Employee[Emp_ID],Master_Employee[OT_Hr_Rate],0),0) -> 0
A34: 29 | B34: 46113 | C34: O163 | D34: =_xlfn.XLOOKUP(Daily_Work[[#This Row],[Emp_ID]],Master_Employee[Emp_ID],Master_Employee[Name_AR],"",0) -> عبد الباسي عبد الرحمن اشير | E34: =_xlfn.XLOOKUP(Daily_Work[[#This Row],[Emp_ID]],Master_Employee[Emp_ID],Master_Employee[Name_EN],"",0) -> 0 | F34: {=IF(Daily_Work[[#This Row],[Emp_ID]]=0,"", _xlfn.XLOOKUP(Daily_Work[[#This Row],[Emp_ID]],Master_Employee[Emp_ID],EmpDepts,"",0) )} -> التشطيبات | G34: عمر مصباح عمر | H34: عمير راشد المري | I34: =IF(Daily_Work[[#This Row],[Project_Name]]="","",_xlfn.XLOOKUP(Daily_Work[[#This Row],[Project_Name]],ProjectNames,ProjectList,"",0)) -> U001F | J34: Work | K34: =IF(Daily_Work[[#This Row],[Emp_Status]]="Absent",0,1) -> 1 | L34: 7 | N34: =Daily_Work[[#This Row],[Days_Work]]*8 -> 56 | O34: =IFERROR(Daily_Work[[#This Row],[Days_Work]]*_xlfn.XLOOKUP(Daily_Work[[#This Row],[Emp_ID]],Master_Employee[Emp_ID],Master_Employee[Daily_Rate],"",0),0) -> 536.66667 | P34: =IFERROR(Daily_Work[[#This Row],[OT_Hrs]]*_xlfn.XLOOKUP(Daily_Work[[#This Row],[Emp_ID]],Master_Employee[Emp_ID],Master_Employee[OT_Hr_Rate],0),0) -> 0
A35: 30 | B35: 46113 | C35: O163 | D35: =_xlfn.XLOOKUP(Daily_Work[[#This Row],[Emp_ID]],Master_Employee[Emp_ID],Master_Employee[Name_AR],"",0) -> عبد الباسي عبد الرحمن اشير | E35: =_xlfn.XLOOKUP(Daily_Work[[#This Row],[Emp_ID]],Master_Employee[Emp_ID],Master_Employee[Name_EN],"",0) -> 0 | F35: {=IF(Daily_Work[[#This Row],[Emp_ID]]=0,"", _xlfn.XLOOKUP(Daily_Work[[#This Row],[Emp_ID]],Master_Employee[Emp_ID],EmpDepts,"",0) )} -> التشطيبات | G35: عمر مصباح عمر | H35: صالح العذبة | I35: =IF(Daily_Work[[#This Row],[Project_Name]]="","",_xlfn.XLOOKUP(Daily_Work[[#This Row],[Project_Name]],ProjectNames,ProjectList,"",0)) -> S004F | J35: Friday | K35: =IF(Daily_Work[[#This Row],[Emp_Status]]="Absent",0,1) -> 1 | L35: 4 | N35: =Daily_Work[[#This Row],[Days_Work]]*8 -> 32 | O35: =IFERROR(Daily_Work[[#This Row],[Days_Work]]*_xlfn.XLOOKUP(Daily_Work[[#This Row],[Emp_ID]],Master_Employee[Emp_ID],Master_Employee[Daily_Rate],"",0),0) -> 306.66667 | P35: =IFERROR(Daily_Work[[#This Row],[OT_Hrs]]*_xlfn.XLOOKUP(Daily_Work[[#This Row],[Emp_ID]],Master_Employee[Emp_ID],Master_Employee[OT_Hr_Rate],0),0) -> 0
A36: 31 | B36: 46113 | C36: 146 | D36: =_xlfn.XLOOKUP(Daily_Work[[#This Row],[Emp_ID]],Master_Employee[Emp_ID],Master_Employee[Name_AR],"",0) -> ﻣﺎﻣﻮﻥ ﺍﺣﻤﺪ ﺷﻮﻧﻮ ﻣﻴﺎﻩ | E36: =_xlfn.XLOOKUP(Daily_Work[[#This Row],[Emp_ID]],Master_Employee[Emp_ID],Master_Employee[Name_EN],"",0) -> 0 | F36: {=IF(Daily_Work[[#This Row],[Emp_ID]]=0,"", _xlfn.XLOOKUP(Daily_Work[[#This Row],[Emp_ID]],Master_Employee[Emp_ID],EmpDepts,"",0) )} -> الإدارة | G36: عمر مصباح عمر | H36: ناصر الحايف | I36: =IF(Daily_Work[[#This Row],[Project_Name]]="","",_xlfn.XLOOKUP(Daily_Work[[#This Row],[Project_Name]],ProjectNames,ProjectList,"",0)) -> N001F | J36: Work | K36: =IF(Daily_Work[[#This Row],[Emp_Status]]="Absent",0,1) -> 1 | L36: 10 | N36: =Daily_Work[[#This Row],[Days_Work]]*8 -> 80 | O36: =IFERROR(Daily_Work[[#This Row],[Days_Work]]*_xlfn.XLOOKUP(Daily_Work[[#This Row],[Emp_ID]],Master_Employee[Emp_ID],Master_Employee[Daily_Rate],"",0),0) -> 433.33333 | P36: =IFERROR(Daily_Work[[#This Row],[OT_Hrs]]*_xlfn.XLOOKUP(Daily_Work[[#This Row],[Emp_ID]],Master_Employee[Emp_ID],Master_Employee[OT_Hr_Rate],0),0) -> 0
A37: 32 | B37: 46113 | C37: 146 | D37: =_xlfn.XLOOKUP(Daily_Work[[#This Row],[Emp_ID]],Master_Employee[Emp_ID],Master_Employee[Name_AR],"",0) -> ﻣﺎﻣﻮﻥ ﺍﺣﻤﺪ ﺷﻮﻧﻮ ﻣﻴﺎﻩ | E37: =_xlfn.XLOOKUP(Daily_Work[[#This Row],[Emp_ID]],Master_Employee[Emp_ID],Master_Employee[Name_EN],"",0) -> 0 | F37: {=IF(Daily_Work[[#This Row],[Emp_ID]]=0,"", _xlfn.XLOOKUP(Daily_Work[[#This Row],[Emp_ID]],Master_Employee[Emp_ID],EmpDepts,"",0) )} -> الإدارة | G37: عمر مصباح عمر | H37: نايف الموسى | I37: =IF(Daily_Work[[#This Row],[Project_Name]]="","",_xlfn.XLOOKUP(Daily_Work[[#This Row],[Project_Name]],ProjectNames,ProjectList,"",0)) -> N001C | J37: Work | K37: =IF(Daily_Work[[#This Row],[Emp_Status]]="Absent",0,1) -> 1 | L37: 10 | N37: =Daily_Work[[#This Row],[Days_Work]]*8 -> 80 | O37: =IFERROR(Daily_Work[[#This Row],[Days_Work]]*_xlfn.XLOOKUP(Daily_Work[[#This Row],[Emp_ID]],Master_Employee[Emp_ID],Master_Employee[Daily_Rate],"",0),0) -> 433.33333 | P37: =IFERROR(Daily_Work[[#This Row],[OT_Hrs]]*_xlfn.XLOOKUP(Daily_Work[[#This Row],[Emp_ID]],Master_Employee[Emp_ID],Master_Employee[OT_Hr_Rate],0),0) -> 0
A38: 33 | B38: 46113 | C38: 146 | D38: =_xlfn.XLOOKUP(Daily_Work[[#This Row],[Emp_ID]],Master_Employee[Emp_ID],Master_Employee[Name_AR],"",0) -> ﻣﺎﻣﻮﻥ ﺍﺣﻤﺪ ﺷﻮﻧﻮ ﻣﻴﺎﻩ | E38: =_xlfn.XLOOKUP(Daily_Work[[#This Row],[Emp_ID]],Master_Employee[Emp_ID],Master_Employee[Name_EN],"",0) -> 0 | F38: {=IF(Daily_Work[[#This Row],[Emp_ID]]=0,"", _xlfn.XLOOKUP(Daily_Work[[#This Row],[Emp_ID]],Master_Employee[Emp_ID],EmpDepts,"",0) )} -> الإدارة | G38: عمر مصباح عمر | H38: امل الشمري | I38: =IF(Daily_Work[[#This Row],[Project_Name]]="","",_xlfn.XLOOKUP(Daily_Work[[#This Row],[Project_Name]],ProjectNames,ProjectList,"",0)) -> A005F | J38: Work | K38: =IF(Daily_Work[[#This Row],[Emp_Status]]="Absent",0,1) -> 1 | L38: 6 | N38: =Daily_Work[[#This Row],[Days_Work]]*8 -> 48 | O38: =IFERROR(Daily_Work[[#This Row],[Days_Work]]*_xlfn.XLOOKUP(Daily_Work[[#This Row],[Emp_ID]],Master_Employee[Emp_ID],Master_Employee[Daily_Rate],"",0),0) -> 260 | P38: =IFERROR(Daily_Work[[#This Row],[OT_Hrs]]*_xlfn.XLOOKUP(Daily_Work[[#This Row],[Emp_ID]],Master_Employee[Emp_ID],Master_Employee[OT_Hr_Rate],0),0) -> 0
A39: 34 | B39: 46113 | C39: 146 | D39: =_xlfn.XLOOKUP(Daily_Work[[#This Row],[Emp_ID]],Master_Employee[Emp_ID],Master_Employee[Name_AR],"",0) -> ﻣﺎﻣﻮﻥ ﺍﺣﻤﺪ ﺷﻮﻧﻮ ﻣﻴﺎﻩ | E39: =_xlfn.XLOOKUP(Daily_Work[[#This Row],[Emp_ID]],Master_Employee[Emp_ID],Master_Employee[Name_EN],"",0) -> 0 | F39: {=IF(Daily_Work[[#This Row],[Emp_ID]]=0,"", _xlfn.XLOOKUP(Daily_Work[[#This Row],[Emp_ID]],Master_Employee[Emp_ID],EmpDepts,"",0) )} -> الإدارة | G39: محمد عمران انصاري | H39: فهد ظافر القحطاني | I39: =IF(Daily_Work[[#This Row],[Project_Name]]="","",_xlfn.XLOOKUP(Daily_Work[[#This Row],[Project_Name]],ProjectNames,ProjectList,"",0)) -> F002F | J39: Friday | K39: =IF(Daily_Work[[#This Row],[Emp_Status]]="Absent",0,1) -> 1 | L39: 4 | N39: =Daily_Work[[#This Row],[Days_Work]]*8 -> 32 | O39: =IFERROR(Daily_Work[[#This Row],[Days_Work]]*_xlfn.XLOOKUP(Daily_Work[[#This Row],[Emp_ID]],Master_Employee[Emp_ID],Master_Employee[Daily_Rate],"",0),0) -> 173.33333 | P39: =IFERROR(Daily_Work[[#This Row],[OT_Hrs]]*_xlfn.XLOOKUP(Daily_Work[[#This Row],[Emp_ID]],Master_Employee[Emp_ID],Master_Employee[OT_Hr_Rate],0),0) -> 0
A40: 35 | B40: 46113 | C40: O304 | D40: =_xlfn.XLOOKUP(Daily_Work[[#This Row],[Emp_ID]],Master_Employee[Emp_ID],Master_Employee[Name_AR],"",0) -> صلاح عبدالرحمن الحاج احمد | E40: =_xlfn.XLOOKUP(Daily_Work[[#This Row],[Emp_ID]],Master_Employee[Emp_ID],Master_Employee[Name_EN],"",0) -> 0 | F40: {=IF(Daily_Work[[#This Row],[Emp_ID]]=0,"", _xlfn.XLOOKUP(Daily_Work[[#This Row],[Emp_ID]],Master_Employee[Emp_ID],EmpDepts,"",0) )} -> الإدارة | G40: محمد عمران انصاري | H40: جابر سالم الغواص | I40: =IF(Daily_Work[[#This Row],[Project_Name]]="","",_xlfn.XLOOKUP(Daily_Work[[#This Row],[Project_Name]],ProjectNames,ProjectList,"",0)) -> J001C | J40: Work | K40: =IF(Daily_Work[[#This Row],[Emp_Status]]="Absent",0,1) -> 1 | L40: 11 | N40: =Daily_Work[[#This Row],[Days_Work]]*8 -> 88 | O40: =IFERROR(Daily_Work[[#This Row],[Days_Work]]*_xlfn.XLOOKUP(Daily_Work[[#This Row],[Emp_ID]],Master_Employee[Emp_ID],Master_Employee[Daily_Rate],"",0),0) -> 660 | P40: =IFERROR(Daily_Work[[#This Row],[OT_Hrs]]*_xlfn.XLOOKUP(Daily_Work[[#This Row],[Emp_ID]],Master_Employee[Emp_ID],Master_Employee[OT_Hr_Rate],0),0) -> 0
A41: 36 | B41: 46113 | C41: O304 | D41: =_xlfn.XLOOKUP(Daily_Work[[#This Row],[Emp_ID]],Master_Employee[Emp_ID],Master_Employee[Name_AR],"",0) -> صلاح عبدالرحمن الحاج احمد | E41: =_xlfn.XLOOKUP(Daily_Work[[#This Row],[Emp_ID]],Master_Employee[Emp_ID],Master_Employee[Name_EN],"",0) -> 0 | F41: {=IF(Daily_Work[[#This Row],[Emp_ID]]=0,"", _xlfn.XLOOKUP(Daily_Work[[#This Row],[Emp_ID]],Master_Employee[Emp_ID],EmpDepts,"",0) )} -> الإدارة | G41: محمد عمران انصاري | H41: عبدالرحمن نقدان | I41: =IF(Daily_Work[[#This Row],[Project_Name]]="","",_xlfn.XLOOKUP(Daily_Work[[#This Row],[Project_Name]],ProjectNames,ProjectList,"",0)) -> A007F | J41: Work | K41: =IF(Daily_Work[[#This Row],[Emp_Status]]="Absent",0,1) -> 1 | L41: 9 | N41: =Daily_Work[[#This Row],[Days_Work]]*8 -> 72 | O41: =IFERROR(Daily_Work[[#This Row],[Days_Work]]*_xlfn.XLOOKUP(Daily_Work[[#This Row],[Emp_ID]],Master_Employee[Emp_ID],Master_Employee[Daily_Rate],"",0),0) -> 540 | P41: =IFERROR(Daily_Work[[#This Row],[OT_Hrs]]*_xlfn.XLOOKUP(Daily_Work[[#This Row],[Emp_ID]],Master_Employee[Emp_ID],Master_Employee[OT_Hr_Rate],0),0) -> 0
A42: 37 | B42: 46113 | C42: O304 | D42: =_xlfn.XLOOKUP(Daily_Work[[#This Row],[Emp_ID]],Master_Employee[Emp_ID],Master_Employee[Name_AR],"",0) -> صلاح عبدالرحمن الحاج احمد | E42: =_xlfn.XLOOKUP(Daily_Work[[#This Row],[Emp_ID]],Master_Employee[Emp_ID],Master_Employee[Name_EN],"",0) -> 0 | F42: {=IF(Daily_Work[[#This Row],[Emp_ID]]=0,"", _xlfn.XLOOKUP(Daily_Work[[#This Row],[Emp_ID]],Master_Employee[Emp_ID],EmpDepts,"",0) )} -> الإدارة | G42: محمد عمران انصاري | H42: سعد عزران | I42: =IF(Daily_Work[[#This Row],[Project_Name]]="","",_xlfn.XLOOKUP(Daily_Work[[#This Row],[Project_Name]],ProjectNames,ProjectList,"",0)) -> S006F | J42: Work | K42: =IF(Daily_Work[[#This Row],[Emp_Status]]="Absent",0,1) -> 1 | L42: 4 | N42: =Daily_Work[[#This Row],[Days_Work]]*8 -> 32 | O42: =IFERROR(Daily_Work[[#This Row],[Days_Work]]*_xlfn.XLOOKUP(Daily_Work[[#This Row],[Emp_ID]],Master_Employee[Emp_ID],Master_Employee[Daily_Rate],"",0),0) -> 240 | P42: =IFERROR(Daily_Work[[#This Row],[OT_Hrs]]*_xlfn.XLOOKUP(Daily_Work[[#This Row],[Emp_ID]],Master_Employee[Emp_ID],Master_Employee[OT_Hr_Rate],0),0) -> 0
A43: 38 | B43: 46113 | C43: O304 | D43: =_xlfn.XLOOKUP(Daily_Work[[#This Row],[Emp_ID]],Master_Employee[Emp_ID],Master_Employee[Name_AR],"",0) -> صلاح عبدالرحمن الحاج احمد | E43: =_xlfn.XLOOKUP(Daily_Work[[#This Row],[Emp_ID]],Master_Employee[Emp_ID],Master_Employee[Name_EN],"",0) -> 0 | F43: {=IF(Daily_Work[[#This Row],[Emp_ID]]=0,"", _xlfn.XLOOKUP(Daily_Work[[#This Row],[Emp_ID]],Master_Employee[Emp_ID],EmpDepts,"",0) )} -> الإدارة | G43: محمد عمران انصاري | H43: مصطفى | I43: =IF(Daily_Work[[#This Row],[Project_Name]]="","",_xlfn.XLOOKUP(Daily_Work[[#This Row],[Project_Name]],ProjectNames,ProjectList,"",0)) -> EF0F | J43: Friday | K43: =IF(Daily_Work[[#This Row],[Emp_Status]]="Absent",0,1) -> 1 | L43: 4 | N43: =Daily_Work[[#This Row],[Days_Work]]*8 -> 32 | O43: =IFERROR(Daily_Work[[#This Row],[Days_Work]]*_xlfn.XLOOKUP(Daily_Work[[#This Row],[Emp_ID]],Master_Employee[Emp_ID],Master_Employee[Daily_Rate],"",0),0) -> 240 | P43: =IFERROR(Daily_Work[[#This Row],[OT_Hrs]]*_xlfn.XLOOKUP(Daily_Work[[#This Row],[Emp_ID]],Master_Employee[Emp_ID],Master_Employee[OT_Hr_Rate],0),0) -> 0
A44: 39 | B44: 46113 | C44: O304 | D44: =_xlfn.XLOOKUP(Daily_Work[[#This Row],[Emp_ID]],Master_Employee[Emp_ID],Master_Employee[Name_AR],"",0) -> صلاح عبدالرحمن الحاج احمد | E44: =_xlfn.XLOOKUP(Daily_Work[[#This Row],[Emp_ID]],Master_Employee[Emp_ID],Master_Employee[Name_EN],"",0) -> 0 | F44: {=IF(Daily_Work[[#This Row],[Emp_ID]]=0,"", _xlfn.XLOOKUP(Daily_Work[[#This Row],[Emp_ID]],Master_Employee[Emp_ID],EmpDepts,"",0) )} -> الإدارة | G44: محمد عمران انصاري | H44: الحجر | I44: =IF(Daily_Work[[#This Row],[Project_Name]]="","",_xlfn.XLOOKUP(Daily_Work[[#This Row],[Project_Name]],ProjectNames,ProjectList,"",0)) -> ST00 | J44: Absent | K44: =IF(Daily_Work[[#This Row],[Emp_Status]]="Absent",0,1) -> 0 | N44: =Daily_Work[[#This Row],[Days_Work]]*8 -> 0 | O44: =IFERROR(Daily_Work[[#This Row],[Days_Work]]*_xlfn.XLOOKUP(Daily_Work[[#This Row],[Emp_ID]],Master_Employee[Emp_ID],Master_Employee[Daily_Rate],"",0),0) -> 0 | P44: =IFERROR(Daily_Work[[#This Row],[OT_Hrs]]*_xlfn.XLOOKUP(Daily_Work[[#This Row],[Emp_ID]],Master_Employee[Emp_ID],Master_Employee[OT_Hr_Rate],0),0) -> 0
A45: 40 | B45: 46113 | C45: O304 | D45: =_xlfn.XLOOKUP(Daily_Work[[#This Row],[Emp_ID]],Master_Employee[Emp_ID],Master_Employee[Name_AR],"",0) -> صلاح عبدالرحمن الحاج احمد | E45: =_xlfn.XLOOKUP(Daily_Work[[#This Row],[Emp_ID]],Master_Employee[Emp_ID],Master_Employee[Name_EN],"",0) -> 0 | F45: {=IF(Daily_Work[[#This Row],[Emp_ID]]=0,"", _xlfn.XLOOKUP(Daily_Work[[#This Row],[Emp_ID]],Master_Employee[Emp_ID],EmpDepts,"",0) )} -> الإدارة | G45: محمد عمران انصاري | H45: جابر قحيز المري | I45: =IF(Daily_Work[[#This Row],[Project_Name]]="","",_xlfn.XLOOKUP(Daily_Work[[#This Row],[Project_Name]],ProjectNames,ProjectList,"",0)) -> J001F | J45: Absent | K45: =IF(Daily_Work[[#This Row],[Emp_Status]]="Absent",0,1) -> 0 | N45: =Daily_Work[[#This Row],[Days_Work]]*8 -> 0 | O45: =IFERROR(Daily_Work[[#This Row],[Days_Work]]*_xlfn.XLOOKUP(Daily_Work[[#This Row],[Emp_ID]],Master_Employee[Emp_ID],Master_Employee[Daily_Rate],"",0),0) -> 0 | P45: =IFERROR(Daily_Work[[#This Row],[OT_Hrs]]*_xlfn.XLOOKUP(Daily_Work[[#This Row],[Emp_ID]],Master_Employee[Emp_ID],Master_Employee[OT_Hr_Rate],0),0) -> 0
A46: 41 | D46: =_xlfn.XLOOKUP(Daily_Work[[#This Row],[Emp_ID]],Master_Employee[Emp_ID],Master_Employee[Name_AR],"",0) | E46: =_xlfn.XLOOKUP(Daily_Work[[#This Row],[Emp_ID]],Master_Employee[Emp_ID],Master_Employee[Name_EN],"",0) | F46: {=IF(Daily_Work[[#This Row],[Emp_ID]]=0,"", _xlfn.XLOOKUP(Daily_Work[[#This Row],[Emp_ID]],Master_Employee[Emp_ID],EmpDepts,"",0) )} | I46: =IF(Daily_Work[[#This Row],[Project_Name]]="","",_xlfn.XLOOKUP(Daily_Work[[#This Row],[Project_Name]],ProjectNames,ProjectList,"",0)) | K46: =IF(Daily_Work[[#This Row],[Emp_Status]]="Absent",0,1) -> 1 | N46: =Daily_Work[[#This Row],[Days_Work]]*8 -> 0 | O46: =IFERROR(Daily_Work[[#This Row],[Days_Work]]*_xlfn.XLOOKUP(Daily_Work[[#This Row],[Emp_ID]],Master_Employee[Emp_ID],Master_Employee[Daily_Rate],"",0),0) -> 0 | P46: =IFERROR(Daily_Work[[#This Row],[OT_Hrs]]*_xlfn.XLOOKUP(Daily_Work[[#This Row],[Emp_ID]],Master_Employee[Emp_ID],Master_Employee[OT_Hr_Rate],0),0) -> 0
A47: 42 | D47: =_xlfn.XLOOKUP(Daily_Work[[#This Row],[Emp_ID]],Master_Employee[Emp_ID],Master_Employee[Name_AR],"",0) | E47: =_xlfn.XLOOKUP(Daily_Work[[#This Row],[Emp_ID]],Master_Employee[Emp_ID],Master_Employee[Name_EN],"",0) | F47: {=IF(Daily_Work[[#This Row],[Emp_ID]]=0,"", _xlfn.XLOOKUP(Daily_Work[[#This Row],[Emp_ID]],Master_Employee[Emp_ID],EmpDepts,"",0) )} | I47: =IF(Daily_Work[[#This Row],[Project_Name]]="","",_xlfn.XLOOKUP(Daily_Work[[#This Row],[Project_Name]],ProjectNames,ProjectList,"",0)) | K47: =IF(Daily_Work[[#This Row],[Emp_Status]]="Absent",0,1) -> 1 | N47: =Daily_Work[[#This Row],[Days_Work]]*8 -> 0 | O47: =IFERROR(Daily_Work[[#This Row],[Days_Work]]*_xlfn.XLOOKUP(Daily_Work[[#This Row],[Emp_ID]],Master_Employee[Emp_ID],Master_Employee[Daily_Rate],"",0),0) -> 0 | P47: =IFERROR(Daily_Work[[#This Row],[OT_Hrs]]*_xlfn.XLOOKUP(Daily_Work[[#This Row],[Emp_ID]],Master_Employee[Emp_ID],Master_Employee[OT_Hr_Rate],0),0) -> 0
A48: 43 | D48: =_xlfn.XLOOKUP(Daily_Work[[#This Row],[Emp_ID]],Master_Employee[Emp_ID],Master_Employee[Name_AR],"",0) | E48: =_xlfn.XLOOKUP(Daily_Work[[#This Row],[Emp_ID]],Master_Employee[Emp_ID],Master_Employee[Name_EN],"",0) | F48: {=IF(Daily_Work[[#This Row],[Emp_ID]]=0,"", _xlfn.XLOOKUP(Daily_Work[[#This Row],[Emp_ID]],Master_Employee[Emp_ID],EmpDepts,"",0) )} | I48: =IF(Daily_Work[[#This Row],[Project_Name]]="","",_xlfn.XLOOKUP(Daily_Work[[#This Row],[Project_Name]],ProjectNames,ProjectList,"",0)) | K48: =IF(Daily_Work[[#This Row],[Emp_Status]]="Absent",0,1) -> 1 | N48: =Daily_Work[[#This Row],[Days_Work]]*8 -> 0 | O48: =IFERROR(Daily_Work[[#This Row],[Days_Work]]*_xlfn.XLOOKUP(Daily_Work[[#This Row],[Emp_ID]],Master_Employee[Emp_ID],Master_Employee[Daily_Rate],"",0),0) -> 0 | P48: =IFERROR(Daily_Work[[#This Row],[OT_Hrs]]*_xlfn.XLOOKUP(Daily_Work[[#This Row],[Emp_ID]],Master_Employee[Emp_ID],Master_Employee[OT_Hr_Rate],0),0) -> 0
A49: 44 | D49: =_xlfn.XLOOKUP(Daily_Work[[#This Row],[Emp_ID]],Master_Employee[Emp_ID],Master_Employee[Name_AR],"",0) | E49: =_xlfn.XLOOKUP(Daily_Work[[#This Row],[Emp_ID]],Master_Employee[Emp_ID],Master_Employee[Name_EN],"",0) | F49: {=IF(Daily_Work[[#This Row],[Emp_ID]]=0,"", _xlfn.XLOOKUP(Daily_Work[[#This Row],[Emp_ID]],Master_Employee[Emp_ID],EmpDepts,"",0) )} | I49: =IF(Daily_Work[[#This Row],[Project_Name]]="","",_xlfn.XLOOKUP(Daily_Work[[#This Row],[Project_Name]],ProjectNames,ProjectList,"",0)) | K49: =IF(Daily_Work[[#This Row],[Emp_Status]]="Absent",0,1) -> 1 | N49: =Daily_Work[[#This Row],[Days_Work]]*8 -> 0 | O49: =IFERROR(Daily_Work[[#This Row],[Days_Work]]*_xlfn.XLOOKUP(Daily_Work[[#This Row],[Emp_ID]],Master_Employee[Emp_ID],Master_Employee[Daily_Rate],"",0),0) -> 0 | P49: =IFERROR(Daily_Work[[#This Row],[OT_Hrs]]*_xlfn.XLOOKUP(Daily_Work[[#This Row],[Emp_ID]],Master_Employee[Emp_ID],Master_Employee[OT_Hr_Rate],0),0) -> 0
A50: 45 | D50: =_xlfn.XLOOKUP(Daily_Work[[#This Row],[Emp_ID]],Master_Employee[Emp_ID],Master_Employee[Name_AR],"",0) | E50: =_xlfn.XLOOKUP(Daily_Work[[#This Row],[Emp_ID]],Master_Employee[Emp_ID],Master_Employee[Name_EN],"",0) | F50: {=IF(Daily_Work[[#This Row],[Emp_ID]]=0,"", _xlfn.XLOOKUP(Daily_Work[[#This Row],[Emp_ID]],Master_Employee[Emp_ID],EmpDepts,"",0) )} | I50: =IF(Daily_Work[[#This Row],[Project_Name]]="","",_xlfn.XLOOKUP(Daily_Work[[#This Row],[Project_Name]],ProjectNames,ProjectList,"",0)) | K50: =IF(Daily_Work[[#This Row],[Emp_Status]]="Absent",0,1) -> 1 | N50: =Daily_Work[[#This Row],[Days_Work]]*8 -> 0 | O50: =IFERROR(Daily_Work[[#This Row],[Days_Work]]*_xlfn.XLOOKUP(Daily_Work[[#This Row],[Emp_ID]],Master_Employee[Emp_ID],Master_Employee[Daily_Rate],"",0),0) -> 0 | P50: =IFERROR(Daily_Work[[#This Row],[OT_Hrs]]*_xlfn.XLOOKUP(Daily_Work[[#This Row],[Emp_ID]],Master_Employee[Emp_ID],Master_Employee[OT_Hr_Rate],0),0) -> 0
A51: 46 | D51: =_xlfn.XLOOKUP(Daily_Work[[#This Row],[Emp_ID]],Master_Employee[Emp_ID],Master_Employee[Name_AR],"",0) | E51: =_xlfn.XLOOKUP(Daily_Work[[#This Row],[Emp_ID]],Master_Employee[Emp_ID],Master_Employee[Name_EN],"",0) | F51: {=IF(Daily_Work[[#This Row],[Emp_ID]]=0,"", _xlfn.XLOOKUP(Daily_Work[[#This Row],[Emp_ID]],Master_Employee[Emp_ID],EmpDepts,"",0) )} | I51: =IF(Daily_Work[[#This Row],[Project_Name]]="","",_xlfn.XLOOKUP(Daily_Work[[#This Row],[Project_Name]],ProjectNames,ProjectList,"",0)) | K51: =IF(Daily_Work[[#This Row],[Emp_Status]]="Absent",0,1) -> 1 | N51: =Daily_Work[[#This Row],[Days_Work]]*8 -> 0 | O51: =IFERROR(Daily_Work[[#This Row],[Days_Work]]*_xlfn.XLOOKUP(Daily_Work[[#This Row],[Emp_ID]],Master_Employee[Emp_ID],Master_Employee[Daily_Rate],"",0),0) -> 0 | P51: =IFERROR(Daily_Work[[#This Row],[OT_Hrs]]*_xlfn.XLOOKUP(Daily_Work[[#This Row],[Emp_ID]],Master_Employee[Emp_ID],Master_Employee[OT_Hr_Rate],0),0) -> 0
A52: 47 | D52: =_xlfn.XLOOKUP(Daily_Work[[#This Row],[Emp_ID]],Master_Employee[Emp_ID],Master_Employee[Name_AR],"",0) | E52: =_xlfn.XLOOKUP(Daily_Work[[#This Row],[Emp_ID]],Master_Employee[Emp_ID],Master_Employee[Name_EN],"",0) | F52: {=IF(Daily_Work[[#This Row],[Emp_ID]]=0,"", _xlfn.XLOOKUP(Daily_Work[[#This Row],[Emp_ID]],Master_Employee[Emp_ID],EmpDepts,"",0) )} | I52: =IF(Daily_Work[[#This Row],[Project_Name]]="","",_xlfn.XLOOKUP(Daily_Work[[#This Row],[Project_Name]],ProjectNames,ProjectList,"",0)) | K52: =IF(Daily_Work[[#This Row],[Emp_Status]]="Absent",0,1) -> 1 | N52: =Daily_Work[[#This Row],[Days_Work]]*8 -> 0 | O52: =IFERROR(Daily_Work[[#This Row],[Days_Work]]*_xlfn.XLOOKUP(Daily_Work[[#This Row],[Emp_ID]],Master_Employee[Emp_ID],Master_Employee[Daily_Rate],"",0),0) -> 0 | P52: =IFERROR(Daily_Work[[#This Row],[OT_Hrs]]*_xlfn.XLOOKUP(Daily_Work[[#This Row],[Emp_ID]],Master_Employee[Emp_ID],Master_Employee[OT_Hr_Rate],0),0) -> 0
A53: 48 | D53: =_xlfn.XLOOKUP(Daily_Work[[#This Row],[Emp_ID]],Master_Employee[Emp_ID],Master_Employee[Name_AR],"",0) | E53: =_xlfn.XLOOKUP(Daily_Work[[#This Row],[Emp_ID]],Master_Employee[Emp_ID],Master_Employee[Name_EN],"",0) | F53: {=IF(Daily_Work[[#This Row],[Emp_ID]]=0,"", _xlfn.XLOOKUP(Daily_Work[[#This Row],[Emp_ID]],Master_Employee[Emp_ID],EmpDepts,"",0) )} | I53: =IF(Daily_Work[[#This Row],[Project_Name]]="","",_xlfn.XLOOKUP(Daily_Work[[#This Row],[Project_Name]],ProjectNames,ProjectList,"",0)) | K53: =IF(Daily_Work[[#This Row],[Emp_Status]]="Absent",0,1) -> 1 | N53: =Daily_Work[[#This Row],[Days_Work]]*8 -> 0 | O53: =IFERROR(Daily_Work[[#This Row],[Days_Work]]*_xlfn.XLOOKUP(Daily_Work[[#This Row],[Emp_ID]],Master_Employee[Emp_ID],Master_Employee[Daily_Rate],"",0),0) -> 0 | P53: =IFERROR(Daily_Work[[#This Row],[OT_Hrs]]*_xlfn.XLOOKUP(Daily_Work[[#This Row],[Emp_ID]],Master_Employee[Emp_ID],Master_Employee[OT_Hr_Rate],0),0) -> 0
A54: 49 | D54: =_xlfn.XLOOKUP(Daily_Work[[#This Row],[Emp_ID]],Master_Employee[Emp_ID],Master_Employee[Name_AR],"",0) | E54: =_xlfn.XLOOKUP(Daily_Work[[#This Row],[Emp_ID]],Master_Employee[Emp_ID],Master_Employee[Name_EN],"",0) | F54: {=IF(Daily_Work[[#This Row],[Emp_ID]]=0,"", _xlfn.XLOOKUP(Daily_Work[[#This Row],[Emp_ID]],Master_Employee[Emp_ID],EmpDepts,"",0) )} | I54: =IF(Daily_Work[[#This Row],[Project_Name]]="","",_xlfn.XLOOKUP(Daily_Work[[#This Row],[Project_Name]],ProjectNames,ProjectList,"",0)) | K54: =IF(Daily_Work[[#This Row],[Emp_Status]]="Absent",0,1) -> 1 | N54: =Daily_Work[[#This Row],[Days_Work]]*8 -> 0 | O54: =IFERROR(Daily_Work[[#This Row],[Days_Work]]*_xlfn.XLOOKUP(Daily_Work[[#This Row],[Emp_ID]],Master_Employee[Emp_ID],Master_Employee[Daily_Rate],"",0),0) -> 0 | P54: =IFERROR(Daily_Work[[#This Row],[OT_Hrs]]*_xlfn.XLOOKUP(Daily_Work[[#This Row],[Emp_ID]],Master_Employee[Emp_ID],Master_Employee[OT_Hr_Rate],0),0) -> 0
A55: 50 | D55: =_xlfn.XLOOKUP(Daily_Work[[#This Row],[Emp_ID]],Master_Employee[Emp_ID],Master_Employee[Name_AR],"",0) | E55: =_xlfn.XLOOKUP(Daily_Work[[#This Row],[Emp_ID]],Master_Employee[Emp_ID],Master_Employee[Name_EN],"",0) | F55: {=IF(Daily_Work[[#This Row],[Emp_ID]]=0,"", _xlfn.XLOOKUP(Daily_Work[[#This Row],[Emp_ID]],Master_Employee[Emp_ID],EmpDepts,"",0) )} | I55: =IF(Daily_Work[[#This Row],[Project_Name]]="","",_xlfn.XLOOKUP(Daily_Work[[#This Row],[Project_Name]],ProjectNames,ProjectList,"",0)) | K55: =IF(Daily_Work[[#This Row],[Emp_Status]]="Absent",0,1) -> 1 | N55: =Daily_Work[[#This Row],[Days_Work]]*8 -> 0 | O55: =IFERROR(Daily_Work[[#This Row],[Days_Work]]*_xlfn.XLOOKUP(Daily_Work[[#This Row],[Emp_ID]],Master_Employee[Emp_ID],Master_Employee[Daily_Rate],"",0),0) -> 0 | P55: =IFERROR(Daily_Work[[#This Row],[OT_Hrs]]*_xlfn.XLOOKUP(Daily_Work[[#This Row],[Emp_ID]],Master_Employee[Emp_ID],Master_Employee[OT_Hr_Rate],0),0) -> 0
A56: 51 | D56: =_xlfn.XLOOKUP(Daily_Work[[#This Row],[Emp_ID]],Master_Employee[Emp_ID],Master_Employee[Name_AR],"",0) | E56: =_xlfn.XLOOKUP(Daily_Work[[#This Row],[Emp_ID]],Master_Employee[Emp_ID],Master_Employee[Name_EN],"",0) | F56: {=IF(Daily_Work[[#This Row],[Emp_ID]]=0,"", _xlfn.XLOOKUP(Daily_Work[[#This Row],[Emp_ID]],Master_Employee[Emp_ID],EmpDepts,"",0) )} | I56: =IF(Daily_Work[[#This Row],[Project_Name]]="","",_xlfn.XLOOKUP(Daily_Work[[#This Row],[Project_Name]],ProjectNames,ProjectList,"",0)) | K56: =IF(Daily_Work[[#This Row],[Emp_Status]]="Absent",0,1) -> 1 | N56: =Daily_Work[[#This Row],[Days_Work]]*8 -> 0 | O56: =IFERROR(Daily_Work[[#This Row],[Days_Work]]*_xlfn.XLOOKUP(Daily_Work[[#This Row],[Emp_ID]],Master_Employee[Emp_ID],Master_Employee[Daily_Rate],"",0),0) -> 0 | P56: =IFERROR(Daily_Work[[#This Row],[OT_Hrs]]*_xlfn.XLOOKUP(Daily_Work[[#This Row],[Emp_ID]],Master_Employee[Emp_ID],Master_Employee[OT_Hr_Rate],0),0) -> 0
A57: 52 | D57: =_xlfn.XLOOKUP(Daily_Work[[#This Row],[Emp_ID]],Master_Employee[Emp_ID],Master_Employee[Name_AR],"",0) | E57: =_xlfn.XLOOKUP(Daily_Work[[#This Row],[Emp_ID]],Master_Employee[Emp_ID],Master_Employee[Name_EN],"",0) | F57: {=IF(Daily_Work[[#This Row],[Emp_ID]]=0,"", _xlfn.XLOOKUP(Daily_Work[[#This Row],[Emp_ID]],Master_Employee[Emp_ID],EmpDepts,"",0) )} | I57: =IF(Daily_Work[[#This Row],[Project_Name]]="","",_xlfn.XLOOKUP(Daily_Work[[#This Row],[Project_Name]],ProjectNames,ProjectList,"",0)) | K57: =IF(Daily_Work[[#This Row],[Emp_Status]]="Absent",0,1) -> 1 | N57: =Daily_Work[[#This Row],[Days_Work]]*8 -> 0 | O57: =IFERROR(Daily_Work[[#This Row],[Days_Work]]*_xlfn.XLOOKUP(Daily_Work[[#This Row],[Emp_ID]],Master_Employee[Emp_ID],Master_Employee[Daily_Rate],"",0),0) -> 0 | P57: =IFERROR(Daily_Work[[#This Row],[OT_Hrs]]*_xlfn.XLOOKUP(Daily_Work[[#This Row],[Emp_ID]],Master_Employee[Emp_ID],Master_Employee[OT_Hr_Rate],0),0) -> 0
... A202: 197 | D202: =_xlfn.XLOOKUP(Daily_Work[[#This Row],[Emp_ID]],Master_Employee[Emp_ID],Master_Employee[Name_AR],"",0) | E202: =_xlfn.XLOOKUP(Daily_Work[[#This Row],[Emp_ID]],Master_Employee[Emp_ID],Master_Employee[Name_EN],"",0) | F202: {=IF(Daily_Work[[#This Row],[Emp_ID]]=0,"", _xlfn.XLOOKUP(Daily_Work[[#This Row],[Emp_ID]],Master_Employee[Emp_ID],EmpDepts,"",0) )} | I202: =IF(Daily_Work[[#This Row],[Project_Name]]="","",_xlfn.XLOOKUP(Daily_Work[[#This Row],[Project_Name]],ProjectNames,ProjectList,"",0)) | K202: =IF(Daily_Work[[#This Row],[Emp_Status]]="Absent",0,1) -> 1 | N202: =Daily_Work[[#This Row],[Days_Work]]*8 -> 0 | O202: =IFERROR(Daily_Work[[#This Row],[Days_Work]]*_xlfn.XLOOKUP(Daily_Work[[#This Row],[Emp_ID]],Master_Employee[Emp_ID],Master_Employee[Daily_Rate],"",0),0) -> 0 | P202: =IFERROR(Daily_Work[[#This Row],[OT_Hrs]]*_xlfn.XLOOKUP(Daily_Work[[#This Row],[Emp_ID]],Master_Employee[Emp_ID],Master_Employee[OT_Hr_Rate],0),0) -> 0

Sheet Lists
AR1: الإنشاءات | AY1: التشطيبات | BF1: الإدارة | BM1: الكهرباء | BT1: السباكة | CA1: الحجر | CH1: كل الأقسام
B2: Employee_Code | F2: Supervisor_For Dept | K2: Job_Title | M2: Emp_Status | P2: Payment_Method | X2: Project_Status | AV2: =_xlfn.XLOOKUP(AR1,tbl_Dept[Dept_Name],tbl_Dept[Dept_ID],"",0) -> CON_D03 | BC2: =_xlfn.XLOOKUP(AY1,tbl_Dept[Dept_Name],tbl_Dept[Dept_ID],"",0) -> FIN_D02 | BJ2: =_xlfn.XLOOKUP(BF1,tbl_Dept[Dept_Name],tbl_Dept[Dept_ID],"",0) -> ADM_D01 | BQ2: =_xlfn.XLOOKUP(BM1,tbl_Dept[Dept_Name],tbl_Dept[Dept_ID],"",0) -> ELE_D04 | BX2: =_xlfn.XLOOKUP(BT1,tbl_Dept[Dept_Name],tbl_Dept[Dept_ID],"",0) -> PLM_D05 | CE2: =_xlfn.XLOOKUP(CA1,tbl_Dept[Dept_Name],tbl_Dept[Dept_ID],"",0) -> STN_D06 | CK2: =_xlfn.XLOOKUP(CH1,tbl_Dept[Dept_Name],tbl_Dept[Dept_ID],"",0) -> All_D11 | CP2: Work_Status | CR2: Trans_Type | CS2: Type_Code
F3: هدخل الداتا بتاعت كل مشرف اسمه وشغال في أي مشروع و ID هيتسحب Auto من ملف الموظفين | AK3: # | AL3: Emp_ID | AM3: Employee_ID | AN3: Name_AR | AO3: Name_EN | AP3: Department_ID | AR3: # | AS3: Emp_ID | AT3: Employee_ID | AU3: Name_AR | AV3: Name_EN | AW3: Department_ID | AY3: # | AZ3: Emp_ID | BA3: Employee_ID | BB3: Name_AR | BC3: Name_EN | BD3: Department_ID | BF3: # | BG3: Emp_ID | BH3: Employee_ID | BI3: Name_AR | BJ3: Name_EN | BK3: Department_ID | BM3: # | BN3: Emp_ID | BO3: Employee_ID | BP3: Name_AR | BQ3: Name_EN | BR3: Department_ID | BT3: # | BU3: Emp_ID | BV3: Employee_ID | BW3: Name_AR | BX3: Name_EN | BY3: Department_ID | CA3: # | CB3: Emp_ID | CC3: Employee_ID | CD3: Name_AR | CE3: Name_EN | CF3: Department_ID | CH3: # | CI3: Emp_ID | CJ3: Name_AR | CK3: Name_EN | CL3: Department_ID | CP3: Work | CR3: سلف - Loans | CS3: Lo_01
B4: # | C4: Emp_ID | F4: Supervisor_Name | G4: Supervisor_ID | H4: Department | K4: Job_Title | M4: Emp_Status | N4: Status_Code | P4: Payment_Method | Q4: Pay_Code | S4: Year | T4: Month | U4: Day | V4: Date | X4: Status | Y4: Flag | AA4: Grade | AC4: Location | AE4: Nationality | AG4: Sponser | AH4: Company | AK4: {=_xlfn.VSTACK(Emp_CON[],Emp_FIN[],Emp_ADM[],Emp_ELE[],Emp_PLM[],Emp_STN[])} -> 1 | AL4: O183 | AM4: 0 | AN4: محمد عمران انصاري | AO4: Muhammad Imran Ansari | AP4: CON_D03 | AR4: 1 | AS4: O183 | AU4: محمد عمران انصاري | AV4: Muhammad Imran Ansari | AW4: =$AV$2 -> CON_D03 | AY4: 1 | AZ4: 243 | BB4: محمد عزيز لاحق | BD4: =$BC$2 -> FIN_D02 | BF4: 1 | BG4: 146 | BI4: ﻣﺎﻣﻮﻥ ﺍﺣﻤﺪ ﺷﻮﻧﻮ ﻣﻴﺎﻩ | BK4: =$BJ$2 -> ADM_D01 | BM4: 1 | BR4: =$BQ$2 -> ELE_D04 | BT4: 1 | BY4: =$BX$2 -> PLM_D05 | CA4: 1 | CF4: =$CE$2 -> STN_D06 | CH4: 1 | CL4: =$CK$2 -> All_D11 | CP4: Absent | CR4: خصم - Deduction | CS4: De_01
B5: 1 | C5: O183 | F5: ﻣﺪ ﺟﻠﺪﻳﻦ ﻣﻴﺎ | G5: =IFERROR(_xlfn.XLOOKUP(Super[[#This Row],[Supervisor_Name]],EmpNames,EmpIDs,"",0),0) | H5: الإدارة | K5: مشرف_موقع | M5: works - يعمل | N5: W_01 | P5: Bank - بنك | Q5: B_0 | S5: 2026 | T5: 1 | U5: =1 -> 1 | V5: =DATE(Month[[#This Row],[Year]],Month[[#This Row],[Month]],Month[[#This Row],[Day]]) -> 46023 | X5: جاري - Active | Y5: Ac_0 | AA5: Manager | AE5: مصري – Egyptian | AG5: كفالة-Sponsership | AK5: 2 | AL5: O287 | AM5: 0 | AN5: علاء الدين مسلمان | AO5: Aladdin Muslim | AP5: CON_D03 | AR5: 2 | AS5: O287 | AU5: علاء الدين مسلمان | AV5: Aladdin Muslim | AW5: =$AV$2 -> CON_D03 | AY5: 2 | AZ5: 389 | BB5: محمد نور نبي | BD5: =$BC$2 -> FIN_D02 | BF5: 2 | BG5: 228 | BI5: ﻣﺎﻣﻮﻥ ﺍﻟﺮﺷﻴﺪ ﻧﻮﺭ ﺍﻟﻘﺎﺩﺭ | BK5: =$BJ$2 -> ADM_D01 | BM5: 2 | BR5: =$BQ$2 -> ELE_D04 | BT5: 2 | BY5: =$BX$2 -> PLM_D05 | CA5: 2 | CF5: =$CE$2 -> STN_D06 | CH5: 2 | CL5: =$CK$2 -> All_D11 | CP5: Friday | CR5: بونص - Bonus | CS5: Bo_01
B6: 2 | C6: O287 | G6: =IFERROR(_xlfn.XLOOKUP(Super[[#This Row],[Supervisor_Name]],EmpNames,EmpIDs,"",0),0) | H6: الإدارة | K6: صباغ | M6: vacation - إجازة | N6: V_01 | P6: cash - نقدا | Q6: C_0 | S6: 2026 | T6: 2 | U6: =1 -> 1 | V6: =DATE(Month[[#This Row],[Year]],Month[[#This Row],[Month]],Month[[#This Row],[Day]]) -> 46054 | X6: مكتمل - Completed | Y6: Co_0 | AA6: Supervisor | AE6: هندي – Indian | AG6: غير كفالة-NoSponsership | AK6: 3 | AL6: O289 | AM6: 0 | AN6: مقصود انصاري | AO6: Maqsood Ansari | AP6: CON_D03 | AR6: 3 | AS6: O289 | AU6: مقصود انصاري | AV6: Maqsood Ansari | AW6: =$AV$2 -> CON_D03 | AY6: 3 | AZ6: 411 | BB6: نور ميستري | BD6: =$BC$2 -> FIN_D02 | BF6: 3 | BG6: 189 | BI6: ﺳﺎﺭﺍﺟﻮﺩﺩﻳﻦ ﺍﻧﺼﺎﺭﻯ | BK6: =$BJ$2 -> ADM_D01 | BM6: 3 | BR6: =$BQ$2 -> ELE_D04 | BT6: 3 | BY6: =$BX$2 -> PLM_D05 | CA6: 3 | CF6: =$CE$2 -> STN_D06 | CH6: 3 | CL6: =$CK$2 -> All_D11 | CP6: Eid | CR6: زيادة - Addition | CS6: Ad_01
B7: 3 | C7: O289 | G7: =IFERROR(_xlfn.XLOOKUP(Super[[#This Row],[Supervisor_Name]],EmpNames,EmpIDs,"",0),0) | H7: الإدارة | K7: سائق | M7: resignation - استقالة | N7: R_01 | P7: Vodafone - فودافون | Q7: V_0 | S7: 2026 | T7: 3 | U7: =1 -> 1 | V7: =DATE(Month[[#This Row],[Year]],Month[[#This Row],[Month]],Month[[#This Row],[Day]]) -> 46082 | X7: متوقف - On Hold | Y7: OH_0 | AA7: Worker | AE7: بنغالي – Bangladeshi | AK7: 4 | AL7: 133 | AM7: 0 | AN7: ﺑﻮﺟﻨﺎﻥ ﻛﻮﺭﻣﺎ | AO7: Bojnan Korma | AP7: CON_D03 | AR7: 4 | AS7: 133 | AU7: ﺑﻮﺟﻨﺎﻥ ﻛﻮﺭﻣﺎ | AV7: Bojnan Korma | AW7: =$AV$2 -> CON_D03 | AY7: 4 | AZ7: 448 | BB7: بابو رام كامي | BD7: =$BC$2 -> FIN_D02 | BF7: 4 | BG7: 314 | BI7: محمد عرلاان | BK7: =$BJ$2 -> ADM_D01 | BM7: 4 | BR7: =$BQ$2 -> ELE_D04 | BT7: 4 | BY7: =$BX$2 -> PLM_D05 | CA7: 4 | CF7: =$CE$2 -> STN_D06 | CH7: 4 | CL7: =$CK$2 -> All_D11
B8: 4 | C8: 133 | G8: =IFERROR(_xlfn.XLOOKUP(Super[[#This Row],[Supervisor_Name]],EmpNames,EmpIDs,"",0),0) | H8: الإدارة | K8: فنى | M8: transfer - نقل | N8: T_01 | S8: 2026 | T8: 4 | U8: =1 -> 1 | V8: =DATE(Month[[#This Row],[Year]],Month[[#This Row],[Month]],Month[[#This Row],[Day]]) -> 46113 | AE8: باكستاني – Pakistani | AK8: 5 | AL8: 318 | AM8: 0 | AN8: ارون كومار ساه | AO8: Arun Kumar Sah | AP8: CON_D03 | AR8: 5 | AS8: 318 | AU8: ارون كومار ساه | AV8: Arun Kumar Sah | AW8: =$AV$2 -> CON_D03 | AY8: 5 | AZ8: 496 | BB8: محمد رفيق ملليك جبار ملليك | BD8: =$BC$2 -> FIN_D02 | BF8: 5 | BG8: 284 | BI8: عبد الرؤف جمعه احمد علي | BK8: =$BJ$2 -> ADM_D01 | BM8: 5 | BR8: =$BQ$2 -> ELE_D04 | BT8: 5 | BY8: =$BX$2 -> PLM_D05 | CA8: 5 | CF8: =$CE$2 -> STN_D06 | CH8: 5 | CL8: =$CK$2 -> All_D11
B9: 5 | C9: 318 | F9: محمد عمران انصاري | G9: =IFERROR(_xlfn.XLOOKUP(Super[[#This Row],[Supervisor_Name]],EmpNames,EmpIDs,"",0),0) -> O183 | H9: الإنشاءات | K9: معلم جبس بورد | M9: Outpatients - مرضى خارجي | N9: O_01 | S9: 2026 | T9: 5 | U9: =1 -> 1 | V9: =DATE(Month[[#This Row],[Year]],Month[[#This Row],[Month]],Month[[#This Row],[Day]]) -> 46143 | AE9: نيبالي – Nepali | AK9: 6 | AL9: 442 | AM9: 0 | AN9: ايمامول انصاري | AO9: Emamol Ansari | AP9: CON_D03 | AR9: 6 | AS9: 442 | AU9: ايمامول انصاري | AV9: Emamol Ansari | AW9: =$AV$2 -> CON_D03 | AY9: 6 | AZ9: 247 | BB9: جمال محمد علي | BD9: =$BC$2 -> FIN_D02 | BF9: 6 | BG9: 440 | BI9: سادكي كوندا | BK9: =$BJ$2 -> ADM_D01 | BM9: 6 | BR9: =$BQ$2 -> ELE_D04 | BT9: 6 | BY9: =$BX$2 -> PLM_D05 | CA9: 6 | CF9: =$CE$2 -> STN_D06 | CH9: 6 | CL9: =$CK$2 -> All_D11
B10: 6 | C10: 442 | G10: =IFERROR(_xlfn.XLOOKUP(Super[[#This Row],[Supervisor_Name]],EmpNames,EmpIDs,"",0),0) | H10: =_xlfn.XLOOKUP(Super[[#This Row],[Supervisor_Name]],EmpNames,EmpDepts,"",0) | K10: فني تشييك | M10: New appointment - تعيين جديد | N10: N_01 | S10: 2026 | T10: 6 | U10: =1 -> 1 | V10: =DATE(Month[[#This Row],[Year]],Month[[#This Row],[Month]],Month[[#This Row],[Day]]) -> 46174 | AE10: فلبيني – Filipino | AK10: 7 | AL10: 113 | AM10: 0 | AN10: ﺟﻮﺟﺎﻧﻨﺪﺍ ﺳﺮﺩﺍﺭ ﺑﺎﺗﺮ | AO10: Jojananda Sardar Patar | AP10: CON_D03 | AR10: 7 | AS10: 113 | AU10: ﺟﻮﺟﺎﻧﻨﺪﺍ ﺳﺮﺩﺍﺭ ﺑﺎﺗﺮ | AV10: Jojananda Sardar Patar | AW10: =$AV$2 -> CON_D03 | AY10: 7 | AZ10: O163 | BB10: عبد الباسي عبد الرحمن اشير | BD10: =$BC$2 -> FIN_D02 | BF10: 7 | BG10: O304 | BI10: صلاح عبدالرحمن الحاج احمد | BK10: =$BJ$2 -> ADM_D01 | BM10: 7 | BR10: =$BQ$2 -> ELE_D04 | BT10: 7 | BY10: =$BX$2 -> PLM_D05 | CA10: 7 | CF10: =$CE$2 -> STN_D06 | CH10: 7 | CL10: =$CK$2 -> All_D11
B11: 7 | C11: 113 | G11: =IFERROR(_xlfn.XLOOKUP(Super[[#This Row],[Supervisor_Name]],EmpNames,EmpIDs,"",0),0) | H11: =_xlfn.XLOOKUP(Super[[#This Row],[Supervisor_Name]],EmpNames,EmpDepts,"",0) | K11: فني جبس | M11: Back to work - عودة للعمل | N11: B_01 | S11: 2026 | T11: 7 | U11: =1 -> 1 | V11: =DATE(Month[[#This Row],[Year]],Month[[#This Row],[Month]],Month[[#This Row],[Day]]) -> 46204 | AE11: سريلانكي – Sri Lankan | AK11: 8 | AL11: 115 | AM11: 0 | AN11: ﺻﺪﺍﻡ ﺣﺴﻴﻦ | AO11: Saddam Hussein | AP11: CON_D03 | AR11: 8 | AS11: 115 | AU11: ﺻﺪﺍﻡ ﺣﺴﻴﻦ | AV11: Saddam Hussein | AW11: =$AV$2 -> CON_D03 | AY11: 8 | AZ11: O187 | BB11: مد موجمل حقي | BD11: =$BC$2 -> FIN_D02 | BF11: 8 | BG11: O143 | BI11: محمد عبد الخان | BK11: =$BJ$2 -> ADM_D01 | BM11: 8 | BR11: =$BQ$2 -> ELE_D04 | BT11: 8 | BY11: =$BX$2 -> PLM_D05 | CA11: 8 | CF11: =$CE$2 -> STN_D06 | CH11: 8 | CL11: =$CK$2 -> All_D11
B12: 8 | C12: 115 | G12: =IFERROR(_xlfn.XLOOKUP(Super[[#This Row],[Supervisor_Name]],EmpNames,EmpIDs,"",0),0) | H12: =_xlfn.XLOOKUP(Super[[#This Row],[Supervisor_Name]],EmpNames,EmpDepts,"",0) | K12: عامل | M12: Termination of services - انهاء خدمات | N12: TS_01 | S12: 2026 | T12: 8 | U12: =1 -> 1 | V12: =DATE(Month[[#This Row],[Year]],Month[[#This Row],[Month]],Month[[#This Row],[Day]]) -> 46235 | AE12: سوداني – Sudanese | AK12: 9 | AL12: 118 | AM12: 0 | AN12: ﻣﺪ ﺟﻠﺪﻳﻦ ﻣﻴﺎ | AO12: Extend two skins, Mia | AP12: CON_D03 | AR12: 9 | AS12: 118 | AU12: ﻣﺪ ﺟﻠﺪﻳﻦ ﻣﻴﺎ | AV12: Extend two skins, Mia | AW12: =$AV$2 -> CON_D03 | AY12: 9 | AZ12: O204 | BB12: محمد ابوبكور محمد حسين | BD12: =$BC$2 -> FIN_D02 | BF12: 9 | BG12: O246 | BI12: أرسلان احمد الطاف حسين | BK12: =$BJ$2 -> ADM_D01 | BM12: 9 | BR12: =$BQ$2 -> ELE_D04 | BT12: 9 | BY12: =$BX$2 -> PLM_D05 | CA12: 9 | CF12: =$CE$2 -> STN_D06 | CH12: 9 | CL12: =$CK$2 -> All_D11
B13: 9 | C13: 118 | G13: =IFERROR(_xlfn.XLOOKUP(Super[[#This Row],[Supervisor_Name]],EmpNames,EmpIDs,"",0),0) | H13: التشطيبات | K13: مساعد صباغ | S13: 2026 | T13: 9 | U13: =1 -> 1 | V13: =DATE(Month[[#This Row],[Year]],Month[[#This Row],[Month]],Month[[#This Row],[Day]]) -> 46266 | AE13: إثيوبي – Ethiopian | AK13: 10 | AL13: 124 | AM13: 0 | AN13: ﻧﺎﺻﺮ ﺣسين | AO13: Nasser Hussein | AP13: CON_D03 | AR13: 10 | AS13: 124 | AU13: ﻧﺎﺻﺮ ﺣسين | AV13: Nasser Hussein | AW13: =$AV$2 -> CON_D03 | AY13: 10 | AZ13: O205 | BB13: محبوب علم تارو مياه | BD13: =$BC$2 -> FIN_D02 | BF13: 10 | BG13: 494 | BI13: منصور عالم مجنو مياه | BK13: =$BJ$2 -> ADM_D01 | BM13: 10 | BR13: =$BQ$2 -> ELE_D04 | BT13: 10 | BY13: =$BX$2 -> PLM_D05 | CA13: 10 | CF13: =$CE$2 -> STN_D06 | CH13: 10 | CL13: =$CK$2 -> All_D11
B14: 10 | C14: 124 | G14: =IFERROR(_xlfn.XLOOKUP(Super[[#This Row],[Supervisor_Name]],EmpNames,EmpIDs,"",0),0) | H14: التشطيبات | K14: عامل مساعد | S14: 2026 | T14: 10 | U14: =1 -> 1 | V14: =DATE(Month[[#This Row],[Year]],Month[[#This Row],[Month]],Month[[#This Row],[Day]]) -> 46296 | AE14: كيني – Kenyan | AK14: 11 | AL14: 178 | AM14: 0 | AN14: ﻟﻴﻞ ﺑﻬﺎﺩﻭﺭ ﺑﻴﺸﻮﻛﺎﺭﻣﺎ | AO14: Lil Bhadur Bishokarma | AP14: CON_D03 | AR14: 11 | AS14: 178 | AU14: ﻟﻴﻞ ﺑﻬﺎﺩﻭﺭ ﺑﻴﺸﻮﻛﺎﺭﻣﺎ | AV14: Lil Bhadur Bishokarma | AW14: =$AV$2 -> CON_D03 | AY14: 11 | AZ14: O207 | BB14: محمد نور الأسلام | BD14: =$BC$2 -> FIN_D02 | BF14: 11 | BG14: 515 | BI14: محمد شفيق محمد اروص | BK14: =$BJ$2 -> ADM_D01 | BM14: 11 | BR14: =$BQ$2 -> ELE_D04 | BT14: 11 | BY14: =$BX$2 -> PLM_D05 | CA14: 11 | CF14: =$CE$2 -> STN_D06 | CH14: 11 | CL14: =$CK$2 -> All_D11
B15: 11 | C15: 178 | G15: =IFERROR(_xlfn.XLOOKUP(Super[[#This Row],[Supervisor_Name]],EmpNames,EmpIDs,"",0),0) | H15: التشطيبات | K15: معلم بلاستر | S15: 2026 | T15: 11 | U15: =1 -> 1 | V15: =DATE(Month[[#This Row],[Year]],Month[[#This Row],[Month]],Month[[#This Row],[Day]]) -> 46327 | AE15: أوغندي – Ugandan | AK15: 12 | AL15: 181 | AM15: 0 | AN15: ﺳﺎﻣﺴﺎﺩ ﺍﻧﺼﺎﺭي | AO15: Samsad Ansari | AP15: CON_D03 | AR15: 12 | AS15: 181 | AU15: ﺳﺎﻣﺴﺎﺩ ﺍﻧﺼﺎﺭي | AV15: Samsad Ansari | AW15: =$AV$2 -> CON_D03 | AY15: 12 | AZ15: O208 | BB15: مد فاروق شايخ | BD15: =$BC$2 -> FIN_D02 | BF15: 12 | BG15: O309 | BI15: محمد أبو محمد حانف | BK15: =$BJ$2 -> ADM_D01 | BM15: 12 | BR15: =$BQ$2 -> ELE_D04 | BT15: 12 | BY15: =$BX$2 -> PLM_D05 | CA15: 12 | CF15: =$CE$2 -> STN_D06 | CH15: 12 | CL15: =$CK$2 -> All_D11
B16: 12 | C16: 181 | G16: =IFERROR(_xlfn.XLOOKUP(Super[[#This Row],[Supervisor_Name]],EmpNames,EmpIDs,"",0),0) | H16: التشطيبات | K16: مساعد بلاستر | S16: 2026 | T16: 12 | U16: =1 -> 1 | V16: =DATE(Month[[#This Row],[Year]],Month[[#This Row],[Month]],Month[[#This Row],[Day]]) -> 46357 | AE16: إندونيسي – Indonesian | AK16: 13 | AL16: 186 | AM16: 0 | AN16: ﺷﺎﻛﻴﻞ ﺑﻜﺎﻟﻪ | AO16: Shakil Bakale | AP16: CON_D03 | AR16: 13 | AS16: 186 | AU16: ﺷﺎﻛﻴﻞ ﺑﻜﺎﻟﻪ | AV16: Shakil Bakale | AW16: =$AV$2 -> CON_D03 | AY16: 13 | AZ16: O316 | BB16: محمد محبوب محمد جيبون ميا | BD16: =$BC$2 -> FIN_D02 | CH16: 13 | CL16: =$CK$2 -> All_D11
B17: 13 | C17: 186 | F17: عمر مصباح عمر | G17: =IFERROR(_xlfn.XLOOKUP(Super[[#This Row],[Supervisor_Name]],EmpNames,EmpIDs,"",0),0) | H17: الكهرباء | K17: معلم تشطيب | S17: 2027 | T17: 1 | U17: =1 -> 1 | V17: =DATE(Month[[#This Row],[Year]],Month[[#This Row],[Month]],Month[[#This Row],[Day]]) -> 46388 | AE17: تايلاندي – Thai | AK17: 14 | AL17: 195 | AM17: 0 | AN17: ﻋﻄﺎﺑﻞ ﺍﻧﺼﺎﺭي | AO17: Atabil Ansari | AP17: CON_D03 | AR17: 14 | AS17: 195 | AU17: ﻋﻄﺎﺑﻞ ﺍﻧﺼﺎﺭي | AV17: Atabil Ansari | AW17: =$AV$2 -> CON_D03 | AY17: 14 | AZ17: O317 | BB17: ال امين حافيج عدين | BD17: =$BC$2 -> FIN_D02
B18: 14 | C18: 195 | G18: =IFERROR(_xlfn.XLOOKUP(Super[[#This Row],[Supervisor_Name]],EmpNames,EmpIDs,"",0),0) | H18: الكهرباء | K18: معلم بلاط | S18: 2027 | T18: 2 | U18: =1 -> 1 | V18: =DATE(Month[[#This Row],[Year]],Month[[#This Row],[Month]],Month[[#This Row],[Day]]) -> 46419 | AE18: فيتنامي – Vietnamese | AK18: 15 | AL18: 201 | AM18: 0 | AN18: ﺣﺴﻴﻦ ﻣﺤﻤﺪ | AO18: Hussein Mohammed | AP18: CON_D03 | AR18: 15 | AS18: 201 | AU18: ﺣﺴﻴﻦ ﻣﺤﻤﺪ | AV18: Hussein Mohammed | AW18: =$AV$2 -> CON_D03 | AY18: 15 | AZ18: o334 | BB18: محمد سيفو تالوكدر | BD18: =$BC$2 -> FIN_D02
B19: 15 | C19: 201 | G19: =IFERROR(_xlfn.XLOOKUP(Super[[#This Row],[Supervisor_Name]],EmpNames,EmpIDs,"",0),0) | H19: الكهرباء | K19: عامل تشطيب | S19: 2027 | T19: 3 | U19: =1 -> 1 | V19: =DATE(Month[[#This Row],[Year]],Month[[#This Row],[Month]],Month[[#This Row],[Day]]) -> 46447 | AE19: صيني – Chinese | AK19: 16 | AL19: 202 | AM19: 0 | AN19: ﻣﻤﺘﺎﺯ ﻣﺎﻳﺎ | AO19: Excellent, Maya | AP19: CON_D03 | AR19: 16 | AS19: 202 | AU19: ﻣﻤﺘﺎﺯ ﻣﺎﻳﺎ | AV19: Excellent, Maya | AW19: =$AV$2 -> CON_D03 | AY19: 16 | AZ19: o335 | BB19: محمد سايمون محمد مومين | BD19: =$BC$2 -> FIN_D02
B20: 16 | C20: 202 | G20: =IFERROR(_xlfn.XLOOKUP(Super[[#This Row],[Supervisor_Name]],EmpNames,EmpIDs,"",0),0) | H20: الكهرباء | K20: ناطور | S20: 2027 | T20: 4 | U20: =1 -> 1 | V20: =DATE(Month[[#This Row],[Year]],Month[[#This Row],[Month]],Month[[#This Row],[Day]]) -> 46478 | AE20: تركي – Turkish | AK20: 17 | AL20: 208 | AM20: 0 | AN20: ﺟﺎﺑﻴﺶ ﺷﺎﺭﻣﺎ ﺷﻴﻔﺠﻲ ﺷﺎﺭﻣﺎ | AO20: Jabesh Sharma Shivji Sharma | AP20: CON_D03 | AR20: 17 | AS20: 208 | AU20: ﺟﺎﺑﻴﺶ ﺷﺎﺭﻣﺎ ﺷﻴﻔﺠﻲ ﺷﺎﺭﻣﺎ | AV20: Jabesh Sharma Shivji Sharma | AW20: =$AV$2 -> CON_D03 | AY20: 17 | AZ20: 134 | BB20: ﻣﺎﺯﻭ ﺍﺣﻤﺪ ﻣﺤﻤﺪ ﺧﺴﺮﺍﻟﺰﻣﺎﻥ ﺳﺎﻱ | BD20: =$BC$2 -> FIN_D02
B21: 17 | C21: 208 | G21: =IFERROR(_xlfn.XLOOKUP(Super[[#This Row],[Supervisor_Name]],EmpNames,EmpIDs,"",0),0) | H21: السباكة | K21: عامل عزل | S21: 2027 | T21: 5 | U21: =1 -> 1 | V21: =DATE(Month[[#This Row],[Year]],Month[[#This Row],[Month]],Month[[#This Row],[Day]]) -> 46508 | AE21: مغربي – Moroccan | AK21: 18 | AL21: 216 | AM21: 0 | AN21: ﺭﺍﺟﻴﺶ ﻛﻮﻣﺎﺭ ﺷﻬﺎﻥ | AO21: Rajesh Kumar Shahan | AP21: CON_D03 | AR21: 18 | AS21: 216 | AU21: ﺭﺍﺟﻴﺶ ﻛﻮﻣﺎﺭ ﺷﻬﺎﻥ | AV21: Rajesh Kumar Shahan | AW21: =$AV$2 -> CON_D03 | AY21: 18 | AZ21: 142 | BB21: ﺑﻴﺸﺎﻥ ﻣﻮﺷﻲ | BD21: =$BC$2 -> FIN_D02
B22: 18 | C22: 216 | G22: =IFERROR(_xlfn.XLOOKUP(Super[[#This Row],[Supervisor_Name]],EmpNames,EmpIDs,"",0),0) | H22: السباكة | K22: فنى بلايستر | S22: 2027 | T22: 6 | U22: =1 -> 1 | V22: =DATE(Month[[#This Row],[Year]],Month[[#This Row],[Month]],Month[[#This Row],[Day]]) -> 46539 | AE22: تونسي – Tunisian | AK22: 19 | AL22: 244 | AM22: 0 | AN22: جمال انصاري | AO22: Jamal Ansari | AP22: CON_D03 | AR22: 19 | AS22: 244 | AU22: جمال انصاري | AV22: Jamal Ansari | AW22: =$AV$2 -> CON_D03 | AY22: 19 | AZ22: 172 | BB22: ﻧﻮﺭ ﺍﺳﻼﻡ ﺣﻨﻴﻒ | BD22: =$BC$2 -> FIN_D02
B23: 19 | C23: 244 | G23: =IFERROR(_xlfn.XLOOKUP(Super[[#This Row],[Supervisor_Name]],EmpNames,EmpIDs,"",0),0) | H23: السباكة | K23: بناء طابوق | S23: 2027 | T23: 7 | U23: =1 -> 1 | V23: =DATE(Month[[#This Row],[Year]],Month[[#This Row],[Month]],Month[[#This Row],[Day]]) -> 46569 | AE23: جزائري – Algerian | AK23: 20 | AL23: 246 | AM23: 0 | AN23: ميراجول انصاري | AO23: Mirajul Ansari | AP23: CON_D03 | AR23: 20 | AS23: 246 | AU23: ميراجول انصاري | AV23: Mirajul Ansari | AW23: =$AV$2 -> CON_D03 | AY23: 20 | AZ23: 192 | BB23: ﻋﺎﺭﻑ ﺣﺴﻴﻦ ﺷﻬﻴﺪﺍﻟﻠﻪ | BD23: =$BC$2 -> FIN_D02
B24: 20 | C24: 246 | G24: =IFERROR(_xlfn.XLOOKUP(Super[[#This Row],[Supervisor_Name]],EmpNames,EmpIDs,"",0),0) | H24: السباكة | K24: مساعد بلاط | S24: 2027 | T24: 8 | U24: =1 -> 1 | V24: =DATE(Month[[#This Row],[Year]],Month[[#This Row],[Month]],Month[[#This Row],[Day]]) -> 46600 | AE24: أردني – Jordanian | AK24: 21 | AL24: 277 | AM24: 0 | AN24: فينود ياداف | AO24: Vinod Yadav | AP24: CON_D03 | AR24: 21 | AS24: 277 | AU24: فينود ياداف | AV24: Vinod Yadav | AW24: =$AV$2 -> CON_D03 | AY24: 21 | AZ24: 309 | BB24: سانجيب كومار ياداز | BD24: =$BC$2 -> FIN_D02
B25: 21 | C25: 277 | G25: =IFERROR(_xlfn.XLOOKUP(Super[[#This Row],[Supervisor_Name]],EmpNames,EmpIDs,"",0),0) | H25: السباكة | K25: فني عزل | S25: 2027 | T25: 9 | U25: =1 -> 1 | V25: =DATE(Month[[#This Row],[Year]],Month[[#This Row],[Month]],Month[[#This Row],[Day]]) -> 46631 | AE25: سوري – Syrian | AK25: 22 | AL25: 373 | AM25: 0 | AN25: الأمير ميان | AO25: Prince Mian | AP25: CON_D03 | AR25: 22 | AS25: 373 | AU25: الأمير ميان | AV25: Prince Mian | AW25: =$AV$2 -> CON_D03 | AY25: 22 | AZ25: 339 | BB25: ازاد صديق | BD25: =$BC$2 -> FIN_D02
B26: 22 | C26: 373 | K26: فني بلاستر | S26: 2027 | T26: 10 | U26: =1 -> 1 | V26: =DATE(Month[[#This Row],[Year]],Month[[#This Row],[Month]],Month[[#This Row],[Day]]) -> 46661 | AE26: لبناني – Lebanese | AK26: 23 | AL26: O162 | AM26: 0 | AN26: يرافن انصاري | AO26: Yaraven Ansari | AP26: CON_D03 | AR26: 23 | AS26: O162 | AU26: يرافن انصاري | AV26: Yaraven Ansari | AW26: =$AV$2 -> CON_D03 | AY26: 23 | AZ26: O186 | BB26: ماجد أحمد جلال الدين | BD26: =$BC$2 -> FIN_D02
B27: 23 | C27: O162 | K27: عامل الثرى دى | S27: 2027 | T27: 11 | U27: =1 -> 1 | V27: =DATE(Month[[#This Row],[Year]],Month[[#This Row],[Month]],Month[[#This Row],[Day]]) -> 46692 | AK27: 24 | AL27: O52 | AM27: 0 | AN27: شميم انصاري | AO27: Shamim Ansari | AP27: CON_D03 | AR27: 24 | AS27: O52 | AU27: شميم انصاري | AV27: Shamim Ansari | AW27: =$AV$2 -> CON_D03 | AY27: 24 | AZ27: O48 | BB27: بنود كومار ساه | BD27: =$BC$2 -> FIN_D02
B28: 24 | C28: O52 | K28: فورمان | S28: 2027 | T28: 12 | U28: =1 -> 1 | V28: =DATE(Month[[#This Row],[Year]],Month[[#This Row],[Month]],Month[[#This Row],[Day]]) -> 46722 | AK28: 25 | AL28: O60 | AM28: 0 | AN28: محمد اكبر صافي | AO28: Muhammad Akbar Safi | AP28: CON_D03 | AR28: 25 | AS28: O60 | AU28: محمد اكبر صافي | AV28: Muhammad Akbar Safi | AW28: =$AV$2 -> CON_D03 | AY28: 25 | AZ28: O227 | BB28: امام حسين محمد اسلام | BD28: =$BC$2 -> FIN_D02
B29: 25 | C29: O60 | K29: سائق بوكت | AK29: 26 | AL29: 121 | AM29: 0 | AN29: ﺍﻟﺠﻴﺐ ﺍﻧﺼﺎﺭي ﻣﺠﻴﺪ ﺍﻧﺼﺎﺭي | AO29: The pocket of Ansari Majid Ansari | AP29: CON_D03 | AR29: 26 | AS29: 121 | AU29: ﺍﻟﺠﻴﺐ ﺍﻧﺼﺎﺭي ﻣﺠﻴﺪ ﺍﻧﺼﺎﺭي | AV29: The pocket of Ansari Majid Ansari | AW29: =$AV$2 -> CON_D03 | AY29: 26 | AZ29: 21 | BB29: ﻣﺎﻟﻚ ﺍﺣﻤﺪ | BD29: =$BC$2 -> FIN_D02
B30: 26 | C30: 121 | K30: كهربائي | AK30: 27 | AL30: 129 | AM30: 0 | AN30: ﻫﺎﺭﻳﻨﺪﺭﺍ ﻣﻮﻛﻬﻴﺎ | AO30: Harendra Mukhiya | AP30: CON_D03 | AR30: 27 | AS30: 129 | AU30: ﻫﺎﺭﻳﻨﺪﺭﺍ ﻣﻮﻛﻬﻴﺎ | AV30: Harendra Mukhiya | AW30: =$AV$2 -> CON_D03 | AY30: 27 | AZ30: 418 | BB30: عبدالعال سعيد مجاهد عبدالعال | BD30: =$BC$2 -> FIN_D02
B31: 27 | C31: 129 | K31: سباك | AK31: 28 | AL31: 127 | AM31: 0 | AN31: ﺷﺎﺗﺮﺩﻫﺎﻥ ﻣﺎﻫﺎﺭﺍ | AO31: Chatardhan Mahara | AP31: CON_D03 | AR31: 28 | AS31: 127 | AU31: ﺷﺎﺗﺮﺩﻫﺎﻥ ﻣﺎﻫﺎﺭﺍ | AV31: Chatardhan Mahara | AW31: =$AV$2 -> CON_D03 | AY31: 28 | AZ31: 443 | BB31: احمد ابراهيم باز عبد الرحيم | BD31: =$BC$2 -> FIN_D02
B32: 28 | C32: 127 | K32: مساعد كهربائي | AK32: 29 | AL32: 138 | AM32: 0 | AN32: ﻛﺎﺟﻞ ﺷﻴﺦ ﺩﺍﻭﺩ ﺷﻴﺦ | AO32: Kajal Sheikh Dawood Sheikh | AP32: CON_D03 | AR32: 29 | AS32: 138 | AU32: ﻛﺎﺟﻞ ﺷﻴﺦ ﺩﺍﻭﺩ ﺷﻴﺦ | AV32: Kajal Sheikh Dawood Sheikh | AW32: =$AV$2 -> CON_D03 | AY32: 29 | AZ32: 530 | BB32: تامر السيد عبد الحميد | BD32: =$BC$2 -> FIN_D02
B33: 29 | C33: 138 | K33: مساعد سباك | AK33: 30 | AL33: 145 | AM33: 0 | AN33: ﺳﺎﺕ ﺑﻞ ﻣﻴﻠﻮ ﺭﺍﻡ | AO33: Sat Bell Milo Ram | AP33: CON_D03 | AR33: 30 | AS33: 145 | AU33: ﺳﺎﺕ ﺑﻞ ﻣﻴﻠﻮ ﺭﺍﻡ | AV33: Sat Bell Milo Ram | AW33: =$AV$2 -> CON_D03 | AY33: 30 | AZ33: 270 | BB33: مسعود صالح قاسمي | BD33: =$BC$2 -> FIN_D02
B34: 30 | C34: 145 | AK34: 31 | AL34: 197 | AM34: 0 | AN34: ﺭﺣﻴﻢ ﺑﺎﺷﺎ ﻗﻄﻮﺑﺪﻱ | AO34: Rahim Pasha Qutubdi | AP34: CON_D03 | AR34: 31 | AS34: 197 | AU34: ﺭﺣﻴﻢ ﺑﺎﺷﺎ ﻗﻄﻮﺑﺪﻱ | AV34: Rahim Pasha Qutubdi | AW34: =$AV$2 -> CON_D03 | AY34: 31 | AZ34: 437 | BB34: نظر الإسلام شاديم علي | BD34: =$BC$2 -> FIN_D02
B35: 31 | C35: 197 | AK35: 32 | AL35: 207 | AM35: 0 | AN35: ﺑﻴﺮﻳﻨﺪﺭﺍ ﻛﻮﻣﺎﺭ ﺑﻮﻫﺎﺭﺍ | AO35: Birendra Kumar Bhohara | AP35: CON_D03 | AR35: 32 | AS35: 207 | AU35: ﺑﻴﺮﻳﻨﺪﺭﺍ ﻛﻮﻣﺎﺭ ﺑﻮﻫﺎﺭﺍ | AV35: Birendra Kumar Bhohara | AW35: =$AV$2 -> CON_D03 | AY35: 32 | AZ35: 441 | BB35: محمد سليم دهالي | BD35: =$BC$2 -> FIN_D02
B36: 32 | C36: 207 | AK36: 33 | AL36: 214 | AM36: 0 | AN36: ﻧﺸﺎﺩ ﻋﺒﺪ ﺣﺴﻴﻦ | AO36: Nashhad Abdel Hussein | AP36: CON_D03 | AR36: 33 | AS36: 214 | AU36: ﻧﺸﺎﺩ ﻋﺒﺪ ﺣﺴﻴﻦ | AV36: Nashhad Abdel Hussein | AW36: =$AV$2 -> CON_D03 | AY36: 33 | AZ36: 493 | BB36: نجم الحسين عامر حسين ديوان | BD36: =$BC$2 -> FIN_D02
B37: 33 | C37: 214 | AK37: 34 | AL37: 302 | AM37: 0 | AN37: ماهندرا ماهارا | AO37: Mahendra Mahara | AP37: CON_D03 | AR37: 34 | AS37: 302 | AU37: ماهندرا ماهارا | AV37: Mahendra Mahara | AW37: =$AV$2 -> CON_D03 | AY37: 34 | AZ37: 279 | BB37: ساوين فقير | BD37: =$BC$2 -> FIN_D02
B38: 34 | C38: 302 | AK38: 35 | AL38: 303 | AM38: 0 | AN38: ايندال يادالا | AO38: Indal Yadala | AP38: CON_D03 | AR38: 35 | AS38: 303 | AU38: ايندال يادالا | AV38: Indal Yadala | AW38: =$AV$2 -> CON_D03 | AY38: 35 | AZ38: o337 | BB38: برويز عالم | BD38: =$BC$2 -> FIN_D02
B39: 35 | C39: 303 | AK39: 36 | AL39: 305 | AM39: 0 | AN39: بركاش باسمان | AO39: Prakash Basman | AP39: CON_D03 | AR39: 36 | AS39: 305 | AU39: بركاش باسمان | AV39: Prakash Basman | AW39: =$AV$2 -> CON_D03 | AY39: 36 | AZ39: 482 | BB39: محمد لال مياه | BD39: =$BC$2 -> FIN_D02
B40: 36 | C40: 305 | AK40: 37 | AL40: 307 | AM40: 0 | AN40: دانيش شودهاري | AO40: Danish Choudhary | AP40: CON_D03 | AR40: 37 | AS40: 307 | AU40: دانيش شودهاري | AV40: Danish Choudhary | AW40: =$AV$2 -> CON_D03 | AY40: 37 | AZ40: 128 | BB40: ﺟﻮﺟﻴﻨﺪﺭﺍ ﺳﺎﺩﺍي | BD40: =$BC$2 -> FIN_D02
B41: 37 | C41: 307 | AK41: 38 | AL41: 308 | AM41: 0 | AN41: لابان انينجوكير | AO41: Laban Aningokir | AP41: CON_D03 | AR41: 38 | AS41: 308 | AU41: لابان انينجوكير | AV41: Laban Aningokir | AW41: =$AV$2 -> CON_D03 | AY41: 38 | AZ41: 290 | BB41: دريسك سيجاوا | BD41: =$BC$2 -> FIN_D02
B42: 38 | C42: 308 | AK42: 39 | AL42: 312 | AM42: 0 | AN42: موهادف موكايا | AO42: Mohadaf Mukaya | AP42: CON_D03 | AR42: 39 | AS42: 312 | AU42: موهادف موكايا | AV42: Mohadaf Mukaya | AW42: =$AV$2 -> CON_D03 | AY42: 39 | AZ42: 322 | BB42: رام بهجان باتار | BD42: =$BC$2 -> FIN_D02
B43: 39 | C43: 312 | AK43: 40 | AL43: 316 | AM43: 0 | AN43: سانتوش كومار ساكور | AO43: Santosh Kumar Sakur | AP43: CON_D03 | AR43: 40 | AS43: 316 | AU43: سانتوش كومار ساكور | AV43: Santosh Kumar Sakur | AW43: =$AV$2 -> CON_D03 | AY43: 40 | AZ43: 325 | BB43: ديل بهادور سونار | BD43: =$BC$2 -> FIN_D02
B44: 40 | C44: 316 | AK44: 41 | AL44: 324 | AM44: 0 | AN44: براديب ماهارا | AO44: Pradeep Mahara | AP44: CON_D03 | AR44: 41 | AS44: 324 | AU44: براديب ماهارا | AV44: Pradeep Mahara | AW44: =$AV$2 -> CON_D03 | AY44: 41 | AZ44: 370 | BB44: مان كومار تامانج | BD44: =$BC$2 -> FIN_D02
B45: 41 | C45: 324 | AK45: 42 | AL45: 336 | AM45: 0 | AN45: سوندار موكهيا | AO45: Sundar Mukhia | AP45: CON_D03 | AR45: 42 | AS45: 336 | AU45: سوندار موكهيا | AV45: Sundar Mukhia | AW45: =$AV$2 -> CON_D03 | AY45: 42 | AZ45: 474 | BB45: محمد رجيب مطلب بيباري | BD45: =$BC$2 -> FIN_D02
B46: 42 | C46: 336 | AK46: 43 | AL46: 337 | AM46: 0 | AN46: سيباش كاتهيت | AO46: Sebash Kathiet | AP46: CON_D03 | AR46: 43 | AS46: 337 | AU46: سيباش كاتهيت | AV46: Sebash Kathiet | AW46: =$AV$2 -> CON_D03 | AY46: 43 | AZ46: 477 | BB46: محمد عبدالأحد | BD46: =$BC$2 -> FIN_D02
B47: 43 | C47: 337 | AK47: 44 | AL47: 348 | AM47: 0 | AN47: اندرجيت سينج | AO47: Anderjit Singh | AP47: CON_D03 | AR47: 44 | AS47: 348 | AU47: اندرجيت سينج | AV47: Anderjit Singh | AW47: =$AV$2 -> CON_D03 | AY47: 44 | AZ47: O106 | BB47: ديدارول اسلام دولا مياح | BD47: =$BC$2 -> FIN_D02
B48: 44 | C48: 348 | AK48: 45 | AL48: 378 | AM48: 0 | AN48: بارويج علم مسلم ميا | AO48: Barwij, Muslim scholar Mia | AP48: CON_D03 | AR48: 45 | AS48: 378 | AU48: بارويج علم مسلم ميا | AV48: Barwij, Muslim scholar Mia | AW48: =$AV$2 -> CON_D03 | AY48: 45 | AZ48: O245 | BB48: محمد عبدور الرحمن | BD48: =$BC$2 -> FIN_D02
B49: 45 | C49: 378 | AK49: 46 | AL49: 386 | AM49: 0 | AN49: مانجيب باسمان | AO49: Manjeeb Basman | AP49: CON_D03 | AR49: 46 | AS49: 386 | AU49: مانجيب باسمان | AV49: Manjeeb Basman | AW49: =$AV$2 -> CON_D03 | AY49: 46 | AZ49: 229 | BB49: ﺍﻻﺟﻴﺎﻩ ﺳﻴﻔﺎﺭﺍﺳﺎ ﻓﺎﺳﺎﻧﺴﺮﺍﺳﺎ | BD49: =$BC$2 -> FIN_D02
B50: 46 | C50: 386 | AK50: 47 | AL50: 387 | AM50: 0 | AN50: رام نيواس قاهر | AO50: Ram Niwas Qahir | AP50: CON_D03 | AR50: 47 | AS50: 387 | AU50: رام نيواس قاهر | AV50: Ram Niwas Qahir | AW50: =$AV$2 -> CON_D03 | AY50: 47 | AZ50: 317 | BB50: ناند كيشور داس | BD50: =$BC$2 -> FIN_D02
B51: 47 | C51: 387 | AK51: 48 | AL51: 388 | AM51: 0 | AN51: كاسندرا ماندال دهانوك | AO51: Cassandra Mandal Dahanock | AP51: CON_D03 | AR51: 48 | AS51: 388 | AU51: كاسندرا ماندال دهانوك | AV51: Cassandra Mandal Dahanock | AW51: =$AV$2 -> CON_D03 | AY51: 48 | AZ51: O308 | BB51: جاسم سيكدار مصطفى سيكدار | BD51: =$BC$2 -> FIN_D02
B52: 48 | C52: 388 | AK52: 49 | AL52: 421 | AM52: 0 | AN52: هيرا لال باسي | AO52: Hera Lal Bassi | AP52: CON_D03 | AR52: 49 | AS52: 421 | AU52: هيرا لال باسي | AV52: Hera Lal Bassi | AW52: =$AV$2 -> CON_D03 | AY52: 49 | AZ52: O312 | BB52: توصيف الاحي ساقب سودهري | BD52: =$BC$2 -> FIN_D02
B53: 49 | C53: 421 | AK53: 50 | AL53: 422 | AM53: 0 | AN53: رام شاندر باسي | AO53: Ram Chander Basi | AP53: CON_D03 | AR53: 50 | AS53: 422 | AU53: رام شاندر باسي | AV53: Ram Chander Basi | AW53: =$AV$2 -> CON_D03 | AY53: 50 | AZ53: O313 | BB53: فهيم احمد محيب الرحمان | BD53: =$BC$2 -> FIN_D02
B54: 50 | C54: 422 | AK54: 51 | AL54: 423 | AM54: 0 | AN54: دهان براساد كركي | AO54: Dahan Prasad Karki | AP54: CON_D03 | AR54: 51 | AS54: 423 | AU54: دهان براساد كركي | AV54: Dahan Prasad Karki | AW54: =$AV$2 -> CON_D03 | AY54: 51 | AZ54: O256 | BB54: خالد احمد منير علي | BD54: =$BC$2 -> FIN_D02
B55: 51 | C55: 423 | AK55: 52 | AL55: 438 | AM55: 0 | AN55: شهادات حسين منير الاسالام | AO55: Hussein Munir Al-Islam Certificates | AP55: CON_D03 | AR55: 52 | AS55: 438 | AU55: شهادات حسين منير الاسالام | AV55: Hussein Munir Al-Islam Certificates | AW55: =$AV$2 -> CON_D03 | AY55: 52 | AZ55: 150 | BB55: ﻧﻮﺭ ﺍﻟﻜﺎﺩﺭ ﺍﺑﻮ ﺍﺣﻤﺪ | BD55: =$BC$2 -> FIN_D02
B56: 52 | C56: 438 | AK56: 53 | AL56: 451 | AM56: 0 | AN56: ابران انصاري | AO56: Ibran Ansari | AP56: CON_D03 | AR56: 53 | AS56: 451 | AU56: ابران انصاري | AV56: Ibran Ansari | AW56: =$AV$2 -> CON_D03 | AY56: 53 | AZ56: 204 | BB56: ﻛﻤﺎﻝ ﻭﺩﻳﻦ | BD56: =$BC$2 -> FIN_D02
B57: 53 | C57: 451 | AK57: 54 | AL57: 486 | AM57: 0 | AN57: راجانا تشيكالا تشيكالا | AO57: Rajana Chikala Chikala | AP57: CON_D03 | AR57: 54 | AS57: 486 | AU57: راجانا تشيكالا تشيكالا | AV57: Rajana Chikala Chikala | AW57: =$AV$2 -> CON_D03 | AY57: 54 | AZ57: 227 | BB57: ﻣﻨﺼﻮﺭ ﻋﻼﺍﻡ | BD57: =$BC$2 -> FIN_D02
B58: 54 | C58: 486 | AK58: 55 | AL58: 487 | AM58: 0 | AN58: كمال انصاري حبيب انصاري | AO58: Kamal Ansari Habib Ansari | AP58: CON_D03 | AR58: 55 | AS58: 487 | AU58: كمال انصاري حبيب انصاري | AV58: Kamal Ansari Habib Ansari | AW58: =$AV$2 -> CON_D03 | AY58: 55 | AZ58: 430 | BB58: نجرول اسلام احمد علي | BD58: =$BC$2 -> FIN_D02
B59: 55 | C59: 487 | AK59: 56 | AL59: 517 | AM59: 0 | AN59: راتنا بهادور ليمبو | AO59: Ratna Bahadur Limbo | AP59: CON_D03 | AR59: 56 | AS59: 517 | AU59: راتنا بهادور ليمبو | AV59: Ratna Bahadur Limbo | AW59: =$AV$2 -> CON_D03 | AY59: 56 | AZ59: 251 | BB59: ﻣﺤﻤﺪ ﻣﺤﻤﻮﺩ ﺣﺎﻣﺪ ﺃﺣﻤﺪ ﺳﻠﻄﺎﻥ | BD59: =$BC$2 -> FIN_D02
B60: 56 | C60: 517 | AK60: 57 | AL60: O201 | AM60: 0 | AN60: محمد ياسين تورب علي | AO60: Mohammed Yassin Torb Ali | AP60: CON_D03 | AR60: 57 | AS60: O201 | AU60: محمد ياسين تورب علي | AV60: Mohammed Yassin Torb Ali | AW60: =$AV$2 -> CON_D03 | AY60: 57 | AZ60: 483 | BB60: ديف ناث ياداف | BD60: =$BC$2 -> FIN_D02
B61: 57 | C61: O201 | AK61: 58 | AL61: O229 | AM61: 0 | AN61: محمد سهيل محمد سليم | AO61: Mohammed Suhail Mohammed Salim | AP61: CON_D03 | AR61: 58 | AS61: O229 | AU61: محمد سهيل محمد سليم | AV61: Mohammed Suhail Mohammed Salim | AW61: =$AV$2 -> CON_D03 | AY61: 58 | AZ61: O124 | BB61: ميتيلا مهاتو | BD61: =$BC$2 -> FIN_D02
B62: 58 | C62: O229 | AK62: 59 | AL62: O231 | AM62: 0 | AN62: محمد عشيقور الرحمن | AO62: Muhammad Ashiqur Rahman | AP62: CON_D03 | AR62: 59 | AS62: O231 | AU62: محمد عشيقور الرحمن | AV62: Muhammad Ashiqur Rahman | AW62: =$AV$2 -> CON_D03 | AY62: 59 | AZ62: O252 | BB62: محمد عاشق الهي كمال الدين | BD62: =$BC$2 -> FIN_D02
B63: 59 | C63: O231 | AK63: 60 | AL63: O263 | AM63: 0 | AN63: سعيد عبدالحافظ محمد عيد | AO63: Saeed Abdul-Hafiz Muhammad Eid | AP63: CON_D03 | AR63: 60 | AS63: O263 | AU63: سعيد عبدالحافظ محمد عيد | AV63: Saeed Abdul-Hafiz Muhammad Eid | AW63: =$AV$2 -> CON_D03 | AY63: 60 | AZ63: 111 | BB63: ﺳﻠﻄﺎﻥ ﺍﺣﻤﺪ ﻣﺤﻴﺐ ﺍﻟﺮﺣﻤﺎﻥ | BD63: =$BC$2 -> FIN_D02
B64: 60 | C64: O263 | AK64: 61 | AL64: O268 | AM64: 0 | AN64: لطفور رحمن مجيبر رحمن | AO64: Latfur Rahman Mujibir Rahman | AP64: CON_D03 | AR64: 61 | AS64: O268 | AU64: لطفور رحمن مجيبر رحمن | AV64: Latfur Rahman Mujibir Rahman | AW64: =$AV$2 -> CON_D03 | AY64: 61 | AZ64: 163 | BB64: ﺷﻬﺎﻥ ﺍﺣﻤﺪ ﺧﺎﻥ | BD64: =$BC$2 -> FIN_D02
B65: 61 | C65: O268 | AK65: 62 | AL65: O276 | AM65: 0 | AN65: محمد عبدل مياه | AO65: Mohammed Abdel Miyah | AP65: CON_D03 | AR65: 62 | AS65: O276 | AU65: محمد عبدل مياه | AV65: Mohammed Abdel Miyah | AW65: =$AV$2 -> CON_D03 | AY65: 62 | AZ65: O212 | BB65: شيام مندال | BD65: =$BC$2 -> FIN_D02
B66: 62 | C66: O276 | AK66: 63 | AL66: O285 | AM66: 0 | AN66: ارساد احمد فقير | AO66: Arsad Ahmed Faqir | AP66: CON_D03 | AR66: 63 | AS66: O285 | AU66: ارساد احمد فقير | AV66: Arsad Ahmed Faqir | AW66: =$AV$2 -> CON_D03 | AY66: 63 | AZ66: O213 | BB66: رنجيت كومار مندل | BD66: =$BC$2 -> FIN_D02
B67: 63 | C67: O285 | AK67: 64 | AL67: O36 | AM67: 0 | AN67: ارشاد انصاري | AO67: Irshad Ansari | AP67: CON_D03 | AR67: 64 | AS67: O36 | AU67: ارشاد انصاري | AV67: Irshad Ansari | AW67: =$AV$2 -> CON_D03 | AY67: 64 | AZ67: O194 | BB67: شفيق الإسلام أحمد علي | BD67: =$BC$2 -> FIN_D02
B68: 64 | C68: O36 | AK68: 65 | AL68: O61 | AM68: 0 | AN68: عبدالحكيم رستم انصاري | AO68: Abdul Hakim Rustam Ansari | AP68: CON_D03 | AR68: 65 | AS68: O61 | AU68: عبدالحكيم رستم انصاري | AV68: Abdul Hakim Rustam Ansari | AW68: =$AV$2 -> CON_D03 | AY68: 65 | AZ68: O310 | BB68: علم أبو طهير شيخ | BD68: =$BC$2 -> FIN_D02
B69: 65 | C69: O61 | AK69: 66 | AL69: 174 | AM69: 0 | AN69: ﺷﻤﺸﻴﺮ ﻋﺎﻟﻢ ﺍﻧﺼﺎﺭﻱ | AO69: Shamsher, Ansari scholar | AP69: CON_D03 | AR69: 66 | AS69: 174 | AU69: ﺷﻤﺸﻴﺮ ﻋﺎﻟﻢ ﺍﻧﺼﺎﺭﻱ | AV69: Shamsher, Ansari scholar | AW69: =$AV$2 -> CON_D03 | AY69: 66 | AZ69: O332 | BB69: شهيد الرحمن مجميل على | BD69: =$BC$2 -> FIN_D02
B70: 66 | C70: 174 | AK70: 67 | AL70: 428 | AM70: 0 | AN70: راشيل باسي | AO70: Rachel Bassey | AP70: CON_D03 | AR70: 67 | AS70: 428 | AU70: راشيل باسي | AV70: Rachel Bassey | AW70: =$AV$2 -> CON_D03 | AY70: 67 | AZ70: 436 | BB70: مرادول اسلام محمد مجنول حق | BD70: =$BC$2 -> FIN_D02
B71: 67 | C71: 428 | AK71: 68 | AL71: O175 | AM71: 0 | AN71: انوار انصاري رحيم انصاري | AO71: Anwar Ansari Rahim Ansari | AP71: CON_D03 | AR71: 68 | AS71: O175 | AU71: انوار انصاري رحيم انصاري | AV71: Anwar Ansari Rahim Ansari | AW71: =$AV$2 -> CON_D03 | AY71: 68 | AZ71: 232 | BB71: ﻋﺒﺪ ﺍﻟﻤﺠﻴﺪ ﺟﻲ | BD71: =$BC$2 -> FIN_D02
B72: 68 | C72: O175 | AK72: 69 | AL72: O180 | AM72: 0 | AN72: جسير انصاري | AO72: Jasser Ansari | AP72: CON_D03 | AR72: 69 | AS72: O180 | AU72: جسير انصاري | AV72: Jasser Ansari | AW72: =$AV$2 -> CON_D03 | AY72: 69 | AZ72: 293 | BB72: سانجاي سينان | BD72: =$BC$2 -> FIN_D02
B73: 69 | C73: O180 | AK73: 70 | AL73: B2 | AM73: 0 | AN73: ميلان ادهيكاري | AO73: Milan Adhikari | AP73: CON_D03 | AR73: 70 | AS73: B2 | AU73: ميلان ادهيكاري | AV73: Milan Adhikari | AW73: =$AV$2 -> CON_D03 | AY73: 70 | AZ73: 330 | BB73: منجات رام باوان كومار | BD73: =$BC$2 -> FIN_D02
B74: 70 | C74: B2 | AK74: 71 | AL74: O133 | AM74: 0 | AN74: فيتسوم كيداني ديستا | AO74: Fitsum Kidani Desta | AP74: CON_D03 | AR74: 71 | AS74: O133 | AU74: فيتسوم كيداني ديستا | AV74: Fitsum Kidani Desta | AW74: =$AV$2 -> CON_D03 | AY74: 71 | AZ74: 439 | BB74: إبراهيم ايمي جمعة نكيما | BD74: =$BC$2 -> FIN_D02
B75: 71 | C75: O133 | AK75: 72 | AL75: 433 | AM75: 0 | AN75: محمد نظام الدين عبد المنان | AO75: Muhammad Nizam al-Din Abd al-Mannan | AP75: CON_D03 | AR75: 72 | AS75: 433 | AU75: محمد نظام الدين عبد المنان | AV75: Muhammad Nizam al-Din Abd al-Mannan | AW75: =$AV$2 -> CON_D03 | AY75: 72 | AZ75: o336 | BB75: جوميل احمد تشودري | BD75: =$BC$2 -> FIN_D02
B76: 72 | C76: 433 | AK76: 73 | AL76: O171 | AM76: 0 | AN76: عماد إبراهيم محمد بعزق | AO76: Emad Ibrahim Mohamed Bazq | AP76: CON_D03 | AR76: 73 | AS76: O171 | AU76: عماد إبراهيم محمد بعزق | AV76: Emad Ibrahim Mohamed Bazq | AW76: =$AV$2 -> CON_D03 | AY76: 73 | AZ76: 321 | BB76: متليش داس | BD76: =$BC$2 -> FIN_D02
B77: 73 | C77: O171 | AK77: 74 | AL77: 164 | AM77: 0 | AN77: ﻇﻔﺮ ﻣﻴﺎﻩ | AO77: Water nail | AP77: CON_D03 | AR77: 74 | AS77: 164 | AU77: ﻇﻔﺮ ﻣﻴﺎﻩ | AV77: Water nail | AW77: =$AV$2 -> CON_D03 | AY77: 74 | AZ77: 452 | BB77: ايمدي رضا ايمدي تسليم | BD77: =$BC$2 -> FIN_D02
B78: 74 | C78: 164 | AK78: 75 | AL78: 224 | AM78: 0 | AN78: ﺟﺎﻫﺮ ﺣﺴﻴﻦ | AO78: Jahar Hussein | AP78: CON_D03 | AR78: 75 | AS78: 224 | AU78: ﺟﺎﻫﺮ ﺣﺴﻴﻦ | AV78: Jahar Hussein | AW78: =$AV$2 -> CON_D03 | AY78: 75 | AZ78: 154 | BB78: ﺭﻳﺤﺎﻝ ﻣﺤﻤﺪ ﺗﺎﻣﺒﻲ ﻏﻔﻮﺭ | BD78: =$BC$2 -> FIN_D02
B79: 75 | C79: 224 | AK79: 76 | AL79: 447 | AM79: 0 | AN79: رام بهادور كاركي | AO79: Ram Bahadur Karki | AP79: CON_D03 | AR79: 76 | AS79: 447 | AU79: رام بهادور كاركي | AV79: Ram Bahadur Karki | AW79: =$AV$2 -> CON_D03 | AY79: 76 | AZ79: 323 | BB79: محمد شاهجاده نور محمد | BD79: =$BC$2 -> FIN_D02
B80: 76 | C80: 447 | AK80: 77 | AL80: 392 | AM80: 0 | AN80: السيد احمد السيد محمد علي | AO80: Mr. Ahmed El-Sayed Mohamed Ali | AP80: CON_D03 | AR80: 77 | AS80: 392 | AU80: السيد احمد السيد محمد علي | AV80: Mr. Ahmed El-Sayed Mohamed Ali | AW80: =$AV$2 -> CON_D03 | AY80: 77 | AZ80: 434 | BB80: نوشاد أنصاري | BD80: =$BC$2 -> FIN_D02
B81: 77 | C81: 392 | AK81: 78 | AL81: 237 | AM81: 0 | AN81: ﺳﺎﻫﺎﺑﻮﺩﻳﻦ ﻣﻴﺎﻩ ﺭﺍكي | AO81: Sahabudin Miyah Raki | AP81: CON_D03 | AR81: 78 | AS81: 237 | AU81: ﺳﺎﻫﺎﺑﻮﺩﻳﻦ ﻣﻴﺎﻩ ﺭﺍكي | AV81: Sahabudin Miyah Raki | AW81: =$AV$2 -> CON_D03 | AY81: 78 | AZ81: 182 | BB81: ﺍﺭﺷﺎﺩ ﻋﻼﺍﻡ | BD81: =$BC$2 -> FIN_D02
B82: 78 | C82: 237 | AK82: 79 | AL82: O138 | AM82: 0 | AN82: محمد غازي إسماعيل | AO82: Mohammed Ghazi Ismail | AP82: CON_D03 | AR82: 79 | AS82: O138 | AU82: محمد غازي إسماعيل | AV82: Mohammed Ghazi Ismail | AW82: =$AV$2 -> CON_D03 | AY82: 79 | AZ82: 107 | BB82: ﺭﺍﻡ ﺍﺷﻴﺶ | BD82: =$BC$2 -> FIN_D02
B83: 79 | C83: O138 | AK83: 80 | AL83: O77 | AM83: 0 | AN83: محمد امجد حسين | AO83: Mohammed Amjad Hussein | AP83: CON_D03 | AR83: 80 | AS83: O77 | AU83: محمد امجد حسين | AV83: Mohammed Amjad Hussein | AW83: =$AV$2 -> CON_D03 | AY83: 80 | AZ83: 198 | BB83: ﺗﻮﺣﻴﺪ ﻣﻴﺎ | BD83: =$BC$2 -> FIN_D02
B84: 80 | C84: O77 | AK84: 81 | AL84: 350 | AM84: 0 | AN84: شاهجاد صديق عباس علي | AO84: Shahjad Sadiq Abbas Ali | AP84: CON_D03 | AR84: 81 | AS84: 350 | AU84: شاهجاد صديق عباس علي | AV84: Shahjad Sadiq Abbas Ali | AW84: =$AV$2 -> CON_D03 | AY84: 81 | AZ84: 226 | BB84: ﺳﻮﻓﻴﺜﺎﻥ ﺳﻴﻨﺎﺛﻮﺭﺍﻱ ﻧﻔﺎﺭﺳﺎ | BD84: =$BC$2 -> FIN_D02
B85: 81 | C85: 350 | AK85: 82 | AL85: 404 | AM85: 0 | AN85: تفضل حسين ولي ميا | AO85: Hussein Wali Mia | AP85: CON_D03 | AR85: 82 | AS85: 404 | AU85: تفضل حسين ولي ميا | AV85: Hussein Wali Mia | AW85: =$AV$2 -> CON_D03 | AY85: 82 | AZ85: 361 | BB85: وسيم احمد عبد المالك | BD85: =$BC$2 -> FIN_D02
B86: 82 | C86: 404 | AK86: 83 | AL86: 405 | AM86: 0 | AN86: اختر ميا علي مياه | AO86: Choose Mia over water | AP86: CON_D03 | AR86: 83 | AS86: 405 | AU86: اختر ميا علي مياه | AV86: Choose Mia over water | AW86: =$AV$2 -> CON_D03 | AY86: 83 | AZ86: 215 | BB86: ﺳﻮﺟﻴﺖ ﻛﻮﻣﺎﺭ ﻳﺎﺩﺍﻑ | BD86: =$BC$2 -> FIN_D02
B87: 83 | C87: 405 | AK87: 84 | AL87: 291 | AM87: 0 | AN87: برودوس مكهاما | AO87: Brodos McHama | AP87: CON_D03 | AR87: 84 | AS87: 291 | AU87: برودوس مكهاما | AV87: Brodos McHama | AW87: =$AV$2 -> CON_D03 | AY87: 84 | AZ87: 239 | BB87: ﺑﺎﺑﻠﻮ ﺑﺎﺭﻛﻼﻩ | BD87: =$BC$2 -> FIN_D02
B88: 84 | C88: 291 | AK88: 85 | AL88: 297 | AM88: 0 | AN88: علي بومبا | AO88: Ali Bomba | AP88: CON_D03 | AR88: 85 | AS88: 297 | AU88: علي بومبا | AV88: Ali Bomba | AW88: =$AV$2 -> CON_D03 | AY88: 85 | AZ88: 191 | BB88: ﺍﺑﻮﻝ ﻛﻼﻡ ﻣﺤﻤﺪ ﺳﻴﺮﺍﺝ | BD88: =$BC$2 -> FIN_D02
B89: 85 | C89: 297 | AK89: 86 | AL89: O303 | AM89: 0 | AN89: سيلو ميكالا ميكالا ملائياه | AO89: Silo Mikala Mikala Malayah | AP89: CON_D03 | AR89: 86 | AS89: O303 | AU89: سيلو ميكالا ميكالا ملائياه | AV89: Silo Mikala Mikala Malayah | AW89: =$AV$2 -> CON_D03 | AY89: 86 | AZ89: 240 | BB89: ﻣﺤﻤﺪ ﺭﻳﺪﻭﻥ ﺩﻭﻻ ﻣﻴﺎ | BD89: =$BC$2 -> FIN_D02
B90: 86 | C90: O303 | AK90: 87 | AL90: 484 | AM90: 0 | AN90: محمد تنجيل حسين | AO90: Muhammad Tanjil Hussein | AP90: CON_D03 | AR90: 87 | AS90: 484 | AU90: محمد تنجيل حسين | AV90: Muhammad Tanjil Hussein | AW90: =$AV$2 -> CON_D03 | AY90: 87 | AZ90: 383 | BB90: بهوان راي | BD90: =$BC$2 -> FIN_D02
B91: 87 | C91: 484 | AK91: 88 | AL91: 412 | AM91: 0 | AN91: اجناس ناداثالاكال | AO91: Genes Nadathalakal | AP91: CON_D03 | AR91: 88 | AS91: 412 | AU91: اجناس ناداثالاكال | AV91: Genes Nadathalakal | AW91: =$AV$2 -> CON_D03 | AY91: 88 | AZ91: 156 | BB91: ﻓﺎﻧﻮﺩ ﻛﻮﻣﺎﺭ | BD91: =$BC$2 -> FIN_D02
B92: 88 | C92: 412 | AK92: 89 | AL92: O306 | AM92: 0 | AN92: محمد نزام عرفان علي | AO92: Muhammad Nizam Irfan Ali | AP92: CON_D03 | AR92: 89 | AS92: O306 | AU92: محمد نزام عرفان علي | AV92: Muhammad Nizam Irfan Ali | AW92: =$AV$2 -> CON_D03 | AY92: 89 | AZ92: O249 | BB92: جلال عبدالمؤمن برهان مصطفى | BD92: =$BC$2 -> FIN_D02
B93: 89 | C93: O306 | AK93: 90 | AL93: 109 | AM93: 0 | AN93: شاكر بهارو بودها | AO93: Shakir Bharu Budha | AP93: CON_D03 | AR93: 90 | AS93: 109 | AU93: شاكر بهارو بودها | AV93: Shakir Bharu Budha | AW93: =$AV$2 -> CON_D03 | AY93: 90 | AZ93: O193 | BB93: محمد صويب | BD93: =$BC$2 -> FIN_D02
B94: 90 | C94: 109 | AK94: 91 | AL94: 125 | AM94: 0 | AN94: ﻓﻴﺼﻞ ﺟﻤﻴﻞ ﺳﻠﻴﻤﺎﻥ ﻟﻴﺒﻲ | AO94: Faisal Jamil Suleiman Libi | AP94: CON_D03 | AR94: 91 | AS94: 125 | AU94: ﻓﻴﺼﻞ ﺟﻤﻴﻞ ﺳﻠﻴﻤﺎﻥ ﻟﻴﺒﻲ | AV94: Faisal Jamil Suleiman Libi | AW94: =$AV$2 -> CON_D03 | AY94: 91 | AZ94: O197 | BB94: محمد ارمان | BD94: =$BC$2 -> FIN_D02
B95: 91 | C95: 125 | AK95: 92 | AL95: 152 | AM95: 0 | AN95: ﺟﻮﺩﻭ ﺍﻧﺼﺎﺭﻱ | AO95: Godot Ansari | AP95: CON_D03 | AR95: 92 | AS95: 152 | AU95: ﺟﻮﺩﻭ ﺍﻧﺼﺎﺭﻱ | AV95: Godot Ansari | AW95: =$AV$2 -> CON_D03 | AY95: 92 | AZ95: 199 | BB95: ﻧﺎﻧﺪﺍﻥ ﺷﻮﻫﺎﻥ | BD95: =$BC$2 -> FIN_D02
B96: 92 | C96: 152 | AK96: 93 | AL96: 168 | AM96: 0 | AN96: ﺻﺎﺑﺮ ﻣﻴﺎﻩ ﺿﺎﻫﻴﺮﻱ | AO96: Saber Miyah Dhahiri | AP96: CON_D03 | AR96: 93 | AS96: 168 | AU96: ﺻﺎﺑﺮ ﻣﻴﺎﻩ ﺿﺎﻫﻴﺮﻱ | AV96: Saber Miyah Dhahiri | AW96: =$AV$2 -> CON_D03 | AY96: 93 | AZ96: 407 | BB96: دلشاد احمد وحيد احمد | BD96: =$BC$2 -> FIN_D02
B97: 93 | C97: 168 | AK97: 94 | AL97: 299 | AM97: 0 | AN97: جانيز زيموانجاز | AO97: Janice Zimuangaz | AP97: CON_D03 | AR97: 94 | AS97: 299 | AU97: جانيز زيموانجاز | AV97: Janice Zimuangaz | AW97: =$AV$2 -> CON_D03 | AY97: 94 | AZ97: 114 | BB97: ﻫﺎﺟﺮﺍﺕ ﺟﺎﻫﻮﺭ ﻣﻴﺎ | BD97: =$BC$2 -> FIN_D02
B98: 94 | C98: 299 | AK98: 95 | AL98: 384 | AM98: 0 | AN98: بير بهادور بيستا | AO98: Bir Bahadur Bista | AP98: CON_D03 | AR98: 95 | AS98: 384 | AU98: بير بهادور بيستا | AV98: Bir Bahadur Bista | AW98: =$AV$2 -> CON_D03 | AY98: 95 | AZ98: 218 | BB98: ﺃﻧﺼﺎﺭ ﺃﻻﻡ | BD98: =$BC$2 -> FIN_D02
B99: 95 | C99: 384 | AK99: 96 | AL99: 431 | AM99: 0 | AN99: رام موخايا | AO99: Ram Mukhaya | AP99: CON_D03 | AR99: 96 | AS99: 431 | AU99: رام موخايا | AV99: Ram Mukhaya | AW99: =$AV$2 -> CON_D03 | AY99: 96 | AZ99: 342 | BB99: شاه نجار | BD99: =$BC$2 -> FIN_D02
B100: 96 | C100: 431 | AK100: 97 | AL100: 488 | AM100: 0 | AN100: اشيش موخيا | AO100: Ashish Mukhia | AP100: CON_D03 | AR100: 97 | AS100: 488 | AU100: اشيش موخيا | AV100: Ashish Mukhia | AW100: =$AV$2 -> CON_D03 | AY100: 97 | AZ100: 223 | BB100: كولاب ميان | BD100: =$BC$2 -> FIN_D02
...
